01_barrel_shifter/barrel_shifter.v
`include "mux2.v"

module barrel_shifter
#(
    parameter   BW_DATA         = 8,
    parameter   BW_CTRL         = 3
)
(   
    output      [BW_DATA-1:0]           o_y,
    input       [BW_DATA-1:0]           i_a,
    input       [BW_CTRL-1:0]           i_k,    // rotate amount
    input                               i_left  // rotate direction (1:left , 0:right)
);

    wire        [BW_DATA-1:0]           stage[BW_CTRL:0]; // stage[p][q] : q-th 'x' from left of p-th row
    
    genvar i, j;
    generate 
        for (i=0; i<=BW_CTRL; i=i+1) begin
            for (j=0; j<BW_DATA; j=j+1) begin
                mux2 
                u_mux2(
                    .o_data         (stage[i][j]                                                                    ),
                    .i_data0        (i==0       ? i_a[j]               : stage[i-1][j]                              ),
                    .i_data1        (i==0       ? i_a[(j+1) % BW_DATA] : stage[i-1][(j+2**(BW_CTRL-i)) % BW_DATA]   ),
                    .i_sel          (i==0       ? i_left               : i_left^i_k[BW_CTRL-i]                      )
                );
            end
        end
    endgenerate
    
    assign o_y = stage[BW_CTRL];
endmodule
    
module barrel_shifter_beh
#(  
    parameter   BW_DATA         = 8,
    parameter   BW_CTRL         = 3
)
(   
    output      [BW_DATA-1:0]           o_y,
    input       [BW_DATA-1:0]           i_a,
    input       [BW_CTRL-1:0]           i_k,    // rotate amount
    input                               i_left  // rotate direction (1:left , 0:right)
);
    assign o_y = i_left ?   (i_a << i_k) | (i_a >> (BW_DATA-i_k)) :
                            (i_a >> i_k) | (i_a << (BW_DATA-i_k));
endmodule

01_barrel_shifter/mux2.v
module mux2
(
	output						o_data,
	input						i_data0,
	input						i_data1,
	input						i_sel
);

	assign o_data = i_sel ? i_data1 : i_data0;

endmodule

01_barrel_shifter/barrel_shifter_tb.v
// --------------------------------------------------
//	Define Global Variables
// --------------------------------------------------
`define	CLKFREQ		100					// Clock Freq. (Unit: MHz)
`define	SIMCYCLE	30					// Sim. Cycles
`define BW_DATA		8					// Bitwidth of data
`define BW_CTRL		$clog2(`BW_DATA)	// Bitwidth of rotate amount

// --------------------------------------------------
//	Includes
// --------------------------------------------------
`include	"barrel_shifter.v"

module barrel_shifter_tb;
// --------------------------------------------------
//	DUT Signals & Instantiate
// --------------------------------------------------
	wire 	[`BW_DATA-1:0]				o_y;
	wire 	[`BW_DATA-1:0]				o_y_beh;
	reg		[`BW_DATA-1:0]				i_a;
	reg		[`BW_CTRL-1:0]				i_k;    
	reg									i_left; 

	barrel_shifter
	#(
		.BW_DATA			(`BW_DATA			),
		.BW_CTRL			(`BW_CTRL			)
	)
	u_barrel_shifter(
		.o_y				(o_y				),
		.i_a				(i_a				),
		.i_k				(i_k				),
		.i_left				(i_left				)
	);

	barrel_shifter_beh
	#(
		.BW_DATA			(`BW_DATA			),
		.BW_CTRL			(`BW_CTRL			)
	)
	u_barrel_shifter_beh(
		.o_y				(o_y_beh			),
		.i_a				(i_a				),
		.i_k				(i_k				),
		.i_left				(i_left				)
	);
// --------------------------------------------------
//	Tasks
// --------------------------------------------------
	integer	err;

	task init;
		begin
			err					= 0;
			i_a					= 0;
			i_k					= 0;
			i_left				= 0;
		end
	endtask

// --------------------------------------------------
//	Test Stimulus
// --------------------------------------------------
	integer	i, j;
	initial begin
		init();
		for (i = 0; i < `SIMCYCLE; i=i+1) begin
			i_a		= $urandom;
			i_k		= i % `BW_DATA;
			i_left	= $urandom;
			#(1000/`CLKFREQ);
		end
		if (err==0) begin
			$display("No error occurred.");
		end
		$finish;
	end

	always #(1000/`CLKFREQ) begin
		if (o_y != o_y_beh) begin
			$display("ERROR at time %t", $time);
			err=err+1;
		end
	end
// --------------------------------------------------
//	Dump VCD
// --------------------------------------------------
	reg	[8*32-1:0]	vcd_file;
	initial begin
		if ($value$plusargs("vcd_file=%s", vcd_file)) begin
			$dumpfile(vcd_file);
			$dumpvars;
			for (j=0; j<=`BW_CTRL; j++) begin
				$dumpvars(0, u_barrel_shifter.stage[i]);
			end
		end else begin
			$dumpfile("barrel_shifter_tb.vcd");
			$dumpvars;
		end
	end

endmodule

01_barrel_shifter/vcd/barrel_shifter.vcd
$date
	Wed Jul  3 13:57:15 2024
$end
$version
	Icarus Verilog
$end
$timescale
	1s
$end
$scope module barrel_shifter_tb $end
$var wire 8 ! o_y_beh [7:0] $end
$var wire 8 " o_y [7:0] $end
$var reg 8 # i_a [7:0] $end
$var reg 3 $ i_k [2:0] $end
$var reg 1 % i_left $end
$var reg 256 & vcd_file [255:0] $end
$var integer 32 ' err [31:0] $end
$var integer 32 ( i [31:0] $end
$var integer 32 ) j [31:0] $end
$scope module u_barrel_shifter $end
$var wire 8 * i_a [7:0] $end
$var wire 3 + i_k [2:0] $end
$var wire 1 % i_left $end
$var wire 8 , o_y [7:0] $end
$scope begin genblk1[0] $end
$scope begin genblk2[0] $end
$scope module u_mux2 $end
$var wire 1 - i_data0 $end
$var wire 1 . i_data1 $end
$var wire 1 % i_sel $end
$var wire 1 / o_data $end
$upscope $end
$upscope $end
$scope begin genblk2[1] $end
$scope module u_mux2 $end
$var wire 1 0 i_data0 $end
$var wire 1 1 i_data1 $end
$var wire 1 % i_sel $end
$var wire 1 2 o_data $end
$upscope $end
$upscope $end
$scope begin genblk2[2] $end
$scope module u_mux2 $end
$var wire 1 3 i_data0 $end
$var wire 1 4 i_data1 $end
$var wire 1 % i_sel $end
$var wire 1 5 o_data $end
$upscope $end
$upscope $end
$scope begin genblk2[3] $end
$scope module u_mux2 $end
$var wire 1 6 i_data0 $end
$var wire 1 7 i_data1 $end
$var wire 1 % i_sel $end
$var wire 1 8 o_data $end
$upscope $end
$upscope $end
$scope begin genblk2[4] $end
$scope module u_mux2 $end
$var wire 1 9 i_data0 $end
$var wire 1 : i_data1 $end
$var wire 1 % i_sel $end
$var wire 1 ; o_data $end
$upscope $end
$upscope $end
$scope begin genblk2[5] $end
$scope module u_mux2 $end
$var wire 1 < i_data0 $end
$var wire 1 = i_data1 $end
$var wire 1 % i_sel $end
$var wire 1 > o_data $end
$upscope $end
$upscope $end
$scope begin genblk2[6] $end
$scope module u_mux2 $end
$var wire 1 ? i_data0 $end
$var wire 1 @ i_data1 $end
$var wire 1 % i_sel $end
$var wire 1 A o_data $end
$upscope $end
$upscope $end
$scope begin genblk2[7] $end
$scope module u_mux2 $end
$var wire 1 B i_data0 $end
$var wire 1 C i_data1 $end
$var wire 1 % i_sel $end
$var wire 1 D o_data $end
$upscope $end
$upscope $end
$upscope $end
$scope begin genblk1[1] $end
$scope begin genblk2[0] $end
$scope module u_mux2 $end
$var wire 1 E i_data0 $end
$var wire 1 F i_data1 $end
$var wire 1 G i_sel $end
$var wire 1 H o_data $end
$upscope $end
$upscope $end
$scope begin genblk2[1] $end
$scope module u_mux2 $end
$var wire 1 I i_data0 $end
$var wire 1 J i_data1 $end
$var wire 1 K i_sel $end
$var wire 1 L o_data $end
$upscope $end
$upscope $end
$scope begin genblk2[2] $end
$scope module u_mux2 $end
$var wire 1 M i_data0 $end
$var wire 1 N i_data1 $end
$var wire 1 O i_sel $end
$var wire 1 P o_data $end
$upscope $end
$upscope $end
$scope begin genblk2[3] $end
$scope module u_mux2 $end
$var wire 1 Q i_data0 $end
$var wire 1 R i_data1 $end
$var wire 1 S i_sel $end
$var wire 1 T o_data $end
$upscope $end
$upscope $end
$scope begin genblk2[4] $end
$scope module u_mux2 $end
$var wire 1 U i_data0 $end
$var wire 1 V i_data1 $end
$var wire 1 W i_sel $end
$var wire 1 X o_data $end
$upscope $end
$upscope $end
$scope begin genblk2[5] $end
$scope module u_mux2 $end
$var wire 1 Y i_data0 $end
$var wire 1 Z i_data1 $end
$var wire 1 [ i_sel $end
$var wire 1 \ o_data $end
$upscope $end
$upscope $end
$scope begin genblk2[6] $end
$scope module u_mux2 $end
$var wire 1 ] i_data0 $end
$var wire 1 ^ i_data1 $end
$var wire 1 _ i_sel $end
$var wire 1 ` o_data $end
$upscope $end
$upscope $end
$scope begin genblk2[7] $end
$scope module u_mux2 $end
$var wire 1 a i_data0 $end
$var wire 1 b i_data1 $end
$var wire 1 c i_sel $end
$var wire 1 d o_data $end
$upscope $end
$upscope $end
$upscope $end
$scope begin genblk1[2] $end
$scope begin genblk2[0] $end
$scope module u_mux2 $end
$var wire 1 e i_data0 $end
$var wire 1 f i_data1 $end
$var wire 1 g i_sel $end
$var wire 1 h o_data $end
$upscope $end
$upscope $end
$scope begin genblk2[1] $end
$scope module u_mux2 $end
$var wire 1 i i_data0 $end
$var wire 1 j i_data1 $end
$var wire 1 k i_sel $end
$var wire 1 l o_data $end
$upscope $end
$upscope $end
$scope begin genblk2[2] $end
$scope module u_mux2 $end
$var wire 1 m i_data0 $end
$var wire 1 n i_data1 $end
$var wire 1 o i_sel $end
$var wire 1 p o_data $end
$upscope $end
$upscope $end
$scope begin genblk2[3] $end
$scope module u_mux2 $end
$var wire 1 q i_data0 $end
$var wire 1 r i_data1 $end
$var wire 1 s i_sel $end
$var wire 1 t o_data $end
$upscope $end
$upscope $end
$scope begin genblk2[4] $end
$scope module u_mux2 $end
$var wire 1 u i_data0 $end
$var wire 1 v i_data1 $end
$var wire 1 w i_sel $end
$var wire 1 x o_data $end
$upscope $end
$upscope $end
$scope begin genblk2[5] $end
$scope module u_mux2 $end
$var wire 1 y i_data0 $end
$var wire 1 z i_data1 $end
$var wire 1 { i_sel $end
$var wire 1 | o_data $end
$upscope $end
$upscope $end
$scope begin genblk2[6] $end
$scope module u_mux2 $end
$var wire 1 } i_data0 $end
$var wire 1 ~ i_data1 $end
$var wire 1 !" i_sel $end
$var wire 1 "" o_data $end
$upscope $end
$upscope $end
$scope begin genblk2[7] $end
$scope module u_mux2 $end
$var wire 1 #" i_data0 $end
$var wire 1 $" i_data1 $end
$var wire 1 %" i_sel $end
$var wire 1 &" o_data $end
$upscope $end
$upscope $end
$upscope $end
$scope begin genblk1[3] $end
$scope begin genblk2[0] $end
$scope module u_mux2 $end
$var wire 1 '" i_data0 $end
$var wire 1 (" i_data1 $end
$var wire 1 )" i_sel $end
$var wire 1 *" o_data $end
$upscope $end
$upscope $end
$scope begin genblk2[1] $end
$scope module u_mux2 $end
$var wire 1 +" i_data0 $end
$var wire 1 ," i_data1 $end
$var wire 1 -" i_sel $end
$var wire 1 ." o_data $end
$upscope $end
$upscope $end
$scope begin genblk2[2] $end
$scope module u_mux2 $end
$var wire 1 /" i_data0 $end
$var wire 1 0" i_data1 $end
$var wire 1 1" i_sel $end
$var wire 1 2" o_data $end
$upscope $end
$upscope $end
$scope begin genblk2[3] $end
$scope module u_mux2 $end
$var wire 1 3" i_data0 $end
$var wire 1 4" i_data1 $end
$var wire 1 5" i_sel $end
$var wire 1 6" o_data $end
$upscope $end
$upscope $end
$scope begin genblk2[4] $end
$scope module u_mux2 $end
$var wire 1 7" i_data0 $end
$var wire 1 8" i_data1 $end
$var wire 1 9" i_sel $end
$var wire 1 :" o_data $end
$upscope $end
$upscope $end
$scope begin genblk2[5] $end
$scope module u_mux2 $end
$var wire 1 ;" i_data0 $end
$var wire 1 <" i_data1 $end
$var wire 1 =" i_sel $end
$var wire 1 >" o_data $end
$upscope $end
$upscope $end
$scope begin genblk2[6] $end
$scope module u_mux2 $end
$var wire 1 ?" i_data0 $end
$var wire 1 @" i_data1 $end
$var wire 1 A" i_sel $end
$var wire 1 B" o_data $end
$upscope $end
$upscope $end
$scope begin genblk2[7] $end
$scope module u_mux2 $end
$var wire 1 C" i_data0 $end
$var wire 1 D" i_data1 $end
$var wire 1 E" i_sel $end
$var wire 1 F" o_data $end
$upscope $end
$upscope $end
$upscope $end
$upscope $end
$scope module u_barrel_shifter_beh $end
$var wire 8 G" i_a [7:0] $end
$var wire 3 H" i_k [2:0] $end
$var wire 1 % i_left $end
$var wire 8 I" o_y [7:0] $end
$upscope $end
$scope task init $end
$upscope $end
$upscope $end
$scope module barrel_shifter_tb $end
$scope module u_barrel_shifter $end
$var reg 8 J" \stage[0] [7:0] $end
$upscope $end
$upscope $end
$enddefinitions $end
#0
$dumpvars
b10010 J"
b100100 I"
b0 H"
b100100 G"
0F"
1E"
0D"
0C"
0B"
1A"
0@"
1?"
1>"
1="
1<"
0;"
0:"
19"
08"
07"
06"
15"
04"
13"
12"
11"
10"
0/"
0."
1-"
0,"
0+"
0*"
1)"
0("
0'"
0&"
1%"
0$"
0#"
1""
1!"
1~
0}
0|
1{
0z
1y
0x
1w
0v
0u
1t
1s
1r
0q
0p
1o
0n
0m
0l
1k
0j
0i
0h
1g
0f
1e
0d
1c
0b
0a
0`
1_
0^
0]
1\
1[
1Z
0Y
0X
1W
0V
1U
0T
1S
0R
0Q
0P
1O
0N
0M
0L
1K
0J
1I
1H
1G
1F
0E
0D
0C
0B
0A
0@
0?
0>
0=
1<
1;
1:
09
08
07
06
05
04
13
12
11
00
0/
0.
0-
b100100 ,
b0 +
b100100 *
b100 )
b0 (
b0 '
b1011100010111101110110011000110110010000101111011000100110000101110010011100100110010101101100010111110111001101101000011010010110011001110100011001010111001000101110011101100110001101100100 &
1%
b0 $
b100100 #
b100100 "
b100100 !
$end
#10
1:"
1."
00"
03"
14"
17"
0<"
0?"
1("
1+"
0t
1x
0""
1l
0r
0y
1v
1}
0e
0~
1j
1q
0\
1`
0H
1T
02"
06"
0>"
b10010 "
b10010 ,
0B"
0I
0Z
1M
1^
0F
0U
1R
1a
0)"
0-"
01"
05"
09"
0="
0A"
0E"
02
15
0;
b10000100 J"
1D
b10010 !
b10010 I"
1-
01
03
14
16
0:
0<
1C
b1 $
b1 +
b1 H"
b1001 #
b1001 *
b1001 G"
b1 (
#20
18"
1;"
1|
12"
1>"
1r
1y
0("
0+"
10"
13"
04"
07"
1<"
1?"
1\
0l
1t
0x
1""
0*"
0."
06"
b110100 "
b110100 ,
1:"
1I
1Z
0g
0k
0o
0s
0w
0{
0!"
0%"
1)"
1-"
11"
15"
19"
1="
1A"
1E"
b10000110 J"
12
b110100 !
b110100 I"
11
13
b10 $
b10 +
b10 H"
b1101 #
b1101 *
b1101 G"
b10 (
#30
0B"
1F"
12"
0@"
0C"
1'"
1D"
10"
13"
1e
1~
0&"
1h
1t
0*"
16"
0:"
b10101100 "
b10101100 ,
1>"
1H
0i
0$"
1f
1m
0j
0q
1r
1y
1v
1}
0z
0#"
0("
0+"
14"
17"
08"
0;"
1<"
1?"
1E
1V
0I
0Z
1J
1Y
1N
1]
0R
0a
0L
1P
0T
1\
1`
0d
0l
1x
0|
1""
1/
02
1>
1A
b1100101 J"
0D
0G
0K
0O
0S
0W
0[
0_
0c
1g
1k
1o
1s
1w
1{
1!"
1%"
b10101100 !
b10101100 I"
04
06
1:
1<
1=
1?
0%
b11 $
b11 +
b11 H"
b1100101 #
b1100101 *
b1100101 G"
b11 (
#40
0>"
0F"
02"
06"
b10000 "
b10000 ,
1:"
0<"
0?"
0'"
0D"
00"
03"
04"
07"
18"
1;"
0""
0h
0t
0x
1|
0e
0~
0f
0m
0r
0y
0v
0}
1z
1#"
0H
0P
0\
0`
1d
0E
0V
0M
0^
0J
0Y
0N
0]
1R
1a
0/
05
0>
0A
b10000000 J"
1D
b10000 !
b10000 I"
01
03
0:
0<
0=
0?
1%
b100 $
b100 +
b100 H"
b1 #
b1 *
b1 G"
b100 (
#50
1B"
1F"
1."
12"
16"
1<"
1?"
1@"
1C"
1("
1+"
1,"
1/"
10"
13"
08"
0;"
1""
1&"
1l
1p
1t
0|
1e
1~
1i
1$"
1j
1q
1n
1u
1r
1y
0z
0#"
1H
1L
1T
1X
1\
0d
0:"
b11001110 "
b11001110 ,
0>"
1E
1V
1I
1Z
1Q
1b
1F
1U
1J
1Y
0R
0a
0)"
0-"
01"
05"
09"
0="
0A"
0E"
1/
12
18
1;
1>
b111011 J"
0D
b11001110 !
b11001110 I"
0-
1.
10
11
13
17
19
1:
1<
1=
1?
0C
b101 $
b101 +
b101 H"
b1110110 #
b1110110 *
b1110110 G"
b101 (
#60
06"
1:"
0B"
1*"
00"
03"
14"
17"
0<"
0?"
1'"
1D"
1."
b10110111 "
b10110111 ,
1>"
0t
1x
0""
1h
1("
1+"
18"
1;"
0r
0y
1v
1}
0e
0~
1f
1m
1l
1|
0\
1`
0H
1P
1j
1q
1z
1#"
0I
0Z
1M
1^
0F
0U
1N
1]
1R
1a
1T
1d
02
15
0;
1A
b11101101 J"
1D
1G
1K
1O
1S
1W
1[
1_
1c
b10110111 !
b10110111 I"
1-
0.
00
14
16
07
09
1@
1B
1C
0%
b110 $
b110 +
b110 H"
b11101101 #
b11101101 *
b11101101 G"
b110 (
#70
04"
07"
1<"
1?"
0x
1""
0v
0}
1e
1~
0`
1H
02"
06"
1>"
b11110011 "
b11110011 ,
1B"
0M
0^
1F
1U
1)"
1-"
11"
15"
19"
1="
1A"
1E"
05
b11111001 J"
1;
b11110011 !
b11110011 I"
01
03
17
19
b111 $
b111 +
b111 H"
b11111001 #
b11111001 *
b11111001 G"
b111 (
#80
0."
0("
0+"
0l
06"
0>"
1B"
0i
0$"
0j
0q
0n
0u
1v
1}
00"
03"
04"
07"
08"
0;"
1<"
1?"
0L
0T
0X
1`
0t
0x
0|
1""
12"
b11000101 "
b11000101 ,
0:"
1M
1^
0Q
0b
0F
0U
0J
0Y
0G
0K
0O
0S
0W
0[
0_
0c
0g
0k
0o
0s
0w
0{
0!"
0%"
0)"
0-"
01"
05"
09"
0="
0A"
0E"
15
08
0;
b11000101 J"
0>
b11000101 !
b11000101 I"
11
13
04
06
07
09
0:
0<
b0 $
b0 +
b0 H"
b11000101 #
b11000101 *
b11000101 G"
b1000 (
#90
16"
10"
13"
1B"
1."
1t
1<"
1?"
1("
1+"
1r
1y
0v
0}
1i
1$"
1""
1l
02"
0:"
0>"
b11001011 "
b11001011 ,
1F"
1\
0`
1L
1e
1~
1j
1q
0n
0u
0z
0#"
0,"
0/"
04"
07"
08"
0;"
1@"
1C"
0E
0V
1I
1Z
0M
0^
1F
1U
1J
1Y
1H
1T
0X
0d
0p
0x
0|
1&"
0/
12
05
1;
b11110010 J"
1>
1G
1K
1O
1S
1W
1[
1_
1c
1g
1k
1o
1s
1w
1{
1!"
1%"
b11001011 !
b11001011 I"
1:
1<
1%
b1 $
b1 +
b1 H"
b11100101 #
b11100101 *
b11100101 G"
b1001 (
#100
0F"
0*"
14"
17"
0'"
0D"
0("
0+"
00"
03"
1x
0h
0l
0t
0:"
1B"
1n
1u
0r
0y
1z
1#"
0e
0~
0i
0$"
0f
0m
0j
0q
0,"
0/"
08"
0;"
0<"
0?"
1@"
1C"
1X
0\
1d
0H
0L
0P
0T
0p
0|
0""
1&"
0."
02"
16"
b1001000 "
b1001000 ,
0>"
1E
1V
0I
0Z
1Q
1b
0F
0U
0J
0Y
0N
0]
0R
0a
0g
0k
0o
0s
0w
0{
0!"
0%"
1)"
1-"
11"
15"
19"
1="
1A"
1E"
1/
02
18
0;
0>
0A
b1001 J"
0D
b1001000 !
b1001000 I"
0-
1.
10
01
03
17
19
0:
0<
0=
0?
0@
0B
0C
b10 $
b10 +
b10 H"
b10010 #
b10010 *
b10010 G"
b1010 (
#110
12"
10"
13"
0>"
0*"
1t
0<"
0?"
0("
0+"
1i
1$"
1r
1y
1v
1}
0""
0l
1."
16"
1:"
b1011110 "
b1011110 ,
1B"
1L
1\
1`
0e
0~
0j
0q
1n
1u
1z
1#"
1,"
1/"
14"
17"
18"
1;"
1@"
1C"
0E
0V
1I
1Z
0Q
0b
1F
1U
1J
1Y
1N
1]
1R
1a
0H
0T
1X
1d
1p
1x
1|
1&"
0/
12
08
1;
1>
1A
b11110010 J"
1D
0G
0K
0O
0S
0W
0[
0_
0c
1g
1k
1o
1s
1w
1{
1!"
1%"
b1011110 !
b1011110 I"
1:
1<
1=
1?
1@
1B
0%
b11 $
b11 +
b11 H"
b11110010 #
b11110010 *
b11110010 G"
b1011 (
#120
0B"
1F"
b10001110 "
b10001110 ,
0:"
0@"
0C"
1'"
1D"
08"
0;"
0&"
1h
0|
0i
0$"
1f
1m
0z
0#"
0L
1P
0d
0I
0Z
1M
1^
0R
0a
02
15
b1110100 J"
0D
b10001110 !
b10001110 I"
0.
00
14
16
07
09
1%
b100 $
b100 +
b100 H"
b11101000 #
b11101000 *
b11101000 G"
b1100 (
#130
02"
1@"
1C"
1("
1+"
0,"
0/"
04"
07"
1&"
1l
0p
0x
1i
1$"
1j
1q
0n
0u
0v
0}
1L
1T
0X
0`
1*"
1."
0:"
b10001011 "
b10001011 ,
1F"
1I
1Z
1Q
1b
0F
0U
0N
0]
0)"
0-"
01"
05"
09"
0="
0A"
0E"
12
18
0;
b101110 J"
0A
b10001011 !
b10001011 I"
11
13
17
19
0:
0<
0@
0B
b101 $
b101 +
b101 H"
b1011100 #
b1011100 *
b1011100 G"
b1101 (
#140
00"
03"
14"
17"
0t
1x
0F"
0:"
0j
0q
1n
1u
0r
0y
1z
1#"
0'"
0D"
1,"
1/"
08"
0;"
1@"
1C"
0T
1X
0\
1d
0h
1p
0|
1&"
1."
02"
16"
b1001011 "
b1001011 ,
1B"
0Q
0b
1F
1U
0J
0Y
1R
1a
0g
0k
0o
0s
0w
0{
0!"
0%"
1)"
1-"
11"
15"
19"
1="
1A"
1E"
08
1;
0>
b10010110 J"
1D
b1001011 !
b1001011 I"
1-
07
09
1:
1<
0=
0?
1C
b110 $
b110 +
b110 H"
b101101 #
b101101 *
b101101 G"
b1110 (
#150
0>"
1B"
1."
12"
0<"
0?"
1@"
1C"
1,"
1/"
10"
13"
0""
1&"
1p
1t
1F"
0*"
06"
b11000110 "
b11000110 ,
0:"
0e
0~
1i
1$"
1f
1m
0j
0q
1n
1u
1r
1y
0v
0}
0z
0#"
1'"
1D"
0("
0+"
04"
07"
08"
0;"
1E
1V
0M
0^
0F
0U
1J
1Y
1N
1]
0R
0a
0H
1L
1P
0T
1X
1\
0`
0d
1h
0l
0x
0|
1/
05
0;
1>
1A
b1100011 J"
0D
1G
1K
1O
1S
1W
1[
1_
1c
1g
1k
1o
1s
1w
1{
1!"
1%"
b11000110 !
b11000110 I"
1.
10
01
03
04
06
1=
1?
0%
b111 $
b111 +
b111 H"
b1100011 #
b1100011 *
b1100011 G"
b1111 (
#160
02"
0,"
0/"
0p
0:"
0>"
1F"
0i
0$"
0f
0m
0n
0u
0r
0y
1z
1#"
0'"
0D"
0("
0+"
00"
03"
04"
07"
08"
0;"
1@"
1C"
0L
0P
0X
0\
1d
0h
0l
0t
0x
0|
1&"
0*"
0."
06"
b10000000 "
b10000000 ,
0B"
0E
0V
0I
0Z
0J
0Y
0N
0]
1R
1a
0G
0K
0O
0S
0W
0[
0_
0c
0g
0k
0o
0s
0w
0{
0!"
0%"
0)"
0-"
01"
05"
09"
0="
0A"
0E"
0/
02
0>
0A
b10000000 J"
1D
b10000000 !
b10000000 I"
0-
0.
00
0:
0<
0=
0?
1@
1B
0C
b0 $
b0 +
b0 H"
b10000000 #
b10000000 *
b10000000 G"
b10000 (
#170
12"
1:"
1B"
1*"
1,"
1/"
14"
17"
1<"
1?"
1'"
1D"
0."
1p
1x
1""
1h
0("
0+"
1n
1u
1v
1}
1e
1~
1f
1m
0l
0>"
b1010101 "
b1010101 ,
0F"
1X
1`
1H
1P
0j
0q
0z
0#"
08"
0;"
0@"
0C"
1E
1V
1M
1^
1F
1U
1N
1]
0R
0a
0T
0d
0|
0&"
1/
15
1;
1A
b1010101 J"
0D
1G
1K
1O
1S
1W
1[
1_
1c
1g
1k
1o
1s
1w
1{
1!"
1%"
b1010101 !
b1010101 I"
1.
10
14
16
1:
1<
1%
b1 $
b1 +
b1 H"
b10101010 #
b10101010 *
b10101010 G"
b10001 (
#180
18"
1;"
0<"
0?"
1@"
1C"
0'"
0D"
1|
0""
1&"
0h
1r
1y
0v
0}
1z
1#"
0e
0~
1\
0`
1d
0H
0*"
1."
02"
16"
1:"
0>"
1B"
b1011010 "
b1011010 ,
0F"
1I
1Z
0M
0^
1Q
1b
0F
0U
0g
0k
0o
0s
0w
0{
0!"
0%"
1)"
1-"
11"
15"
19"
1="
1A"
1E"
12
05
18
b1001011 J"
0;
b1011010 !
b1011010 I"
11
13
04
06
17
19
0:
0<
b10 $
b10 +
b10 H"
b10010110 #
b10010110 *
b10010110 G"
b10010 (
#190
0:"
04"
07"
1<"
1?"
0@"
0C"
0,"
0/"
10"
13"
0x
1""
0&"
0p
1t
0n
0u
1v
1}
0z
0#"
0f
0m
1j
1q
0X
1`
0d
0P
1T
0."
02"
16"
1>"
1B"
b1101000 "
b1101000 ,
0F"
0E
0V
1M
1^
0Q
0b
0N
0]
1R
1a
0)"
0-"
01"
05"
09"
0="
0A"
0E"
0/
15
08
0A
b10000110 J"
1D
b1101000 !
b1101000 I"
1-
0.
00
14
16
07
09
0@
0B
1C
b11 $
b11 +
b11 H"
b1101 #
b1101 *
b1101 G"
b10011 (
#200
1F"
1."
1'"
1D"
1,"
1/"
1h
1p
0*"
1>"
1e
1~
1f
1m
0j
0q
1n
1u
0v
0}
1z
1#"
0("
0+"
04"
07"
18"
1;"
1<"
1?"
1H
1P
0T
1X
0`
1d
0l
0x
1|
1""
12"
06"
1:"
b10110110 "
b10110110 ,
0B"
1E
1V
0I
0Z
1F
1U
1J
1Y
0G
0K
0O
0S
0W
0[
0_
0c
1g
1k
1o
1s
1w
1{
1!"
1%"
1)"
1-"
11"
15"
19"
1="
1A"
1E"
1/
02
1;
b10110101 J"
1>
b10110110 !
b10110110 I"
1.
10
01
03
1:
1<
1=
1?
b100 $
b100 +
b100 H"
b1101011 #
b1101011 *
b1101011 G"
b10100 (
#210
0F"
0'"
0D"
0*"
0."
1:"
0h
0("
0+"
0,"
0/"
18"
1;"
0n
0u
0e
0~
0l
0p
1|
02"
06"
0>"
b10000 "
b10000 ,
0B"
0X
0H
0i
0$"
0f
0m
0j
0q
1r
1y
0v
0}
0z
0#"
00"
03"
04"
07"
0<"
0?"
0@"
0C"
0E
0V
1I
1Z
0M
0^
0F
0U
0J
0Y
0R
0a
0L
0P
0T
1\
0`
0d
0t
0x
0""
0&"
0/
12
05
0;
0>
b10 J"
0D
1G
1K
1O
1S
1W
1[
1_
1c
0g
0k
0o
0s
0w
0{
0!"
0%"
b10000 !
b10000 I"
0-
04
06
0:
0<
0=
0?
0C
0%
b101 $
b101 +
b101 H"
b10 #
b10 *
b10 G"
b10101 (
#220
1."
12"
1B"
1,"
1/"
10"
13"
1@"
1C"
1*"
b1000111 "
b1000111 ,
0:"
1p
1t
1&"
1("
1+"
08"
0;"
1f
1m
1j
1q
1z
1#"
1l
0|
1P
1T
1d
1i
1$"
0r
0y
1M
1^
1Q
1b
1R
1a
1L
0\
15
18
b10001110 J"
1D
0G
0K
0O
0S
0W
0[
0_
0c
b1000111 !
b1000111 I"
1-
0.
00
11
13
14
16
17
19
1C
1%
b110 $
b110 +
b110 H"
b11101 #
b11101 *
b11101 G"
b10110 (
#230
0*"
0("
0+"
1B"
06"
0l
1@"
1C"
04"
07"
1n
1u
0z
0#"
0j
0q
1&"
0x
0F"
1."
12"
b1000110 "
b1000110 ,
0:"
1X
0d
0T
1i
1$"
0f
0m
1r
1y
0v
0}
0'"
0D"
1,"
1/"
10"
13"
08"
0;"
1E
1V
0M
0^
0Q
0b
1J
1Y
0R
0a
1L
0P
1\
0`
0h
1p
1t
0|
1/
05
08
1>
b100011 J"
0D
1G
1K
1O
1S
1W
1[
1_
1c
1g
1k
1o
1s
1w
1{
1!"
1%"
b1000110 !
b1000110 I"
1.
10
01
03
04
06
07
09
1:
1<
0%
b111 $
b111 +
b111 H"
b100011 #
b100011 *
b100011 G"
b10111 (
#240
1<"
1?"
1""
02"
0:"
0>"
1j
1q
0n
0u
0r
0y
1v
1}
1z
1#"
1("
1+"
0,"
0/"
10"
13"
04"
07"
08"
0;"
1@"
1C"
1T
0X
0\
1`
1d
1l
0p
1t
0x
0|
1&"
1."
16"
1B"
b11001010 "
b11001010 ,
1F"
0E
0V
1Q
1b
0J
0Y
1N
1]
1R
1a
0G
0K
0O
0S
0W
0[
0_
0c
0g
0k
0o
0s
0w
0{
0!"
0%"
0)"
0-"
01"
05"
09"
0="
0A"
0E"
0/
18
0>
1A
b11001010 J"
1D
b11001010 !
b11001010 I"
0-
14
16
0:
0<
1=
1?
1@
1B
0C
b0 $
b0 +
b0 H"
b11001010 #
b11001010 *
b11001010 G"
b11000 (
#250
1:"
00"
03"
14"
17"
18"
1;"
0t
1x
1|
0j
0q
1n
1u
1r
1y
0T
1X
1\
1*"
0."
02"
16"
1>"
b1111001 "
b1111001 ,
0F"
0Q
0b
1F
1U
1J
1Y
1)"
1-"
11"
15"
19"
1="
1A"
1E"
08
1;
b11110010 J"
1>
b1111001 !
b1111001 I"
04
06
17
19
1:
1<
b1 $
b1 +
b1 H"
b11110010 #
b11110010 *
b11110010 G"
b11001 (
#260
0>"
0@"
0C"
08"
0;"
0&"
0|
02"
1B"
1e
1~
0i
0$"
0n
0u
0r
0y
0z
0#"
0("
0+"
0,"
0/"
00"
03"
1<"
1?"
1H
0L
0X
0\
0d
0l
0p
0t
1""
0*"
0."
06"
b1010000 "
b1010000 ,
0F"
1E
1V
0I
0Z
0F
0U
0J
0Y
0R
0a
1g
1k
1o
1s
1w
1{
1!"
1%"
0)"
0-"
01"
05"
09"
0="
0A"
0E"
1/
02
0;
0>
b1000001 J"
0D
b1010000 !
b1010000 I"
1-
0.
00
07
09
0:
0<
0@
0B
1C
b10 $
b10 +
b10 H"
b1000001 #
b1000001 *
b1000001 G"
b11010 (
