02_alu/alu.v
// module alu
// #(	
// 	parameter	N			= 32
// )
// (	
// 	output reg	[N-1:0]		o_y,
// 	output 					o_c,
// 	input		[N-1:0]		i_a,
// 	input		[N-1:0]		i_b,
// 	input		[2:0]		i_f
// );
// 	wire		[N-1:0]		bmux = i_f[2] ? ~i_b : i_b;
// 	wire		[N-1:0]		sum_a_bmux;
// 
// 	assign {o_c, sum_a_bmux} = i_a + bmux + i_f[2];
// 	
// 	always @(*) begin
// 		case (i_f[1:0])
// 			2'b00 : o_y = i_a & bmux;
// 			2'b01 : o_y = i_a | bmux;
// 			2'b10 : o_y = sum_a_bmux;
// 			2'b11 : o_y = {{(N-1){1'b0}}, sum_a_bmux[N-1]};
// 		endcase
// 	end
// endmodule

module alu
#(	
	parameter	N			= 32
)
(	
	output reg signed	[N-1:0]		o_y,
	output	 						o_c,
	output							o_ovf,
	input signed		[N-1:0]		i_a,
	input signed 		[N-1:0]		i_b,
	input 				[2:0]		i_f
);

	wire signed			[N-1:0]		sum;
	wire							ovf_add	=	(i_f == 3'b010) &&
												((~i_a[N-1] && ~i_b[N-1] && sum[N-1]) || (i_a[N-1] && i_b[N-1] && ~sum[N-1]));
	wire							ovf_sub =	(i_f == 3'b110) && 
												((~i_a[N-1] && i_b[N-1] && sum[N-1]) || (i_a[N-1] && ~i_b[N-1] && ~sum[N-1]));

	assign o_ovf = ovf_add || ovf_sub;	
	assign {o_c, sum} = i_f[2] ? i_a-i_b : i_a+i_b;

	always @(*) begin
		case (i_f)
			3'b000	: o_y = i_a & i_b;
			3'b001	: o_y = i_a | i_b;
			3'b010	: o_y = sum;
			3'b100	: o_y = i_a & ~i_b;
			3'b101	: o_y = i_a | ~i_b;
			3'b110	: o_y = sum;
			3'b111	: o_y = i_a < i_b;
			default : o_y = 'd0;
		endcase
	end
endmodule

02_alu/alu_tb.v
// --------------------------------------------------
//	Define Global Variables
// --------------------------------------------------
`define	CLKFREQ		100		// Clock Freq. (Unit: MHz)
`define	SIMCYCLE	100		// Sim. Cycles
`define N			32		// Bitwidth of data

// --------------------------------------------------
//	Includes
// --------------------------------------------------
`include	"alu.v"

module alu_tb;
// --------------------------------------------------
//	DUT Signals & Instantiate
// --------------------------------------------------
	wire	[`N-1:0]	o_y;
	wire				o_c;
	wire				o_ovf;
	reg		[`N-1:0]	i_a;
	reg		[`N-1:0]	i_b;
	reg		[2:0]		i_f;

	alu
	#(
		.N			(`N			)
	)
	u_alu_beh(
		.o_y				(o_y				),
		.o_c				(o_c				),
		.o_ovf				(o_ovf				),
		.i_a				(i_a				),
		.i_b				(i_b				),
		.i_f				(i_f				)
	);


// --------------------------------------------------
//	Tasks
// --------------------------------------------------
	reg		[4*32-1:0]	operation;

	task init;
		begin
			i_a				= 0;
			i_b				= 0;
			i_f				= 0;
		end
	endtask

	task perform_operation;
		input	[2:0]		ti_f;
		input	[`N-1:0]	ti_a;
		input	[`N-1:0]	ti_b;
		begin
			#(1000/`CLKFREQ);
			i_a	= ti_a;
			i_b	= ti_b;
			i_f	= ti_f;
		end
	endtask

// --------------------------------------------------
//	Test Stimulus
// --------------------------------------------------
	integer i, fn;

	initial begin
		init();
		i	= 0;
		fn	= 0;
		while(i < `SIMCYCLE) begin
			if (fn%8 == 7) begin
				perform_operation(
					fn,
					$urandom,
					$urandom
				);	
				i=i+1;
			end
			fn=fn+1;
		end
		#(1000/`CLKFREQ);
		$finish;
	end
	always @(*) begin
		case (i_f)
			3'b000	: operation = "AND";
			3'b001	: operation = "OR";
			3'b010	: operation = "ADD";
			3'b100	: operation = "AND_N";
			3'b101	: operation = "OR_N";
			3'b110	: operation = "SUB";
			3'b111	: operation = "SLT";
			default	: operation = "NOT_USED";
		endcase
	end

// --------------------------------------------------
//	Dump VCD
// --------------------------------------------------
	reg	[8*32-1:0]	vcd_file;
	initial begin
		if ($value$plusargs("vcd_file=%s", vcd_file)) begin
			$dumpfile(vcd_file);
			$dumpvars;
		end else begin
			$dumpfile("alu_tb.vcd");
			$dumpvars;
		end
	end

endmodule

02_alu/vcd/alu.vcd
$date
	Tue Jul  2 17:22:38 2024
$end
$version
	Icarus Verilog
$end
$timescale
	1s
$end
$scope module alu_tb $end
$var wire 32 ! o_y [31:0] $end
$var wire 1 " o_ovf $end
$var wire 1 # o_c $end
$var reg 32 $ i_a [31:0] $end
$var reg 32 % i_b [31:0] $end
$var reg 3 & i_f [2:0] $end
$var reg 128 ' operation [127:0] $end
$var reg 256 ( vcd_file [255:0] $end
$var integer 32 ) fn [31:0] $end
$var integer 32 * i [31:0] $end
$scope module u_alu_beh $end
$var wire 32 + i_a [31:0] $end
$var wire 32 , i_b [31:0] $end
$var wire 3 - i_f [2:0] $end
$var wire 1 " o_ovf $end
$var wire 1 . ovf_add $end
$var wire 1 / ovf_sub $end
$var wire 32 0 sum [31:0] $end
$var wire 1 # o_c $end
$var reg 32 1 o_y [31:0] $end
$upscope $end
$scope task init $end
$upscope $end
$scope task perform_operation $end
$var reg 32 2 ti_a [31:0] $end
$var reg 32 3 ti_b [31:0] $end
$var reg 3 4 ti_f [2:0] $end
$upscope $end
$upscope $end
$enddefinitions $end
#0
$dumpvars
b111 4
b1000000100010010101111010000001 3
b10010010000101010011010100100100 2
b0 1
b0 0
0/
0.
b0 -
b0 ,
b0 +
b0 *
b111 )
b101110001011110111011001100011011001000010111101100001011011000111010100101110011101100110001101100100 (
b10000010100111001000100 '
b0 &
b0 %
b0 $
0#
0"
b0 !
$end
#10
b1010001100010111101011010100011 0
1#
b10100110100110001010100 '
b1 !
b1 1
b110001111100000101011001100011 3
b100100001001101011000001001 2
b1111 )
b1 *
b111 &
b111 -
b1000000100010010101111010000001 %
b1000000100010010101111010000001 ,
b10010010000101010011010100100100 $
b10010010000101010011010100100100 +
#20
b11010010100101000111111110100110 0
b11000110110111111001100110001101 3
b10000110101110010111101100001101 2
b10111 )
b10 *
b110001111100000101011001100011 %
b110001111100000101011001100011 ,
b100100001001101011000001001 $
b100100001001101011000001001 +
#30
b10111111110110011110000110000000 0
b1001001101110101001000010010 3
b110010110000101000010001100101 2
b11111 )
b11 *
b11000110110111111001100110001101 %
b11000110110111111001100110001101 ,
b10000110101110010111101100001101 $
b10000110101110010111101100001101 +
#40
b101001100010110011001001010011 0
0#
b0 !
b0 1
b10000110110101111100110100001101 3
b10000000111100111110001100000001 2
b100111 )
b100 *
b1001001101110101001000010010 %
b1001001101110101001000010010 ,
b110010110000101000010001100101 $
b110010110000101000010001100101 +
#50
b11111010000111000001010111110100 0
1#
b1 !
b1 1
b10011110100011011100110100111101 3
b10111011001000111111000101110110 2
b101111 )
b101 *
b10000110110101111100110100001101 %
b10000110110101111100110100001101 ,
b10000000111100111110001100000001 $
b10000000111100111110001100000001 +
#60
b11100100101100010010000111001 0
0#
b0 !
b0 1
b11000110001011011111011110001100 3
b11110110110101000101011111101101 2
b110111 )
b110 *
b10011110100011011100110100111101 %
b10011110100011011100110100111101 ,
b10111011001000111111000101110110 $
b10111011001000111111000101110110 +
#70
b110000101001100110000001100001 0
b1100011001101110010010011000110 3
b11111100111111011110100111111001 2
b111111 )
b111 *
b11000110001011011111011110001100 %
b11000110001011011111011110001100 ,
b11110110110101000101011111101101 $
b11110110110101000101011111101101 +
#80
b10011001110001101100010100110011 0
1#
b1 !
b1 1
b1010101000100111101001010101010 3
b1100010111101111000010011000101 2
b1000111 )
b1000 *
b1100011001101110010010011000110 %
b1100011001101110010010011000110 ,
b11111100111111011110100111111001 $
b11111100111111011110100111111001 +
#90
b1101111000111011001000011011 0
0#
b0 !
b0 1
b111011110100100111001001110111 3
b11110010101011111111011111100101 2
b1001111 )
b1001 *
b1010101000100111101001010101010 %
b1010101000100111101001010101010 ,
b1100010111101111000010011000101 $
b1100010111101111000010011000101 +
#100
b10110110110111011000010101101110 0
1#
b1 !
b1 1
b11000111111011001101101110001111 3
b1001001100101101011000010010 2
b1010111 )
b1010 *
b111011110100100111001001110111 %
b111011110100100111001001110111 ,
b11110010101011111111011111100101 $
b11110010101011111111011111100101 +
#110
b1000001010001011111101010000011 0
0#
b0 !
b0 1
b1100111011101101001011011001110 3
b11111001001100000110100111110010 2
b1011111 )
b1011 *
b11000111111011001101101110001111 %
b11000111111011001101101110001111 ,
b1001001100101101011000010010 $
b1001001100101101011000010010 +
#120
b10010001101110011101001100100100 0
1#
b1 !
b1 1
b1100010110010100100111011000101 3
b1110100000000000111101011101000 2
b1100111 )
b1100 *
b1100111011101101001011011001110 %
b1100111011101101001011011001110 ,
b11111001001100000110100111110010 $
b11111001001100000110100111110010 +
#130
b10001001101100010110000100011 0
0#
b0 !
b0 1
b1011110100011100010100010111101 3
b10101110010110000100100101011100 2
b1101111 )
b1101 *
b1100010110010100100111011000101 %
b1100010110010100100111011000101 ,
b1110100000000000111101011101000 $
b1110100000000000111101011101000 +
#140
b1001111110010100010000010011111 0
1#
b1 !
b1 1
b110010101001110010011001100101 3
b10110101010110101100000101101 2
b1110111 )
b1110 *
b1011110100011100010100010111101 %
b1011110100011100010100010111101 ,
b10101110010110000100100101011100 $
b10101110010110000100100101011100 +
#150
b11100100000001000011000111001000 0
b10000101011100111000011100001010 3
b110001111011110110001001100011 2
b1111111 )
b1111 *
b110010101001110010011001100101 %
b110010101001110010011001100101 ,
b10110101010110101100000101101 $
b10110101010110101100000101101 +
#160
b10101100011110111101101101011001 0
0#
b0 !
b0 1
b10010000011001000010000100100000 3
b1000000001110110010001010000000 2
b10000111 )
b10000 *
b10000101011100111000011100001010 %
b10000101011100111000011100001010 ,
b110001111011110110001001100011 $
b110001111011110110001001100011 +
#170
b10101111110101110000000101100000 0
b1001110110011001100110010011101 3
b11010101011110000100010110101010 2
b10001111 )
b10001 *
b10010000011001000010000100100000 %
b10010000011001000010000100100000 ,
b1000000001110110010001010000000 $
b1000000001110110010001010000000 +
#180
b10000110101010110111100100001101 0
1#
b1 !
b1 1
b1001100000111011100000010011 3
b1001011001000000011111010010110 2
b10010111 )
b10010 *
b1001110110011001100110010011101 %
b1001110110011001100110010011101 ,
b11010101011110000100010110101010 $
b11010101011110000100010110101010 +
#190
b1000001100111001000011010000011 0
0#
b0 !
b0 1
b101001101001111101011001010011 3
b110101111000011100000001101 2
b10011111 )
b10011 *
b1001100000111011100000010011 %
b1001100000111011100000010011 ,
b1001011001000000011111010010110 $
b1001011001000000011111010010110 +
#200
b11011101000101000110000110111010 0
1#
b1 !
b1 1
b1101010101001100010101011010101 3
b10110101100111111101110101101011 2
b10100111 )
b10100 *
b101001101001111101011001010011 %
b101001101001111101011001010011 ,
b110101111000011100000001101 $
b110101111000011100000001101 +
#210
b1001010111110011011001010010110 0
b1010111010101100011111010101110 3
b1000101110100101000000010 2
b10101111 )
b10101 *
b1101010101001100010101011010101 %
b1101010101001100010101011010101 ,
b10110101100111111101110101101011 $
b10110101100111111101110101101011 +
#220
b10101001110000010000101101010100 0
b1100111110001010111001011001111 3
b10001110111111111110100100011101 2
b10110111 )
b10110 *
b1010111010101100011111010101110 %
b1010111010101100011111010101110 ,
b1000101110100101000000010 $
b1000101110100101000000010 +
#230
b100111001110100111011001001110 0
b10000101000010010110010100001010 3
b10010001100001000100100100100011 2
b10111111 )
b10111 *
b1100111110001010111001011001111 %
b1100111110001010111001011001111 ,
b10001110111111111110100100011101 $
b10001110111111111110100100011101 +
#240
b1100011110101110010000011001 0
0#
b0 !
b0 1
b11110001100010100110000111100 3
b1100101011100110000101011001010 2
b11000111 )
b11000 *
b10000101000010010110010100001010 %
b10000101000010010110010100001010 ,
b10010001100001000100100100100011 $
b10010001100001000100100100100011 +
#250
b1000111010000011011111010001110 0
b11000101001011100110000110001010 3
b11111001011010001011110111110010 2
b11001111 )
b11001 *
b11110001100010100110000111100 %
b11110001100010100110000111100 ,
b1100101011100110000101011001010 $
b1100101011100110000101011001010 +
#260
b110100001110100101110001101000 0
b1101100010010110011010011011000 3
b10100000110001001011001101000001 2
b11010111 )
b11010 *
b11000101001011100110000110001010 %
b11000101001011100110000110001010 ,
b11111001011010001011110111110010 $
b11111001011010001011110111110010 +
#270
b110100011110010111111001101001 0
1#
b1 !
b1 1
b1000100100010100001001010001001 3
b10111100001000001111001101111000 2
b11011111 )
b11011 *
b1101100010010110011010011011000 %
b1101100010010110011010011011000 ,
b10100000110001001011001101000001 $
b10100000110001001011001101000001 +
#280
b1110111100101101110000011101111 0
b11011011000000100110010110110110 3
b11110101110001010000110111101011 2
b11100111 )
b11100 *
b1000100100010100001001010001001 %
b1000100100010100001001010001001 ,
b10111100001000001111001101111000 $
b10111100001000001111001101111000 +
#290
b11010110000101010100000110101 0
0#
b0 !
b0 1
b11010111000101010001001110101110 3
b11100011010010111111100111000110 2
b11101111 )
b11101 *
b11011011000000100110010110110110 %
b11011011000000100110010110110110 ,
b11110101110001010000110111101011 $
b11110101110001010000110111101011 +
#300
b1100001101101110011000011000 0
b10010101000011111101110100101010 3
b1011110011101010000001010111100 2
b11110111 )
b11110 *
b11010111000101010001001110101110 %
b11010111000101010001001110101110 ,
b11100011010010111111100111000110 $
b11100011010010111111100111000110 +
#310
b11001001011001010010010110010010 0
b111000100101111011111001110001 3
b101110101111001101000001011 2
b11111111 )
b11111 *
b10010101000011111101110100101010 %
b10010101000011111101110100101010 ,
b1011110011101010000001010111100 $
b1011110011101010000001010111100 +
#320
b11001101001111111101101110011010 0
1#
b1 !
b1 1
b10100111111100100101010101001111 3
b11000010111100100100000110000101 2
b100000111 )
b100000 *
b111000100101111011111001110001 %
b111000100101111011111001110001 ,
b101110101111001101000001011 $
b101110101111001101000001011 +
#330
b11010111111111110110000110110 0
0#
b0 !
b0 1
b10011101000001100011001100111010 3
b11101110011000110000000111011 2
b100001111 )
b100001 *
b10100111111100100101010101001111 %
b10100111111100100101010101001111 ,
b11000010111100100100000110000101 $
b11000010111100100100000110000101 +
#340
b10000000110001100010110100000001 0
b10001010101010100100101100010101 3
b111111001000110011001001111110 2
b100010111 )
b100010 *
b10011101000001100011001100111010 %
b10011101000001100011001100111010 ,
b11101110011000110000000111011 $
b11101110011000110000000111011 +
#350
b10110100011110001110011101101001 0
b11101100100111000100101111011001 3
b11111000110110011001101111110001 2
b100011111 )
b100011 *
b10001010101010100100101100010101 %
b10001010101010100100101100010101 ,
b111111001000110011001001111110 $
b111111001000110011001001111110 +
#360
b1100001111010101000000011000 0
b10100110001101011111101101001100 3
b10110001001000110000011101100010 2
b100100111 )
b100100 *
b11101100100111000100101111011001 %
b11101100100111000100101111011001 ,
b11111000110110011001101111110001 $
b11111000110110011001101111110001 +
#370
b1010111011010000110000010110 0
b11000111101110011010000110001111 3
b11001111101000010101010110011111 2
b100101111 )
b100101 *
b10100110001101011111101101001100 %
b10100110001101011111101101001100 ,
b10110001001000110000011101100010 $
b10110001001000110000011101100010 +
#380
b111111001111011010000010000 0
b1011011110011010110000010110111 3
b11111100011011011010100111111000 2
b100110111 )
b100110 *
b11000111101110011010000110001111 %
b11000111101110011010000110001111 ,
b11001111101000010101010110011111 $
b11001111101000010101010110011111 +
#390
b10100000101000000100100101000001 0
1#
b1 !
b1 1
b101110011111011001010001011100 3
b1001111110001000101011010011111 2
b100111111 )
b100111 *
b1011011110011010110000010110111 %
b1011011110011010110000010110111 ,
b11111100011011011010100111111000 $
b11111100011011011010100111111000 +
#400
b100001010001101100001001000011 0
0#
b0 !
b0 1
b11000100110111100011011110001001 3
b101101110010111100000001011011 2
b101000111 )
b101000 *
b101110011111011001010001011100 %
b101110011111011001010001011100 ,
b1001111110001000101011010011111 $
b1001111110001000101011010011111 +
#410
b1101000111011011000100011010010 0
b1101000001000110011111011010000 3
b100100101011100011001001001001 2
b101001111 )
b101001 *
b11000100110111100011011110001001 %
b11000100110111100011011110001001 ,
b101101110010111100000001011011 $
b101101110010111100000001011011 +
#420
b10111100100010101111001101111001 0
1#
b1 !
b1 1
b101000110001111111110001010001 3
b1101011111111101100000011010111 2
b101010111 )
b101010 *
b1101000001000110011111011010000 %
b1101000001000110011111011010000 ,
b100100101011100011001001001001 $
b100100101011100011001001001001 +
#430
b1000011001101101100010010000110 0
0#
b0 !
b0 1
b10000110000111010111111100001100 3
b11001011001000010010111110010110 2
b101011111 )
b101011 *
b101000110001111111110001010001 %
b101000110001111111110001010001 ,
b1101011111111101100000011010111 $
b1101011111111101100000011010111 +
#440
b1000101000000111011000010001010 0
b11100100010101111110110111001000 3
b1100001001011001100111011000010 2
b101100111 )
b101100 *
b10000110000111010111111100001100 %
b10000110000111010111111100001100 ,
b11001011001000010010111110010110 $
b11001011001000010010111110010110 +
#450
b1111100110101001110000011111010 0
b10011110111100101110110100111101 3
b111011100000100101101001110111 2
b101101111 )
b101101 *
b11100100010101111110110111001000 %
b11100100010101111110110111001000 ,
b1100001001011001100111011000010 $
b1100001001011001100111011000010 +
#460
b10011100100011110110110100111010 0
b111111000001010000000001111110 3
b10001001000011001101101100010010 2
b101110111 )
b101110 *
b10011110111100101110110100111101 %
b10011110111100101110110100111101 ,
b111011100000100101101001110111 $
b111011100000100101101001110111 +
#470
b1001010000001111101101010010100 0
1#
b1 !
b1 1
b10011100110110011110011100111001 3
b10110110111001011000000101101101 2
b101111111 )
b101111 *
b111111000001010000000001111110 %
b111111000001010000000001111110 ,
b10001001000011001101101100010010 $
b10001001000011001101101100010010 +
#480
b11010000010111001101000110100 0
0#
b0 !
b0 1
b1101001111010111111011011010011 3
b10001111110100101000111100011111 2
b110000111 )
b110000 *
b10011100110110011110011100111001 %
b10011100110110011110011100111001 ,
b10110110111001011000000101101101 $
b10110110111001011000000101101101 +
#490
b100101111001101001100001001100 0
1#
b1 !
b1 1
b111100000101001000100001111000 3
b11000010110110010010111110000101 2
b110001111 )
b110001 *
b1101001111010111111011011010011 %
b1101001111010111111011011010011 ,
b10001111110100101000111100011111 $
b10001111110100101000111100011111 +
#500
b10000110110001001010011100001101 0
b10100100100010110100101101001001 3
b10101101110110100101100101011011 2
b110010111 )
b110010 *
b111100000101001000100001111000 %
b111100000101001000100001111000 ,
b11000010110110010010111110000101 $
b11000010110110010010111110000101 +
#510
b1001010011110000111000010010 0
0#
b0 !
b0 1
b10010101000011001010111100101010 3
b11111111100101010111000111111 2
b110011111 )
b110011 *
b10100100100010110100101101001001 %
b10100100100010110100101101001001 ,
b10101101110110100101100101011011 $
b10101101110110100101100101011011 +
#520
b10001010111001011111111100010101 0
b1000011001111110011100010000110 3
b10101100000101010110001101011000 2
b110100111 )
b110100 *
b10010101000011001010111100101010 %
b10010101000011001010111100101010 ,
b11111111100101010111000111111 $
b11111111100101010111000111111 +
#530
b1101000110101100010101011010010 0
1#
b1 !
b1 1
b1001110001011111111001010011100 3
b1000111000110100000110010001110 2
b110101111 )
b110101 *
b1000011001111110011100010000110 %
b1000011001111110011100010000110 ,
b10101100000101010110001101011000 $
b10101100000101010110001101011000 +
#540
b11111000111010100001100111110010 0
b10011011111011011110000100110 3
b11111101001101011001100111111010 2
b110110111 )
b110110 *
b1001110001011111111001010011100 %
b1001110001011111111001010011100 ,
b1000111000110100000110010001110 $
b1000111000110100000110010001110 +
#550
b11101001101101111101110111010100 0
b1010001100010111011010010100011 3
b10111001100101100001011101110011 2
b110111111 )
b110111 *
b10011011111011011110000100110 %
b10011011111011011110000100110 ,
b11111101001101011001100111111010 $
b11111101001101011001100111111010 +
#560
b1101000000010100110001011010000 0
b1011001110100101001001010110011 3
b10111100110011010100000101111 2
b111000111 )
b111000 *
b1010001100010111011010010100011 %
b1010001100010111011010010100011 ,
b10111001100101100001011101110011 $
b10111001100101100001011101110011 +
#570
b10111101110001110001010101111100 0
b10100010001010010000110101000100 3
b101111110110000101011001011111 2
b111001111 )
b111001 *
b1011001110100101001001010110011 %
b1011001110100101001001010110011 ,
b10111100110011010100000101111 $
b10111100110011010100000101111 +
#580
b10001101101011110100100100011011 0
0#
b0 !
b0 1
b1100101100110110011011011001011 3
b11111011111110001111110111110111 2
b111010111 )
b111010 *
b10100010001010010000110101000100 %
b10100010001010010000110101000100 ,
b101111110110000101011001011111 $
b101111110110000101011001011111 +
#590
b10010110010111011100011100101100 0
1#
b1 !
b1 1
b10101101001010001101101101011010 3
b1110011000010010001101011100110 2
b111011111 )
b111011 *
b1100101100110110011011011001011 %
b1100101100110110011011011001011 ,
b11111011111110001111110111110111 $
b11111011111110001111110111110111 +
#600
b11000101111000000011111110001100 0
0#
b0 !
b0 1
b1110110100000101110001011101101 3
b10010100110011111100000100101001 2
b111100111 )
b111100 *
b10101101001010001101101101011010 %
b10101101001010001101101101011010 ,
b1110011000010010001101011100110 $
b1110011000010010001101011100110 +
#610
b11110010011001101111000111100 0
1#
b1 !
b1 1
b110010100111111011011001100101 3
b1101101010100110110110011011010 2
b111101111 )
b111101 *
b1110110100000101110001011101101 %
b1110110100000101110001011101101 ,
b10010100110011111100000100101001 $
b10010100110011111100000100101001 +
#620
b111010101100111011011001110101 0
0#
b0 !
b0 1
b1101111101111101001010011011111 3
b1011010100010101110001010110101 2
b111110111 )
b111110 *
b110010100111111011011001100101 %
b110010100111111011011001100101 ,
b1101101010100110110110011011010 $
b1101101010100110110110011011010 +
#630
b11101010110011000100110111010110 0
1#
b1 !
b1 1
b10100010001100011111111101000100 3
b10111100111100010001100101111001 2
b111111111 )
b111111 *
b1101111101111101001010011011111 %
b1101111101111101001010011011111 ,
b1011010100010101110001010110101 $
b1011010100010101110001010110101 +
#640
b11010101111110001101000110101 0
0#
b0 !
b0 1
b10010101000010010000101100101010 3
b1101000011101000000110011010000 2
b1000000111 )
b1000000 *
b10100010001100011111111101000100 %
b10100010001100011111111101000100 ,
b10111100111100010001100101111001 $
b10111100111100010001100101111001 +
#650
b11010011011010110000000110100110 0
b10000111011011111100111100001110 3
b11010101111101101010110110101011 2
b1000001111 )
b1000001 *
b10010101000010010000101100101010 %
b10010101000010010000101100101010 ,
b1101000011101000000110011010000 $
b1101000011101000000110011010000 +
#660
b1001110100001101101111010011101 0
b1001101010111101011110010011010 3
b11101110010111011010110111011100 2
b1000010111 )
b1000010 *
b10000111011011111100111100001110 %
b10000111011011111100111100001110 ,
b11010101111101101010110110101011 $
b11010101111101101010110110101011 +
#670
b10100000111111101111000101000010 0
1#
b1 !
b1 1
b1100001111100010000001011000011 3
b1111110110111110111001011111101 2
b1000011111 )
b1000011 *
b1001101010111101011110010011010 %
b1001101010111101011110010011010 ,
b11101110010111011010110111011100 $
b11101110010111011010110111011100 +
#680
b11100111011100111000000111010 0
0#
b0 !
b0 1
b10100111011110011110100101001110 3
b10101011000011101110110101010110 2
b1000100111 )
b1000100 *
b1100001111100010000001011000011 %
b1100001111100010000001011000011 ,
b1111110110111110111001011111101 $
b1111110110111110111001011111101 +
#690
b11100101010000010000001000 0
b101001100010011010000001010 3
b110011110110010111011001100111 2
b1000101111 )
b1000101 *
b10100111011110011110100101001110 %
b10100111011110011110100101001110 ,
b10101011000011101110110101010110 $
b10101011000011101110110101010110 +
#700
b101110101010000100001001011101 0
b11100000011101000101000111000 3
b11011011011011111011100110110110 2
b1000110111 )
b1000110 *
b101001100010011010000001010 %
b101001100010011010000001010 ,
b110011110110010111011001100111 $
b110011110110010111011001100111 +
#710
b10111111011000010010111101111110 0
1#
b1 !
b1 1
b1011100001010111100010010111000 3
b10111100110100011000011101111001 2
b1000111111 )
b1000111 *
b11100000011101000101000111000 %
b11100000011101000101000111000 ,
b11011011011011111011100110110110 $
b11011011011011111011100110110110 +
#720
b1100000101001011100001011000001 0
b11001001110001100101110110010011 3
b11001010011101001011111110010100 2
b1001000111 )
b1001000 *
b1011100001010111100010010111000 %
b1011100001010111100010010111000 ,
b10111100110100011000011101111001 $
b10111100110100011000011101111001 +
#730
b101011100110001000000001 0
0#
b0 !
b0 1
b101100101101111100101001011001 3
b10001111110010110000000100 2
b1001001111 )
b1001001 *
b11001001110001100101110110010011 %
b11001001110001100101110110010011 ,
b11001010011101001011111110010100 $
b11001010011101001011111110010100 +
#740
b11010101100001110110000110101011 0
1#
b1 !
b1 1
b100110111111001101111001001101 3
b11101101110010110110100111011011 2
b1001010111 )
b1001010 *
b101100101101111100101001011001 %
b101100101101111100101001011001 ,
b10001111110010110000000100 $
b10001111110010110000000100 +
#750
b11000110110011101000101110001110 0
b110110101001000010011001101101 3
b11101100101100001011011111011001 2
b1001011111 )
b1001011 *
b100110111111001101111001001101 %
b100110111111001101111001001101 ,
b11101101110010110110100111011011 $
b11101101110010110110100111011011 +
#760
b10110110000011001001000101101100 0
b11100101001110110100100111001010 3
b111011010001011110001001110110 2
b1001100111 )
b1001100 *
b110110101001000010011001101101 %
b110110101001000010011001101101 ,
b11101100101100001011011111011001 $
b11101100101100001011011111011001 +
#770
b1010110000010101001100010101100 0
0#
b0 !
b0 1
b11001010100100110111000110010101 3
b11011011000101110010110110110110 2
b1001101111 )
b1001101 *
b11100101001110110100100111001010 %
b11100101001110110100100111001010 ,
b111011010001011110001001110110 $
b111011010001011110001001110110 +
#780
b10000100000111011110000100001 0
b10000010011101001001101100000100 3
b100011000001110001101001000110 2
b1001110111 )
b1001110 *
b11001010100100110111000110010101 %
b11001010100100110111000110010101 ,
b11011011000101110010110110110110 $
b11011011000101110010110110110110 +
#790
b10100000100100100111111101000010 0
b10110100100110000000011101101001 3
b11111011110100100110000111110111 2
b1001111111 )
b1001111 *
b10000010011101001001101100000100 %
b10000010011101001001101100000100 ,
b100011000001110001101001000110 $
b100011000001110001101001000110 +
#800
b1000111001110100101101010001110 0
b11000100000000011000110110001000 3
b1011010011011101011101010110100 2
b1010000111 )
b1010000 *
b10110100100110000000011101101001 %
b10110100100110000000011101101001 ,
b11111011110100100110000111110111 $
b11111011110100100110000111110111 +
#810
b10010110011011010010110100101100 0
b10110100100000000010000101101 3
b10010100011111001101100100101000 2
b1010001111 )
b1010001 *
b11000100000000011000110110001000 %
b11000100000000011000110110001000 ,
b1011010011011101011101010110100 $
b1011010011011101011101010110100 +
#820
b1111101111011001101010011111011 0
1#
b1 !
b1 1
b10111010111001001110000101110 3
b1100011110001010011000011000111 2
b1010010111 )
b1010010 *
b10110100100000000010000101101 %
b10110100100000000010000101101 ,
b10010100011111001101100100101000 $
b10010100011111001101100100101000 +
#830
b1001100011010001001010010011001 0
0#
b0 !
b0 1
b10001110010000010100010100011100 3
b100011101111110010000001000 2
b1010011111 )
b1010011 *
b10111010111001001110000101110 %
b10111010111001001110000101110 ,
b1100011110001010011000011000111 $
b1100011110001010011000011000111 +
#840
b1110110001101101001111011101100 0
b10010100100111100000011100101001 3
b1111110101001111010011011111101 2
b1010100111 )
b1010100 *
b10001110010000010100010100011100 %
b10001110010000010100010100011100 ,
b100011101111110010000001000 $
b100011101111110010000001000 +
#850
b11101010000010011001111111010100 0
b11000011001101010110011110000110 3
b1110001101111001000000011100 2
b1010101111 )
b1010101 *
b10010100100111100000011100101001 %
b10010100100111100000011100101001 ,
b1111110101001111010011011111101 $
b1111110101001111010011011111101 +
#860
b1001011000000100010100010010110 0
b11110101101111100011000111101 3
b1101101001101000000100011011010 2
b1010110111 )
b1010110 *
b11000011001101010110011110000110 %
b11000011001101010110011110000110 ,
b1110001101111001000000011100 $
b1110001101111001000000011100 +
#870
b1001110011111000100001010011101 0
b111000010101011100010001110000 3
b10110011010011101010011101100110 2
b1010111111 )
b1010111 *
b11110101101111100011000111101 %
b11110101101111100011000111101 ,
b1101101001101000000100011011010 $
b1101101001101000000100011011010 +
#880
b1111010111110001110001011110110 0
1#
b1 !
b1 1
b11011101011100011001100110111010 3
b111001111101010000010001110011 2
b1011000111 )
b1011000 *
b111000010101011100010001110000 %
b111000010101011100010001110000 ,
b10110011010011101010011101100110 $
b10110011010011101010011101100110 +
#890
b1011100100000110110101010111001 0
0#
b0 !
b0 1
b11111101010001110111100111111010 3
b10101111001110101011001101011110 2
b1011001111 )
b1011001 *
b11011101011100011001100110111010 %
b11011101011100011001100110111010 ,
b111001111101010000010001110011 $
b111001111101010000010001110011 +
#900
b10110001111100110011100101100100 0
1#
b1 !
b1 1
b1101001001001111011000011010 3
b11101010100011100000010111010101 2
b1011010111 )
b1011010 *
b11111101010001110111100111111010 %
b11111101010001110111100111111010 ,
b10101111001110101011001101011110 $
b10101111001110101011001101011110 +
#910
b11011101011010010000111110111011 0
b10011011100001110110000100110111 3
b1011100111100000000000010111001 2
b1011011111 )
b1011011 *
b1101001001001111011000011010 %
b1101001001001111011000011010 ,
b11101010100011100000010111010101 $
b11101010100011100000010111010101 +
#920
b11000001011010001001111110000010 0
0#
b0 !
b0 1
b11100000001110010010000111000000 3
b11001011001001110011011110010110 2
b1011100111 )
b1011100 *
b10011011100001110110000100110111 %
b10011011100001110110000100110111 ,
b1011100111100000000000010111001 $
b1011100111100000000000010111001 +
#930
b11101010111011100001010111010110 0
1#
b1 !
b1 1
b1011011010001100001101010110110 3
b10010011001001011001111100100110 2
b1011101111 )
b1011101 *
b11100000001110010010000111000000 %
b11100000001110010010000111000000 ,
b11001011001001110011011110010110 $
b11001011001001110011011110010110 +
#940
b110111110111111000010001110000 0
b11101110010111110000111111011100 3
b10111110100110011000001101111101 2
b1011110111 )
b1011110 *
b1011011010001100001101010110110 %
b1011011010001100001101010110110 ,
b10010011001001011001111100100110 $
b10010011001001011001111100100110 +
#950
b11010000001110100111001110100001 0
b10111100000000111111111101111000 3
b11000011011000010101011110000110 2
b1011111111 )
b1011111 *
b11101110010111110000111111011100 %
b11101110010111110000111111011100 ,
b10111110100110011000001101111101 $
b10111110100110011000001101111101 +
