02_alu/alu.v
// module alu
// #(	
// 	parameter	N			= 32
// )
// (	
// 	output reg	[N-1:0]		o_y,
// 	output 					o_c,
// 	input		[N-1:0]		i_a,
// 	input		[N-1:0]		i_b,
// 	input		[2:0]		i_f
// );
// 	wire		[N-1:0]		bmux = i_f[2] ? ~i_b : i_b;
// 	wire		[N-1:0]		sum_a_bmux;
// 
// 	assign {o_c, sum_a_bmux} = i_a + bmux + i_f[2];
// 	
// 	always @(*) begin
// 		case (i_f[1:0])
// 			2'b00 : o_y = i_a & bmux;
// 			2'b01 : o_y = i_a | bmux;
// 			2'b10 : o_y = sum_a_bmux;
// 			2'b11 : o_y = {{(N-1){1'b0}}, sum_a_bmux[N-1]};
// 		endcase
// 	end
// endmodule

module alu
#(	
	parameter	N		= 32
)
(	
	output reg signed	[N-1:0]		o_y,
	output	 						o_c,
//	output							o_ovf,
	input signed		[N-1:0]		i_a,
	input signed 		[N-1:0]		i_b,
	input 				[2:0]		i_f
);

	wire signed			[N-1:0]		sum;
//	wire							ovf_add	=	(i_f == 3'b010) &&
//												((~i_a[N-1] && ~i_b[N-1] && sum[N-1]) || (i_a[N-1] && i_b[N-1] && ~sum[N-1]));
//	wire							ovf_sub =	(i_f == 3'b110) && 
//												((~i_a[N-1] && i_b[N-1] && sum[N-1]) || (i_a[N-1] && ~i_b[N-1] && ~sum[N-1]));
//
//	assign o_ovf = ovf_add || ovf_sub;	
	assign {o_c, sum} = i_f[2] ? i_a-i_b : i_a+i_b;

	always @(*) begin
		case (i_f)
			3'b000	: o_y = i_a & i_b;
			3'b001	: o_y = i_a | i_b;
			3'b010	: o_y = sum;
			3'b100	: o_y = i_a & ~i_b;
			3'b101	: o_y = i_a | ~i_b;
			3'b110	: o_y = sum;
			3'b111	: o_y = i_a < i_b;
			default : o_y = 'd0;
		endcase
	end
endmodule

02_alu/alu_tb.v
// --------------------------------------------------
//	Define Global Variables
// --------------------------------------------------
`define	CLKFREQ		100		// Clock Freq. (Unit: MHz)
`define	SIMCYCLE	100		// Sim. Cycles
`define N			32		// Bitwidth of data

// --------------------------------------------------
//	Includes
// --------------------------------------------------
`include	"alu.v"

module alu_tb;
// --------------------------------------------------
//	DUT Signals & Instantiate
// --------------------------------------------------
	wire	[`N-1:0]	o_y;
	wire				o_c;
//	wire				o_ovf;
	reg		[`N-1:0]	i_a;
	reg		[`N-1:0]	i_b;
	reg		[2:0]		i_f;

	alu
	#(
		.N			(`N			)
	)
	u_alu_beh(
		.o_y				(o_y				),
		.o_c				(o_c				),
//		.o_ovf				(o_ovf				),
		.i_a				(i_a				),
		.i_b				(i_b				),
		.i_f				(i_f				)
	);


// --------------------------------------------------
//	Tasks
// --------------------------------------------------
	reg		[4*32-1:0]	operation;

	task init;
		begin
			i_a				= 0;
			i_b				= 0;
			i_f				= 0;
		end
	endtask

	task perform_operation;
		input	[2:0]		ti_f;
		input	[`N-1:0]	ti_a;
		input	[`N-1:0]	ti_b;
		begin
			#(1000/`CLKFREQ);
			i_a	= ti_a;
			i_b	= ti_b;
			i_f	= ti_f;
		end
	endtask

// --------------------------------------------------
//	Test Stimulus
// --------------------------------------------------
	integer i, fn;

	initial begin
		init();
		i	= 0;
		fn	= 0;
		while(i < `SIMCYCLE) begin
			if (fn%8 != 3) begin
				perform_operation(
					fn,
					$urandom,
					$urandom
				);	
				i=i+1;
			end
			fn=fn+1;
		end
		#(1000/`CLKFREQ);
		$finish;
	end
	always @(*) begin
		case (i_f)
			3'b000	: operation = "AND";
			3'b001	: operation = "OR";
			3'b010	: operation = "ADD";
			3'b100	: operation = "AND_N";
			3'b101	: operation = "OR_N";
			3'b110	: operation = "SUB";
			3'b111	: operation = "SLT";
			default	: operation = "NOT_USED";
		endcase
	end

// --------------------------------------------------
//	Dump VCD
// --------------------------------------------------
	reg	[8*32-1:0]	vcd_file;
	initial begin
		if ($value$plusargs("vcd_file=%s", vcd_file)) begin
			$dumpfile(vcd_file);
			$dumpvars;
		end else begin
			$dumpfile("alu_tb.vcd");
			$dumpvars;
		end
	end

endmodule

02_alu/vcd/alu.vcd
$date
	Thu Jul  4 11:16:21 2024
$end
$version
	Icarus Verilog
$end
$timescale
	1s
$end
$scope module alu_tb $end
$var wire 32 ! o_y [31:0] $end
$var wire 1 " o_c $end
$var reg 32 # i_a [31:0] $end
$var reg 32 $ i_b [31:0] $end
$var reg 3 % i_f [2:0] $end
$var reg 128 & operation [127:0] $end
$var reg 256 ' vcd_file [255:0] $end
$var integer 32 ( fn [31:0] $end
$var integer 32 ) i [31:0] $end
$scope module u_alu_beh $end
$var wire 32 * i_a [31:0] $end
$var wire 32 + i_b [31:0] $end
$var wire 3 , i_f [2:0] $end
$var wire 32 - sum [31:0] $end
$var wire 1 " o_c $end
$var reg 32 . o_y [31:0] $end
$upscope $end
$scope task init $end
$upscope $end
$scope task perform_operation $end
$var reg 32 / ti_a [31:0] $end
$var reg 32 0 ti_b [31:0] $end
$var reg 3 1 ti_f [2:0] $end
$upscope $end
$upscope $end
$enddefinitions $end
#0
$dumpvars
b0 1
b1000000100010010101111010000001 0
b10010010000101010011010100100100 /
b0 .
b0 -
b0 ,
b0 +
b0 *
b0 )
b0 (
b101110001011110111011001100011011001000010111101100001011011000111010100101110011101100110001101100100 '
b10000010100111001000100 &
b0 %
b0 $
b0 #
0"
b0 !
$end
#10
b11010010100111101001001110100101 -
1"
b10001010000000000 !
b10001010000000000 .
b110001111100000101011001100011 0
b100100001001101011000001001 /
b1 1
b1 (
b1 )
b1000000100010010101111010000001 $
b1000000100010010101111010000001 +
b10010010000101010011010100100100 #
b10010010000101010011010100100100 *
#20
b110110011101010010110001101100 -
0"
b100111101010010 &
b110101111101001101011001101011 !
b110101111101001101011001101011 .
b11000110110111111001100110001101 0
b10000110101110010111101100001101 /
b10 1
b10 (
b10 )
b1 %
b1 ,
b110001111100000101011001100011 $
b110001111100000101011001100011 +
b100100001001101011000001001 #
b100100001001101011000001001 *
#30
b1001101100110010001010010011010 -
1"
b10000010100010001000100 &
b1001101100110010001010010011010 !
b1001101100110010001010010011010 .
b1001001101110101001000010010 0
b110010110000101000010001100101 /
b100 1
b100 (
b11 )
b10 %
b10 ,
b11000110110111111001100110001101 $
b11000110110111111001100110001101 +
b10000110101110010111101100001101 #
b10000110101110010111101100001101 *
#40
b101001100010110011001001010011 -
0"
b100000101001110010001000101111101001110 &
b110010110000001000010001100101 !
b110010110000001000010001100101 .
b10000110110101111100110100001101 0
b10000000111100111110001100000001 /
b101 1
b101 (
b100 )
b100 %
b100 ,
b1001001101110101001000010010 $
b1001001101110101001000010010 +
b110010110000101000010001100101 #
b110010110000101000010001100101 *
#50
b11111010000111000001010111110100 -
1"
b1001111010100100101111101001110 &
b11111001111110111111001111110011 !
b11111001111110111111001111110011 .
b10011110100011011100110100111101 0
b10111011001000111111000101110110 /
b110 1
b110 (
b101 )
b101 %
b101 ,
b10000110110101111100110100001101 $
b10000110110101111100110100001101 +
b10000000111100111110001100000001 #
b10000000111100111110001100000001 *
#60
b11100100101100010010000111001 -
0"
b10100110101010101000010 &
b11100100101100010010000111001 !
b11100100101100010010000111001 .
b11000110001011011111011110001100 0
b11110110110101000101011111101101 /
b111 1
b111 (
b110 )
b110 %
b110 ,
b10011110100011011100110100111101 $
b10011110100011011100110100111101 +
b10111011001000111111000101110110 #
b10111011001000111111000101110110 *
#70
b110000101001100110000001100001 -
b10100110100110001010100 &
b0 !
b0 .
b1100011001101110010010011000110 0
b11111100111111011110100111111001 /
b0 1
b1000 (
b111 )
b111 %
b111 ,
b11000110001011011111011110001100 $
b11000110001011011111011110001100 +
b11110110110101000101011111101101 #
b11110110110101000101011111101101 *
#80
b1100000001101010000111010111111 -
0"
b10000010100111001000100 &
b1100000001101010010000011000000 !
b1100000001101010010000011000000 .
b1010101000100111101001010101010 0
b1100010111101111000010011000101 /
b1 1
b1001 (
b1000 )
b0 %
b0 ,
b1100011001101110010010011000110 $
b1100011001101110010010011000110 +
b11111100111111011110100111111001 #
b11111100111111011110100111111001 *
#90
b10111000000010110101011101101111 -
b100111101010010 &
b1110111111101111101011011101111 !
b1110111111101111101011011101111 .
b111011110100100111001001110111 0
b11110010101011111111011111100101 /
b10 1
b1010 (
b1001 )
b1 %
b1 ,
b1010101000100111101001010101010 $
b1010101000100111101001010101010 +
b1100010111101111000010011000101 #
b1100010111101111000010011000101 *
#100
b101110100000100110101001011100 -
b10000010100010001000100 &
b101110100000100110101001011100 !
b101110100000100110101001011100 .
b11000111111011001101101110001111 0
b1001001100101101011000010010 /
b100 1
b1100 (
b1010 )
b10 %
b10 ,
b111011110100100111001001110111 $
b111011110100100111001001110111 +
b11110010101011111111011111100101 #
b11110010101011111111011111100101 *
#110
b1000001010001011111101010000011 -
0"
b100000101001110010001000101111101001110 &
b1000000100100000010000010000 !
b1000000100100000010000010000 .
b1100111011101101001011011001110 0
b11111001001100000110100111110010 /
b101 1
b1101 (
b1011 )
b100 %
b100 ,
b11000111111011001101101110001111 $
b11000111111011001101101110001111 +
b1001001100101101011000010010 #
b1001001100101101011000010010 *
#120
b10010001101110011101001100100100 -
1"
b1001111010100100101111101001110 &
b11111001101110010110100111110011 !
b11111001101110010110100111110011 .
b1100010110010100100111011000101 0
b1110100000000000111101011101000 /
b110 1
b1110 (
b1100 )
b101 %
b101 ,
b1100111011101101001011011001110 $
b1100111011101101001011011001110 +
b11111001001100000110100111110010 #
b11111001001100000110100111110010 *
#130
b10001001101100010110000100011 -
0"
b10100110101010101000010 &
b10001001101100010110000100011 !
b10001001101100010110000100011 .
b1011110100011100010100010111101 0
b10101110010110000100100101011100 /
b111 1
b1111 (
b1101 )
b110 %
b110 ,
b1100010110010100100111011000101 $
b1100010110010100100111011000101 +
b1110100000000000111101011101000 #
b1110100000000000111101011101000 *
#140
b1001111110010100010000010011111 -
1"
b10100110100110001010100 &
b1 !
b1 .
b110010101001110010011001100101 0
b10110101010110101100000101101 /
b0 1
b10000 (
b1110 )
b111 %
b111 ,
b1011110100011100010100010111101 $
b1011110100011100010100010111101 +
b10101110010110000100100101011100 #
b10101110010110000100100101011100 *
#150
0"
b1001001010100100111111010010010 -
b10000010100111001000100 &
b10010101000110000000000100101 !
b10010101000110000000000100101 .
b10000101011100111000011100001010 0
b110001111011110110001001100011 /
b1 1
b10001 (
b1111 )
b0 %
b0 ,
b110010101001110010011001100101 $
b110010101001110010011001100101 +
b10110101010110101100000101101 #
b10110101010110101100000101101 *
#160
b10110111011000101110100101101101 -
1"
b100111101010010 &
b10110101111111111110011101101011 !
b10110101111111111110011101101011 .
b10010000011001000010000100100000 0
b1000000001110110010001010000000 /
b10 1
b10010 (
b10000 )
b1 %
b1 ,
b10000101011100111000011100001010 $
b10000101011100111000011100001010 +
b110001111011110110001001100011 #
b110001111011110110001001100011 *
#170
b11010000100111110100001110100000 -
b10000010100010001000100 &
b11010000100111110100001110100000 !
b11010000100111110100001110100000 .
b1001110110011001100110010011101 0
b11010101011110000100010110101010 /
b100 1
b10100 (
b10001 )
b10 %
b10 ,
b10010000011001000010000100100000 $
b10010000011001000010000100100000 +
b1000000001110110010001010000000 #
b1000000001110110010001010000000 *
#180
b10000110101010110111100100001101 -
1"
b100000101001110010001000101111101001110 &
b10010001001100000000000100100010 !
b10010001001100000000000100100010 .
b1001100000111011100000010011 0
b1001011001000000011111010010110 /
b101 1
b10101 (
b10010 )
b100 %
b100 ,
b1001110110011001100110010011101 $
b1001110110011001100110010011101 +
b11010101011110000100010110101010 #
b11010101011110000100010110101010 *
#190
b1000001100111001000011010000011 -
0"
b1001111010100100101111101001110 &
b11111111011111000111111111111110 !
b11111111011111000111111111111110 .
b101001101001111101011001010011 0
b110101111000011100000001101 /
b110 1
b10110 (
b10011 )
b101 %
b101 ,
b1001100000111011100000010011 $
b1001100000111011100000010011 +
b1001011001000000011111010010110 #
b1001011001000000011111010010110 *
#200
b11011101000101000110000110111010 -
1"
b10100110101010101000010 &
b11011101000101000110000110111010 !
b11011101000101000110000110111010 .
b1101010101001100010101011010101 0
b10110101100111111101110101101011 /
b111 1
b10111 (
b10100 )
b110 %
b110 ,
b101001101001111101011001010011 $
b101001101001111101011001010011 +
b110101111000011100000001101 #
b110101111000011100000001101 *
#210
b1001010111110011011001010010110 -
b10100110100110001010100 &
b1 !
b1 .
b1010111010101100011111010101110 0
b1000101110100101000000010 /
b0 1
b11000 (
b10101 )
b111 %
b111 ,
b1101010101001100010101011010101 $
b1101010101001100010101011010101 +
b10110101100111111101110101101011 #
b10110101100111111101110101101011 *
#220
0"
b1011000011011011000100010110000 -
b10000010100111001000100 &
b1000101100000101000000010 !
b1000101100000101000000010 .
b1100111110001010111001011001111 0
b10001110111111111110100100011101 /
b1 1
b11001 (
b10110 )
b0 %
b0 ,
b1010111010101100011111010101110 $
b1010111010101100011111010101110 +
b1000101110100101000000010 #
b1000101110100101000000010 *
#230
b11110110110001010101101111101100 -
1"
b100111101010010 &
b11101111111111111111101111011111 !
b11101111111111111111101111011111 .
b10000101000010010110010100001010 0
b10010001100001000100100100100011 /
b10 1
b11010 (
b10111 )
b1 %
b1 ,
b1100111110001010111001011001111 $
b1100111110001010111001011001111 +
b10001110111111111110100100011101 #
b10001110111111111110100100011101 *
#240
b10110100011011010111000101101 -
b10000010100010001000100 &
b10110100011011010111000101101 !
b10110100011011010111000101101 .
b11110001100010100110000111100 0
b1100101011100110000101011001010 /
b100 1
b11100 (
b11000 )
b10 %
b10 ,
b10000101000010010110010100001010 $
b10000101000010010110010100001010 +
b10010001100001000100100100100011 #
b10010001100001000100100100100011 *
#250
b1000111010000011011111010001110 -
0"
b100000101001110010001000101111101001110 &
b1100001010000100000001011000010 !
b1100001010000100000001011000010 .
b11000101001011100110000110001010 0
b11111001011010001011110111110010 /
b101 1
b11101 (
b11001 )
b100 %
b100 ,
b11110001100010100110000111100 $
b11110001100010100110000111100 +
b1100101011100110000101011001010 #
b1100101011100110000101011001010 *
#260
b110100001110100101110001101000 -
b1001111010100100101111101001110 &
b11111011111110011011111111110111 !
b11111011111110011011111111110111 .
b1101100010010110011010011011000 0
b10100000110001001011001101000001 /
b110 1
b11110 (
b11010 )
b101 %
b101 ,
b11000101001011100110000110001010 $
b11000101001011100110000110001010 +
b11111001011010001011110111110010 #
b11111001011010001011110111110010 *
#270
b110100011110010111111001101001 -
1"
b10100110101010101000010 &
b110100011110010111111001101001 !
b110100011110010111111001101001 .
b1000100100010100001001010001001 0
b10111100001000001111001101111000 /
b111 1
b11111 (
b11011 )
b110 %
b110 ,
b1101100010010110011010011011000 $
b1101100010010110011010011011000 +
b10100000110001001011001101000001 #
b10100000110001001011001101000001 *
#280
b1110111100101101110000011101111 -
b10100110100110001010100 &
b1 !
b1 .
b11011011000000100110010110110110 0
b11110101110001010000110111101011 /
b0 1
b100000 (
b11100 )
b111 %
b111 ,
b1000100100010100001001010001001 $
b1000100100010100001001010001001 +
b10111100001000001111001101111000 #
b10111100001000001111001101111000 *
#290
b11010000110001110111001110100001 -
1"
b10000010100111001000100 &
b11010001000000000000010110100010 !
b11010001000000000000010110100010 .
b11010111000101010001001110101110 0
b11100011010010111111100111000110 /
b1 1
b100001 (
b11101 )
b0 %
b0 ,
b11011011000000100110010110110110 $
b11011011000000100110010110110110 +
b11110101110001010000110111101011 #
b11110101110001010000110111101011 *
#300
b10111010011000010000110101110100 -
b100111101010010 &
b11110111010111111111101111101110 !
b11110111010111111111101111101110 .
b10010101000011111101110100101010 0
b1011110011101010000001010111100 /
b10 1
b100010 (
b11110 )
b1 %
b1 ,
b11010111000101010001001110101110 $
b11010111000101010001001110101110 +
b11100011010010111111100111000110 #
b11100011010010111111100111000110 *
#310
b11110011100001001101111111100110 -
b10000010100010001000100 &
b11110011100001001101111111100110 !
b11110011100001001101111111100110 .
b111000100101111011111001110001 0
b101110101111001101000001011 /
b100 1
b100100 (
b11111 )
b10 %
b10 ,
b10010101000011111101110100101010 $
b10010101000011111101110100101010 +
b1011110011101010000001010111100 #
b1011110011101010000001010111100 *
#320
b11001101001111111101101110011010 -
1"
b100000101001110010001000101111101001110 &
b101010000000000000000001010 !
b101010000000000000000001010 .
b10100111111100100101010101001111 0
b11000010111100100100000110000101 /
b101 1
b100101 (
b100000 )
b100 %
b100 ,
b111000100101111011111001110001 $
b111000100101111011111001110001 +
b101110101111001101000001011 #
b101110101111001101000001011 *
#330
b11010111111111110110000110110 -
0"
b1001111010100100101111101001110 &
b11011010111111111110101110110101 !
b11011010111111111110101110110101 .
b10011101000001100011001100111010 0
b11101110011000110000000111011 /
b110 1
b100110 (
b100001 )
b101 %
b101 ,
b10100111111100100101010101001111 $
b10100111111100100101010101001111 +
b11000010111100100100000110000101 #
b11000010111100100100000110000101 *
#340
b10000000110001100010110100000001 -
b10100110101010101000010 &
b10000000110001100010110100000001 !
b10000000110001100010110100000001 .
b10001010101010100100101100010101 0
b111111001000110011001001111110 /
b111 1
b100111 (
b100010 )
b110 %
b110 ,
b10011101000001100011001100111010 $
b10011101000001100011001100111010 +
b11101110011000110000000111011 #
b11101110011000110000000111011 *
#350
b10110100011110001110011101101001 -
b10100110100110001010100 &
b0 !
b0 .
b11101100100111000100101111011001 0
b11111000110110011001101111110001 /
b0 1
b101000 (
b100011 )
b111 %
b111 ,
b10001010101010100100101100010101 $
b10001010101010100100101100010101 +
b111111001000110011001001111110 #
b111111001000110011001001111110 *
#360
1"
b11100101011101011110011111001010 -
b10000010100111001000100 &
b11101000100110000000101111010001 !
b11101000100110000000101111010001 .
b10100110001101011111101101001100 0
b10110001001000110000011101100010 /
b1 1
b101001 (
b100100 )
b0 %
b0 ,
b11101100100111000100101111011001 $
b11101100100111000100101111011001 +
b11111000110110011001101111110001 #
b11111000110110011001101111110001 *
#370
b1010111010110010000001010101110 -
b100111101010010 &
b10110111001101111111111101101110 !
b10110111001101111111111101101110 .
b11000111101110011010000110001111 0
b11001111101000010101010110011111 /
b10 1
b101010 (
b100101 )
b1 %
b1 ,
b10100110001101011111101101001100 $
b10100110001101011111101101001100 +
b10110001001000110000011101100010 #
b10110001001000110000011101100010 *
#380
b10010111010110101111011100101110 -
b10000010100010001000100 &
b10010111010110101111011100101110 !
b10010111010110101111011100101110 .
b1011011110011010110000010110111 0
b11111100011011011010100111111000 /
b100 1
b101100 (
b100110 )
b10 %
b10 ,
b11000111101110011010000110001111 $
b11000111101110011010000110001111 +
b11001111101000010101010110011111 #
b11001111101000010101010110011111 *
#390
b10100000101000000100100101000001 -
1"
b100000101001110010001000101111101001110 &
b10100100001000001000100101001000 !
b10100100001000001000100101001000 .
b101110011111011001010001011100 0
b1001111110001000101011010011111 /
b101 1
b101101 (
b100111 )
b100 %
b100 ,
b1011011110011010110000010110111 $
b1011011110011010110000010110111 +
b11111100011011011010100111111000 #
b11111100011011011010100111111000 *
#400
b100001010001101100001001000011 -
0"
b1001111010100100101111101001110 &
b11011111110001100111111110111111 !
b11011111110001100111111110111111 .
b11000100110111100011011110001001 0
b101101110010111100000001011011 /
b110 1
b101110 (
b101000 )
b101 %
b101 ,
b101110011111011001010001011100 $
b101110011111011001010001011100 +
b1001111110001000101011010011111 #
b1001111110001000101011010011111 *
#410
b1101000111011011000100011010010 -
b10100110101010101000010 &
b1101000111011011000100011010010 !
b1101000111011011000100011010010 .
b1101000001000110011111011010000 0
b100100101011100011001001001001 /
b111 1
b101111 (
b101001 )
b110 %
b110 ,
b11000100110111100011011110001001 $
b11000100110111100011011110001001 +
b101101110010111100000001011011 #
b101101110010111100000001011011 *
#420
b10111100100010101111001101111001 -
1"
b10100110100110001010100 &
b1 !
b1 .
b101000110001111111110001010001 0
b1101011111111101100000011010111 /
b0 1
b110000 (
b101010 )
b111 %
b111 ,
b1101000001000110011111011010000 $
b1101000001000110011111011010000 +
b100100101011100011001001001001 #
b100100101011100011001001001001 *
#430
b10010100110001101011110100101000 -
0"
b10000010100111001000100 &
b101000110001101100000001010001 !
b101000110001101100000001010001 .
b10000110000111010111111100001100 0
b11001011001000010010111110010110 /
b1 1
b110001 (
b101011 )
b0 %
b0 ,
b101000110001111111110001010001 $
b101000110001111111110001010001 +
b1101011111111101100000011010111 #
b1101011111111101100000011010111 *
#440
b1010001001111101010111010100010 -
1"
b100111101010010 &
b11001111001111010111111110011110 !
b11001111001111010111111110011110 .
b11100100010101111110110111001000 0
b1100001001011001100111011000010 /
b10 1
b110010 (
b101100 )
b1 %
b1 ,
b10000110000111010111111100001100 $
b10000110000111010111111100001100 +
b11001011001000010010111110010110 #
b11001011001000010010111110010110 *
#450
b1000101100001001011110010001010 -
0"
b10000010100010001000100 &
b1000101100001001011110010001010 !
b1000101100001001011110010001010 .
b10011110111100101110110100111101 0
b111011100000100101101001110111 /
b100 1
b110100 (
b101101 )
b10 %
b10 ,
b11100100010101111110110111001000 $
b11100100010101111110110111001000 +
b1100001001011001100111011000010 #
b1100001001011001100111011000010 *
#460
b10011100100011110110110100111010 -
0"
b100000101001110010001000101111101001110 &
b100001000000000001001001000010 !
b100001000000000001001001000010 .
b111111000001010000000001111110 0
b10001001000011001101101100010010 /
b101 1
b110101 (
b101110 )
b100 %
b100 ,
b10011110111100101110110100111101 $
b10011110111100101110110100111101 +
b111011100000100101101001110111 #
b111011100000100101101001110111 *
#470
b1001010000001111101101010010100 -
1"
b1001111010100100101111101001110 &
b11001001111111101111111110010011 !
b11001001111111101111111110010011 .
b10011100110110011110011100111001 0
b10110110111001011000000101101101 /
b110 1
b110110 (
b101111 )
b101 %
b101 ,
b111111000001010000000001111110 $
b111111000001010000000001111110 +
b10001001000011001101101100010010 #
b10001001000011001101101100010010 *
#480
b11010000010111001101000110100 -
0"
b10100110101010101000010 &
b11010000010111001101000110100 !
b11010000010111001101000110100 .
b1101001111010111111011011010011 0
b10001111110100101000111100011111 /
b111 1
b110111 (
b110000 )
b110 %
b110 ,
b10011100110110011110011100111001 $
b10011100110110011110011100111001 +
b10110110111001011000000101101101 #
b10110110111001011000000101101101 *
#490
b100101111001101001100001001100 -
1"
b10100110100110001010100 &
b1 !
b1 .
b111100000101001000100001111000 0
b11000010110110010010111110000101 /
b0 1
b111000 (
b110001 )
b111 %
b111 ,
b1101001111010111111011011010011 $
b1101001111010111111011011010011 +
b10001111110100101000111100011111 #
b10001111110100101000111100011111 *
#500
b11111110111011011011011111111101 -
b10000010100111001000100 &
b100000000100000000000 !
b100000000100000000000 .
b10100100100010110100101101001001 0
b10101101110110100101100101011011 /
b1 1
b111001 (
b110010 )
b0 %
b0 ,
b111100000101001000100001111000 $
b111100000101001000100001111000 +
b11000010110110010010111110000101 #
b11000010110110010010111110000101 *
#510
b1010010011001011010010010100100 -
b100111101010010 &
b10101101110110110101101101011011 !
b10101101110110110101101101011011 .
b10010101000011001010111100101010 0
b11111111100101010111000111111 /
b10 1
b111010 (
b110011 )
b1 %
b1 ,
b10100100100010110100101101001001 $
b10100100100010110100101101001001 +
b10101101110110100101100101011011 #
b10101101110110100101100101011011 *
#520
b10110100111111110101110101101001 -
b10000010100010001000100 &
b10110100111111110101110101101001 !
b10110100111111110101110101101001 .
b1000011001111110011100010000110 0
b10101100000101010110001101011000 /
b100 1
b111100 (
b110100 )
b10 %
b10 ,
b10010101000011001010111100101010 $
b10010101000011001010111100101010 +
b11111111100101010111000111111 #
b11111111100101010111000111111 *
#530
b1101000110101100010101011010010 -
b100000101001110010001000101111101001110 &
b10101100000000000100001101011000 !
b10101100000000000100001101011000 .
b1001110001011111111001010011100 0
b1000111000110100000110010001110 /
b101 1
b111101 (
b110101 )
b100 %
b100 ,
b1000011001111110011100010000110 $
b1000011001111110011100010000110 +
b10101100000101010110001101011000 #
b10101100000101010110001101011000 *
#540
b11111000111010100001100111110010 -
b1001111010100100101111101001110 &
b11110111110110100000110111101111 !
b11110111110110100000110111101111 .
b10011011111011011110000100110 0
b11111101001101011001100111111010 /
b110 1
b111110 (
b110110 )
b101 %
b101 ,
b1001110001011111111001010011100 $
b1001110001011111111001010011100 +
b1000111000110100000110010001110 #
b1000111000110100000110010001110 *
#550
b11101001101101111101110111010100 -
b10100110101010101000010 &
b11101001101101111101110111010100 !
b11101001101101111101110111010100 .
b1010001100010111011010010100011 0
b10111001100101100001011101110011 /
b111 1
b111111 (
b110111 )
b110 %
b110 ,
b10011011111011011110000100110 $
b10011011111011011110000100110 +
b11111101001101011001100111111010 #
b11111101001101011001100111111010 *
#560
b1101000000010100110001011010000 -
b10100110100110001010100 &
b1 !
b1 .
b1011001110100101001001010110011 0
b10111100110011010100000101111 /
b0 1
b1000000 (
b111000 )
b111 %
b111 ,
b1010001100010111011010010100011 $
b1010001100010111011010010100011 +
b10111001100101100001011101110011 #
b10111001100101100001011101110011 *
#570
0"
b1110001011011000011101011100010 -
b10000010100111001000100 &
b10001100100001000000000100011 !
b10001100100001000000000100011 .
b10100010001010010000110101000100 0
b101111110110000101011001011111 /
b1 1
b1000001 (
b111001 )
b0 %
b0 ,
b1011001110100101001001010110011 $
b1011001110100101001001010110011 +
b10111100110011010100000101111 #
b10111100110011010100000101111 *
#580
b11010010000000010110001110100011 -
1"
b100111101010010 &
b10101111111110010101111101011111 !
b10101111111110010101111101011111 .
b1100101100110110011011011001011 0
b11111011111110001111110111110111 /
b10 1
b1000010 (
b111010 )
b1 %
b1 ,
b10100010001010010000110101000100 $
b10100010001010010000110101000100 +
b101111110110000101011001011111 #
b101111110110000101011001011111 *
#590
b1100001100101000011010011000010 -
0"
b10000010100010001000100 &
b1100001100101000011010011000010 !
b1100001100101000011010011000010 .
b10101101001010001101101101011010 0
b1110011000010010001101011100110 /
b100 1
b1000100 (
b111011 )
b10 %
b10 ,
b1100101100110110011011011001011 $
b1100101100110110011011011001011 +
b11111011111110001111110111110111 #
b11111011111110001111110111110111 *
#600
b11000101111000000011111110001100 -
b100000101001110010001000101111101001110 &
b1010010000000010000000010100100 !
b1010010000000010000000010100100 .
b1110110100000101110001011101101 0
b10010100110011111100000100101001 /
b101 1
b1000101 (
b111100 )
b100 %
b100 ,
b10101101001010001101101101011010 $
b10101101001010001101101101011010 +
b1110011000010010001101011100110 #
b1110011000010010001101011100110 *
#610
b11110010011001101111000111100 -
1"
b1001111010100100101111101001110 &
b10011101111111111101110100111011 !
b10011101111111111101110100111011 .
b110010100111111011011001100101 0
b1101101010100110110110011011010 /
b110 1
b1000110 (
b111101 )
b101 %
b101 ,
b1110110100000101110001011101101 $
b1110110100000101110001011101101 +
b10010100110011111100000100101001 #
b10010100110011111100000100101001 *
#620
b111010101100111011011001110101 -
0"
b10100110101010101000010 &
b111010101100111011011001110101 !
b111010101100111011011001110101 .
b1101111101111101001010011011111 0
b1011010100010101110001010110101 /
b111 1
b1000111 (
b111110 )
b110 %
b110 ,
b110010100111111011011001100101 $
b110010100111111011011001100101 +
b1101101010100110110110011011010 #
b1101101010100110110110011011010 *
#630
b11101010110011000100110111010110 -
1"
b10100110100110001010100 &
b1 !
b1 .
b10100010001100011111111101000100 0
b10111100111100010001100101111001 /
b0 1
b1001000 (
b111111 )
b111 %
b111 ,
b1101111101111101001010011011111 $
b1101111101111101001010011011111 +
b1011010100010101110001010110101 #
b1011010100010101110001010110101 *
#640
b1011111001000110001100010111101 -
1"
b10000010100111001000100 &
b10100000001100010001100101000000 !
b10100000001100010001100101000000 .
b10010101000010010000101100101010 0
b1101000011101000000110011010000 /
b1 1
b1001001 (
b1000000 )
b0 %
b0 ,
b10100010001100011111111101000100 $
b10100010001100011111111101000100 +
b10111100111100010001100101111001 #
b10111100111100010001100101111001 *
#650
b11111101011111010001011111111010 -
b100111101010010 &
b11111101011111010000111111111010 !
b11111101011111010000111111111010 .
b10000111011011111100111100001110 0
b11010101111101101010110110101011 /
b10 1
b1001010 (
b1000001 )
b1 %
b1 ,
b10010101000010010000101100101010 $
b10010101000010010000101100101010 +
b1101000011101000000110011010000 #
b1101000011101000000110011010000 *
#660
b1011101011001100111110010111001 -
b10000010100010001000100 &
b1011101011001100111110010111001 !
b1011101011001100111110010111001 .
b1001101010111101011110010011010 0
b11101110010111011010110111011100 /
b100 1
b1001100 (
b1000010 )
b10 %
b10 ,
b10000111011011111100111100001110 $
b10000111011011111100111100001110 +
b11010101111101101010110110101011 #
b11010101111101101010110110101011 *
#670
b10100000111111101111000101000010 -
1"
b100000101001110010001000101111101001110 &
b10100010000000010000000101000100 !
b10100010000000010000000101000100 .
b1100001111100010000001011000011 0
b1111110110111110111001011111101 /
b101 1
b1001101 (
b1000011 )
b100 %
b100 ,
b1001101010111101011110010011010 $
b1001101010111101011110010011010 +
b11101110010111011010110111011100 #
b11101110010111011010110111011100 *
#680
b11100111011100111000000111010 -
0"
b1001111010100100101111101001110 &
b11111110110111111111111111111101 !
b11111110110111111111111111111101 .
b10100111011110011110100101001110 0
b10101011000011101110110101010110 /
b110 1
b1001110 (
b1000100 )
b101 %
b101 ,
b1100001111100010000001011000011 $
b1100001111100010000001011000011 +
b1111110110111110111001011111101 #
b1111110110111110111001011111101 *
#690
b11100101010000010000001000 -
b10100110101010101000010 &
b11100101010000010000001000 !
b11100101010000010000001000 .
b101001100010011010000001010 0
b110011110110010111011001100111 /
b111 1
b1001111 (
b1000101 )
b110 %
b110 ,
b10100111011110011110100101001110 $
b10100111011110011110100101001110 +
b10101011000011101110110101010110 #
b10101011000011101110110101010110 *
#700
b101110101010000100001001011101 -
b10100110100110001010100 &
b0 !
b0 .
b11100000011101000101000111000 0
b11011011011011111011100110110110 /
b0 1
b1010000 (
b1000110 )
b111 %
b111 ,
b101001100010011010000001010 $
b101001100010011010000001010 +
b110011110110010111011001100111 #
b110011110110010111011001100111 *
