06_sram_extension/spsram.v
module spsram
#(
	parameter BW_DATA = 32,
	parameter BW_ADDR = 8
)(
	output		[BW_DATA-1:0]	o_data,
	input		[BW_DATA-1:0]	i_data,
	input		[BW_ADDR-1:0]	i_addr,
	input						i_wen,
	input						i_cen,
	input						i_oen,
	input						i_clk
);

	reg		[BW_DATA-1:0]	mem[0:2**BW_ADDR-1];
	always @(posedge i_clk) begin
		if (i_cen && i_wen) begin
			mem[i_addr]	<= i_data;
		end
		else begin
			mem[i_addr]	<= mem[i_addr];
		end
	end	

	`ifdef	SPSRAM_ASYNC
		assign o_data	=	!i_oen			 ? 'bz :
							i_cen &&  !i_wen ? mem[i_addr] : 'bz;
	`else
		reg		[BW_DATA-1:0] o_data;
		always @(posedge i_clk) begin
			if (i_oen) begin
				if (i_cen && !i_wen) begin
					o_data	<= mem[i_addr];
				end	
				else begin
					o_data <= 'bz;
				end	
			end 
			else begin
				o_data	<= 'bz;
			end	
		end	
	`endif
endmodule

06_sram_extension/sram_extension.v
`include "spsram.v"

module sram_extension
(
	output		[63:0]	o_data,
	input		[63:0]	i_data,
	input		[5:0]	i_addr,
	input				i_wen,
	input				i_oen,
	input				i_clk
);

	wire		[31:0]	w_o_data[1:0];	// i/o data is divided to 2 parts
	wire		[31:0]	w_i_data[1:0];	// chip select
	reg			[3:0]	cen;

	assign o_data 						= {w_o_data[1], w_o_data[0]};
	assign {w_i_data[1], w_i_data[0]}	= i_data;
	
	always @(*) begin
		case (i_addr[5:4])				// 2 out of 8 chips are activated for each case.
			2'h0 : cen = 4'b0001;
			2'h1 : cen = 4'b0010;
			2'h2 : cen = 4'b0100;
			2'h3 : cen = 4'b1000;
		endcase
	end

	genvar i, j;
	generate 
		for (i=0; i<4; i=i+1) begin		// i==0 : lowest mem addresses, i==3 : highest mem addresses
			for (j=0; j<2; j=j+1) begin	// j==0 : lower 32-bit data, j==1 : upper 32-bit data
				spsram
				#(
					.BW_DATA		(32           	),
					.BW_ADDR		(4            	)
				)
				u_spsram(
					.o_data			(w_o_data[j]	),
					.i_data			(w_i_data[j]	),
					.i_addr			(i_addr[3:0]  	),
					.i_wen			(i_wen			),
					.i_cen			(cen[i]       	),
					.i_oen			(i_oen			),
					.i_clk			(i_clk        	)
				);
			end
		end
	endgenerate
endmodule

06_sram_extension/sram_extension_tb.v
// --------------------------------------------------
//	Define Global Variables
// --------------------------------------------------
`define	CLKFREQ		100		// Clock Freq. (Unit: MHz)
`define	SIMCYCLE	64		// Sim. Cycles

// --------------------------------------------------
//	Includes
// --------------------------------------------------
`include	"sram_extension.v"

module sram_extension_tb;
// --------------------------------------------------
//	DUT Signals & Instantiate
// --------------------------------------------------

	wire	[63:0]	o_data;
	reg		[63:0]	i_data;
	reg		[5:0]	i_addr;
	reg				i_wen;
	reg				i_oen;
	reg				i_clk;

	sram_extension
	u_sram_extension(
		.o_data				(o_data				),
		.i_data				(i_data				),
		.i_addr				(i_addr				),
		.i_wen				(i_wen				),
		.i_oen				(i_oen				),
		.i_clk				(i_clk				)
	);
	
// --------------------------------------------------
//	Clock
// --------------------------------------------------
	always	#(500/`CLKFREQ)		i_clk = ~i_clk;

// --------------------------------------------------
//	Tasks
// --------------------------------------------------
	reg		[4*32-1:0]	taskState;

	task init;
		begin
			taskState		= "Init";
			i_data				= 0;
			i_addr				= 0;
			i_wen				= 0;
			i_oen				= 0;
			i_clk				= 0;
		end
	endtask

	task memWR;
		input [63:0]	ti_data;
		input [5:0]		ti_addr;
		begin
			@(negedge i_clk) begin
				i_data		= ti_data;
				i_addr		= ti_addr;
				i_wen		= 1;
				i_oen		= 0;
			end
		end
	endtask
	
	task memRD;
		input	[5:0]	ti_addr;
		begin
			@(negedge i_clk) begin
				i_addr		= ti_addr;
				i_wen		= 0;
				i_oen		= 1;
			end
		end
	endtask

// --------------------------------------------------
//	Test Stimulus
// --------------------------------------------------
	integer		i, j;
	initial begin
		init();
		#(1000/`CLKFREQ);
		for (i=0; i<`SIMCYCLE; i=i+1) begin
			memWR(i,i);
		end
		for (i=0; i<`SIMCYCLE; i=i+1) begin
			memRD(i);
		end
		#(1000/`CLKFREQ);
		i_oen = 0;
		for (i=0; i<20; i=i+1) begin
			#(1000/`CLKFREQ);
		end
		$finish;
	end
	
	always @(*) begin
		case ({i_wen, i_oen})
			2'b00 : taskState = "STANDBY";
			2'b01 : begin
				case (u_sram_extension.cen)
					4'b0001 : taskState = "RD_C0X";
					4'b0010 : taskState = "RD_C1X";
					4'b0100 : taskState = "RD_C2X";
					4'b1000 : taskState = "RD_C3X";
				endcase
			end
			2'b10 : begin
				case (u_sram_extension.cen)
					4'b0001 : taskState = "WR_C0X";
					4'b0010 : taskState = "WR_C1X";
					4'b0100 : taskState = "WR_C2X";
					4'b1000 : taskState = "WR_C3X";
				endcase
			end
			default : taskState = "NOT_ALLOWED";
		endcase
	end

// --------------------------------------------------
//	Dump VCD
// --------------------------------------------------
	reg	[8*32-1:0]	vcd_file;
	initial begin
		if ($value$plusargs("vcd_file=%s", vcd_file)) begin
			$dumpfile(vcd_file);
			$dumpvars;
			for (j=0; j<16; j=j+1) begin
				$dumpvars(0, u_sram_extension.genblk1[0].genblk2[0].u_spsram.mem[j]); // mem of chip0l
				$dumpvars(0, u_sram_extension.genblk1[0].genblk2[1].u_spsram.mem[j]); // mem of chip0h
				$dumpvars(0, u_sram_extension.genblk1[1].genblk2[0].u_spsram.mem[j]); // mem of chip1l
				$dumpvars(0, u_sram_extension.genblk1[1].genblk2[1].u_spsram.mem[j]); // mem of chip1h
			end
		end else begin
			$dumpfile("sram_extension_tb.vcd");
			$dumpvars;
		end
	end

endmodule

06_sram_extension/vcd/sram_extension.vcd
$date
	Thu Jul  4 10:57:42 2024
$end
$version
	Icarus Verilog
$end
$timescale
	1s
$end
$scope module sram_extension_tb $end
$var wire 64 ! o_data [63:0] $end
$var reg 6 " i_addr [5:0] $end
$var reg 1 # i_clk $end
$var reg 64 $ i_data [63:0] $end
$var reg 1 % i_oen $end
$var reg 1 & i_wen $end
$var reg 128 ' taskState [127:0] $end
$var reg 256 ( vcd_file [255:0] $end
$var integer 32 ) i [31:0] $end
$var integer 32 * j [31:0] $end
$scope module u_sram_extension $end
$var wire 6 + i_addr [5:0] $end
$var wire 1 # i_clk $end
$var wire 64 , i_data [63:0] $end
$var wire 1 % i_oen $end
$var wire 1 & i_wen $end
$var wire 64 - o_data [63:0] $end
$var reg 4 . cen [3:0] $end
$scope begin genblk1[0] $end
$scope begin genblk2[0] $end
$scope module u_spsram $end
$var wire 4 / i_addr [3:0] $end
$var wire 1 0 i_cen $end
$var wire 1 # i_clk $end
$var wire 32 1 i_data [31:0] $end
$var wire 1 % i_oen $end
$var wire 1 & i_wen $end
$var reg 32 2 o_data [31:0] $end
$upscope $end
$upscope $end
$scope begin genblk2[1] $end
$scope module u_spsram $end
$var wire 4 3 i_addr [3:0] $end
$var wire 1 4 i_cen $end
$var wire 1 # i_clk $end
$var wire 32 5 i_data [31:0] $end
$var wire 1 % i_oen $end
$var wire 1 & i_wen $end
$var reg 32 6 o_data [31:0] $end
$upscope $end
$upscope $end
$upscope $end
$scope begin genblk1[1] $end
$scope begin genblk2[0] $end
$scope module u_spsram $end
$var wire 4 7 i_addr [3:0] $end
$var wire 1 8 i_cen $end
$var wire 1 # i_clk $end
$var wire 32 9 i_data [31:0] $end
$var wire 1 % i_oen $end
$var wire 1 & i_wen $end
$var reg 32 : o_data [31:0] $end
$upscope $end
$upscope $end
$scope begin genblk2[1] $end
$scope module u_spsram $end
$var wire 4 ; i_addr [3:0] $end
$var wire 1 < i_cen $end
$var wire 1 # i_clk $end
$var wire 32 = i_data [31:0] $end
$var wire 1 % i_oen $end
$var wire 1 & i_wen $end
$var reg 32 > o_data [31:0] $end
$upscope $end
$upscope $end
$upscope $end
$scope begin genblk1[2] $end
$scope begin genblk2[0] $end
$scope module u_spsram $end
$var wire 4 ? i_addr [3:0] $end
$var wire 1 @ i_cen $end
$var wire 1 # i_clk $end
$var wire 32 A i_data [31:0] $end
$var wire 1 % i_oen $end
$var wire 1 & i_wen $end
$var reg 32 B o_data [31:0] $end
$upscope $end
$upscope $end
$scope begin genblk2[1] $end
$scope module u_spsram $end
$var wire 4 C i_addr [3:0] $end
$var wire 1 D i_cen $end
$var wire 1 # i_clk $end
$var wire 32 E i_data [31:0] $end
$var wire 1 % i_oen $end
$var wire 1 & i_wen $end
$var reg 32 F o_data [31:0] $end
$upscope $end
$upscope $end
$upscope $end
$scope begin genblk1[3] $end
$scope begin genblk2[0] $end
$scope module u_spsram $end
$var wire 4 G i_addr [3:0] $end
$var wire 1 H i_cen $end
$var wire 1 # i_clk $end
$var wire 32 I i_data [31:0] $end
$var wire 1 % i_oen $end
$var wire 1 & i_wen $end
$var reg 32 J o_data [31:0] $end
$upscope $end
$upscope $end
$scope begin genblk2[1] $end
$scope module u_spsram $end
$var wire 4 K i_addr [3:0] $end
$var wire 1 L i_cen $end
$var wire 1 # i_clk $end
$var wire 32 M i_data [31:0] $end
$var wire 1 % i_oen $end
$var wire 1 & i_wen $end
$var reg 32 N o_data [31:0] $end
$upscope $end
$upscope $end
$upscope $end
$upscope $end
$scope task init $end
$upscope $end
$scope task memRD $end
$var reg 6 O ti_addr [5:0] $end
$upscope $end
$scope task memWR $end
$var reg 6 P ti_addr [5:0] $end
$var reg 64 Q ti_data [63:0] $end
$upscope $end
$upscope $end
$scope module sram_extension_tb $end
$scope module u_sram_extension $end
$scope begin genblk1[0] $end
$scope begin genblk2[0] $end
$scope module u_spsram $end
$var reg 32 R \mem[0] [31:0] $end
$upscope $end
$upscope $end
$upscope $end
$upscope $end
$upscope $end
$scope module sram_extension_tb $end
$scope module u_sram_extension $end
$scope begin genblk1[0] $end
$scope begin genblk2[1] $end
$scope module u_spsram $end
$var reg 32 S \mem[0] [31:0] $end
$upscope $end
$upscope $end
$upscope $end
$upscope $end
$upscope $end
$scope module sram_extension_tb $end
$scope module u_sram_extension $end
$scope begin genblk1[1] $end
$scope begin genblk2[0] $end
$scope module u_spsram $end
$var reg 32 T \mem[0] [31:0] $end
$upscope $end
$upscope $end
$upscope $end
$upscope $end
$upscope $end
$scope module sram_extension_tb $end
$scope module u_sram_extension $end
$scope begin genblk1[1] $end
$scope begin genblk2[1] $end
$scope module u_spsram $end
$var reg 32 U \mem[0] [31:0] $end
$upscope $end
$upscope $end
$upscope $end
$upscope $end
$upscope $end
$scope module sram_extension_tb $end
$scope module u_sram_extension $end
$scope begin genblk1[0] $end
$scope begin genblk2[0] $end
$scope module u_spsram $end
$var reg 32 V \mem[1] [31:0] $end
$upscope $end
$upscope $end
$upscope $end
$upscope $end
$upscope $end
$scope module sram_extension_tb $end
$scope module u_sram_extension $end
$scope begin genblk1[0] $end
$scope begin genblk2[1] $end
$scope module u_spsram $end
$var reg 32 W \mem[1] [31:0] $end
$upscope $end
$upscope $end
$upscope $end
$upscope $end
$upscope $end
$scope module sram_extension_tb $end
$scope module u_sram_extension $end
$scope begin genblk1[1] $end
$scope begin genblk2[0] $end
$scope module u_spsram $end
$var reg 32 X \mem[1] [31:0] $end
$upscope $end
$upscope $end
$upscope $end
$upscope $end
$upscope $end
$scope module sram_extension_tb $end
$scope module u_sram_extension $end
$scope begin genblk1[1] $end
$scope begin genblk2[1] $end
$scope module u_spsram $end
$var reg 32 Y \mem[1] [31:0] $end
$upscope $end
$upscope $end
$upscope $end
$upscope $end
$upscope $end
$scope module sram_extension_tb $end
$scope module u_sram_extension $end
$scope begin genblk1[0] $end
$scope begin genblk2[0] $end
$scope module u_spsram $end
$var reg 32 Z \mem[2] [31:0] $end
$upscope $end
$upscope $end
$upscope $end
$upscope $end
$upscope $end
$scope module sram_extension_tb $end
$scope module u_sram_extension $end
$scope begin genblk1[0] $end
$scope begin genblk2[1] $end
$scope module u_spsram $end
$var reg 32 [ \mem[2] [31:0] $end
$upscope $end
$upscope $end
$upscope $end
$upscope $end
$upscope $end
$scope module sram_extension_tb $end
$scope module u_sram_extension $end
$scope begin genblk1[1] $end
$scope begin genblk2[0] $end
$scope module u_spsram $end
$var reg 32 \ \mem[2] [31:0] $end
$upscope $end
$upscope $end
$upscope $end
$upscope $end
$upscope $end
$scope module sram_extension_tb $end
$scope module u_sram_extension $end
$scope begin genblk1[1] $end
$scope begin genblk2[1] $end
$scope module u_spsram $end
$var reg 32 ] \mem[2] [31:0] $end
$upscope $end
$upscope $end
$upscope $end
$upscope $end
$upscope $end
$scope module sram_extension_tb $end
$scope module u_sram_extension $end
$scope begin genblk1[0] $end
$scope begin genblk2[0] $end
$scope module u_spsram $end
$var reg 32 ^ \mem[3] [31:0] $end
$upscope $end
$upscope $end
$upscope $end
$upscope $end
$upscope $end
$scope module sram_extension_tb $end
$scope module u_sram_extension $end
$scope begin genblk1[0] $end
$scope begin genblk2[1] $end
$scope module u_spsram $end
$var reg 32 _ \mem[3] [31:0] $end
$upscope $end
$upscope $end
$upscope $end
$upscope $end
$upscope $end
$scope module sram_extension_tb $end
$scope module u_sram_extension $end
$scope begin genblk1[1] $end
$scope begin genblk2[0] $end
$scope module u_spsram $end
$var reg 32 ` \mem[3] [31:0] $end
$upscope $end
$upscope $end
$upscope $end
$upscope $end
$upscope $end
$scope module sram_extension_tb $end
$scope module u_sram_extension $end
$scope begin genblk1[1] $end
$scope begin genblk2[1] $end
$scope module u_spsram $end
$var reg 32 a \mem[3] [31:0] $end
$upscope $end
$upscope $end
$upscope $end
$upscope $end
$upscope $end
$scope module sram_extension_tb $end
$scope module u_sram_extension $end
$scope begin genblk1[0] $end
$scope begin genblk2[0] $end
$scope module u_spsram $end
$var reg 32 b \mem[4] [31:0] $end
$upscope $end
$upscope $end
$upscope $end
$upscope $end
$upscope $end
$scope module sram_extension_tb $end
$scope module u_sram_extension $end
$scope begin genblk1[0] $end
$scope begin genblk2[1] $end
$scope module u_spsram $end
$var reg 32 c \mem[4] [31:0] $end
$upscope $end
$upscope $end
$upscope $end
$upscope $end
$upscope $end
$scope module sram_extension_tb $end
$scope module u_sram_extension $end
$scope begin genblk1[1] $end
$scope begin genblk2[0] $end
$scope module u_spsram $end
$var reg 32 d \mem[4] [31:0] $end
$upscope $end
$upscope $end
$upscope $end
$upscope $end
$upscope $end
$scope module sram_extension_tb $end
$scope module u_sram_extension $end
$scope begin genblk1[1] $end
$scope begin genblk2[1] $end
$scope module u_spsram $end
$var reg 32 e \mem[4] [31:0] $end
$upscope $end
$upscope $end
$upscope $end
$upscope $end
$upscope $end
$scope module sram_extension_tb $end
$scope module u_sram_extension $end
$scope begin genblk1[0] $end
$scope begin genblk2[0] $end
$scope module u_spsram $end
$var reg 32 f \mem[5] [31:0] $end
$upscope $end
$upscope $end
$upscope $end
$upscope $end
$upscope $end
$scope module sram_extension_tb $end
$scope module u_sram_extension $end
$scope begin genblk1[0] $end
$scope begin genblk2[1] $end
$scope module u_spsram $end
$var reg 32 g \mem[5] [31:0] $end
$upscope $end
$upscope $end
$upscope $end
$upscope $end
$upscope $end
$scope module sram_extension_tb $end
$scope module u_sram_extension $end
$scope begin genblk1[1] $end
$scope begin genblk2[0] $end
$scope module u_spsram $end
$var reg 32 h \mem[5] [31:0] $end
$upscope $end
$upscope $end
$upscope $end
$upscope $end
$upscope $end
$scope module sram_extension_tb $end
$scope module u_sram_extension $end
$scope begin genblk1[1] $end
$scope begin genblk2[1] $end
$scope module u_spsram $end
$var reg 32 i \mem[5] [31:0] $end
$upscope $end
$upscope $end
$upscope $end
$upscope $end
$upscope $end
$scope module sram_extension_tb $end
$scope module u_sram_extension $end
$scope begin genblk1[0] $end
$scope begin genblk2[0] $end
$scope module u_spsram $end
$var reg 32 j \mem[6] [31:0] $end
$upscope $end
$upscope $end
$upscope $end
$upscope $end
$upscope $end
$scope module sram_extension_tb $end
$scope module u_sram_extension $end
$scope begin genblk1[0] $end
$scope begin genblk2[1] $end
$scope module u_spsram $end
$var reg 32 k \mem[6] [31:0] $end
$upscope $end
$upscope $end
$upscope $end
$upscope $end
$upscope $end
$scope module sram_extension_tb $end
$scope module u_sram_extension $end
$scope begin genblk1[1] $end
$scope begin genblk2[0] $end
$scope module u_spsram $end
$var reg 32 l \mem[6] [31:0] $end
$upscope $end
$upscope $end
$upscope $end
$upscope $end
$upscope $end
$scope module sram_extension_tb $end
$scope module u_sram_extension $end
$scope begin genblk1[1] $end
$scope begin genblk2[1] $end
$scope module u_spsram $end
$var reg 32 m \mem[6] [31:0] $end
$upscope $end
$upscope $end
$upscope $end
$upscope $end
$upscope $end
$scope module sram_extension_tb $end
$scope module u_sram_extension $end
$scope begin genblk1[0] $end
$scope begin genblk2[0] $end
$scope module u_spsram $end
$var reg 32 n \mem[7] [31:0] $end
$upscope $end
$upscope $end
$upscope $end
$upscope $end
$upscope $end
$scope module sram_extension_tb $end
$scope module u_sram_extension $end
$scope begin genblk1[0] $end
$scope begin genblk2[1] $end
$scope module u_spsram $end
$var reg 32 o \mem[7] [31:0] $end
$upscope $end
$upscope $end
$upscope $end
$upscope $end
$upscope $end
$scope module sram_extension_tb $end
$scope module u_sram_extension $end
$scope begin genblk1[1] $end
$scope begin genblk2[0] $end
$scope module u_spsram $end
$var reg 32 p \mem[7] [31:0] $end
$upscope $end
$upscope $end
$upscope $end
$upscope $end
$upscope $end
$scope module sram_extension_tb $end
$scope module u_sram_extension $end
$scope begin genblk1[1] $end
$scope begin genblk2[1] $end
$scope module u_spsram $end
$var reg 32 q \mem[7] [31:0] $end
$upscope $end
$upscope $end
$upscope $end
$upscope $end
$upscope $end
$scope module sram_extension_tb $end
$scope module u_sram_extension $end
$scope begin genblk1[0] $end
$scope begin genblk2[0] $end
$scope module u_spsram $end
$var reg 32 r \mem[8] [31:0] $end
$upscope $end
$upscope $end
$upscope $end
$upscope $end
$upscope $end
$scope module sram_extension_tb $end
$scope module u_sram_extension $end
$scope begin genblk1[0] $end
$scope begin genblk2[1] $end
$scope module u_spsram $end
$var reg 32 s \mem[8] [31:0] $end
$upscope $end
$upscope $end
$upscope $end
$upscope $end
$upscope $end
$scope module sram_extension_tb $end
$scope module u_sram_extension $end
$scope begin genblk1[1] $end
$scope begin genblk2[0] $end
$scope module u_spsram $end
$var reg 32 t \mem[8] [31:0] $end
$upscope $end
$upscope $end
$upscope $end
$upscope $end
$upscope $end
$scope module sram_extension_tb $end
$scope module u_sram_extension $end
$scope begin genblk1[1] $end
$scope begin genblk2[1] $end
$scope module u_spsram $end
$var reg 32 u \mem[8] [31:0] $end
$upscope $end
$upscope $end
$upscope $end
$upscope $end
$upscope $end
$scope module sram_extension_tb $end
$scope module u_sram_extension $end
$scope begin genblk1[0] $end
$scope begin genblk2[0] $end
$scope module u_spsram $end
$var reg 32 v \mem[9] [31:0] $end
$upscope $end
$upscope $end
$upscope $end
$upscope $end
$upscope $end
$scope module sram_extension_tb $end
$scope module u_sram_extension $end
$scope begin genblk1[0] $end
$scope begin genblk2[1] $end
$scope module u_spsram $end
$var reg 32 w \mem[9] [31:0] $end
$upscope $end
$upscope $end
$upscope $end
$upscope $end
$upscope $end
$scope module sram_extension_tb $end
$scope module u_sram_extension $end
$scope begin genblk1[1] $end
$scope begin genblk2[0] $end
$scope module u_spsram $end
$var reg 32 x \mem[9] [31:0] $end
$upscope $end
$upscope $end
$upscope $end
$upscope $end
$upscope $end
$scope module sram_extension_tb $end
$scope module u_sram_extension $end
$scope begin genblk1[1] $end
$scope begin genblk2[1] $end
$scope module u_spsram $end
$var reg 32 y \mem[9] [31:0] $end
$upscope $end
$upscope $end
$upscope $end
$upscope $end
$upscope $end
$scope module sram_extension_tb $end
$scope module u_sram_extension $end
$scope begin genblk1[0] $end
$scope begin genblk2[0] $end
$scope module u_spsram $end
$var reg 32 z \mem[10] [31:0] $end
$upscope $end
$upscope $end
$upscope $end
$upscope $end
$upscope $end
$scope module sram_extension_tb $end
$scope module u_sram_extension $end
$scope begin genblk1[0] $end
$scope begin genblk2[1] $end
$scope module u_spsram $end
$var reg 32 { \mem[10] [31:0] $end
$upscope $end
$upscope $end
$upscope $end
$upscope $end
$upscope $end
$scope module sram_extension_tb $end
$scope module u_sram_extension $end
$scope begin genblk1[1] $end
$scope begin genblk2[0] $end
$scope module u_spsram $end
$var reg 32 | \mem[10] [31:0] $end
$upscope $end
$upscope $end
$upscope $end
$upscope $end
$upscope $end
$scope module sram_extension_tb $end
$scope module u_sram_extension $end
$scope begin genblk1[1] $end
$scope begin genblk2[1] $end
$scope module u_spsram $end
$var reg 32 } \mem[10] [31:0] $end
$upscope $end
$upscope $end
$upscope $end
$upscope $end
$upscope $end
$scope module sram_extension_tb $end
$scope module u_sram_extension $end
$scope begin genblk1[0] $end
$scope begin genblk2[0] $end
$scope module u_spsram $end
$var reg 32 ~ \mem[11] [31:0] $end
$upscope $end
$upscope $end
$upscope $end
$upscope $end
$upscope $end
$scope module sram_extension_tb $end
$scope module u_sram_extension $end
$scope begin genblk1[0] $end
$scope begin genblk2[1] $end
$scope module u_spsram $end
$var reg 32 !" \mem[11] [31:0] $end
$upscope $end
$upscope $end
$upscope $end
$upscope $end
$upscope $end
$scope module sram_extension_tb $end
$scope module u_sram_extension $end
$scope begin genblk1[1] $end
$scope begin genblk2[0] $end
$scope module u_spsram $end
$var reg 32 "" \mem[11] [31:0] $end
$upscope $end
$upscope $end
$upscope $end
$upscope $end
$upscope $end
$scope module sram_extension_tb $end
$scope module u_sram_extension $end
$scope begin genblk1[1] $end
$scope begin genblk2[1] $end
$scope module u_spsram $end
$var reg 32 #" \mem[11] [31:0] $end
$upscope $end
$upscope $end
$upscope $end
$upscope $end
$upscope $end
$scope module sram_extension_tb $end
$scope module u_sram_extension $end
$scope begin genblk1[0] $end
$scope begin genblk2[0] $end
$scope module u_spsram $end
$var reg 32 $" \mem[12] [31:0] $end
$upscope $end
$upscope $end
$upscope $end
$upscope $end
$upscope $end
$scope module sram_extension_tb $end
$scope module u_sram_extension $end
$scope begin genblk1[0] $end
$scope begin genblk2[1] $end
$scope module u_spsram $end
$var reg 32 %" \mem[12] [31:0] $end
$upscope $end
$upscope $end
$upscope $end
$upscope $end
$upscope $end
$scope module sram_extension_tb $end
$scope module u_sram_extension $end
$scope begin genblk1[1] $end
$scope begin genblk2[0] $end
$scope module u_spsram $end
$var reg 32 &" \mem[12] [31:0] $end
$upscope $end
$upscope $end
$upscope $end
$upscope $end
$upscope $end
$scope module sram_extension_tb $end
$scope module u_sram_extension $end
$scope begin genblk1[1] $end
$scope begin genblk2[1] $end
$scope module u_spsram $end
$var reg 32 '" \mem[12] [31:0] $end
$upscope $end
$upscope $end
$upscope $end
$upscope $end
$upscope $end
$scope module sram_extension_tb $end
$scope module u_sram_extension $end
$scope begin genblk1[0] $end
$scope begin genblk2[0] $end
$scope module u_spsram $end
$var reg 32 (" \mem[13] [31:0] $end
$upscope $end
$upscope $end
$upscope $end
$upscope $end
$upscope $end
$scope module sram_extension_tb $end
$scope module u_sram_extension $end
$scope begin genblk1[0] $end
$scope begin genblk2[1] $end
$scope module u_spsram $end
$var reg 32 )" \mem[13] [31:0] $end
$upscope $end
$upscope $end
$upscope $end
$upscope $end
$upscope $end
$scope module sram_extension_tb $end
$scope module u_sram_extension $end
$scope begin genblk1[1] $end
$scope begin genblk2[0] $end
$scope module u_spsram $end
$var reg 32 *" \mem[13] [31:0] $end
$upscope $end
$upscope $end
$upscope $end
$upscope $end
$upscope $end
$scope module sram_extension_tb $end
$scope module u_sram_extension $end
$scope begin genblk1[1] $end
$scope begin genblk2[1] $end
$scope module u_spsram $end
$var reg 32 +" \mem[13] [31:0] $end
$upscope $end
$upscope $end
$upscope $end
$upscope $end
$upscope $end
$scope module sram_extension_tb $end
$scope module u_sram_extension $end
$scope begin genblk1[0] $end
$scope begin genblk2[0] $end
$scope module u_spsram $end
$var reg 32 ," \mem[14] [31:0] $end
$upscope $end
$upscope $end
$upscope $end
$upscope $end
$upscope $end
$scope module sram_extension_tb $end
$scope module u_sram_extension $end
$scope begin genblk1[0] $end
$scope begin genblk2[1] $end
$scope module u_spsram $end
$var reg 32 -" \mem[14] [31:0] $end
$upscope $end
$upscope $end
$upscope $end
$upscope $end
$upscope $end
$scope module sram_extension_tb $end
$scope module u_sram_extension $end
$scope begin genblk1[1] $end
$scope begin genblk2[0] $end
$scope module u_spsram $end
$var reg 32 ." \mem[14] [31:0] $end
$upscope $end
$upscope $end
$upscope $end
$upscope $end
$upscope $end
$scope module sram_extension_tb $end
$scope module u_sram_extension $end
$scope begin genblk1[1] $end
$scope begin genblk2[1] $end
$scope module u_spsram $end
$var reg 32 /" \mem[14] [31:0] $end
$upscope $end
$upscope $end
$upscope $end
$upscope $end
$upscope $end
$scope module sram_extension_tb $end
$scope module u_sram_extension $end
$scope begin genblk1[0] $end
$scope begin genblk2[0] $end
$scope module u_spsram $end
$var reg 32 0" \mem[15] [31:0] $end
$upscope $end
$upscope $end
$upscope $end
$upscope $end
$upscope $end
$scope module sram_extension_tb $end
$scope module u_sram_extension $end
$scope begin genblk1[0] $end
$scope begin genblk2[1] $end
$scope module u_spsram $end
$var reg 32 1" \mem[15] [31:0] $end
$upscope $end
$upscope $end
$upscope $end
$upscope $end
$upscope $end
$scope module sram_extension_tb $end
$scope module u_sram_extension $end
$scope begin genblk1[1] $end
$scope begin genblk2[0] $end
$scope module u_spsram $end
$var reg 32 2" \mem[15] [31:0] $end
$upscope $end
$upscope $end
$upscope $end
$upscope $end
$upscope $end
$scope module sram_extension_tb $end
$scope module u_sram_extension $end
$scope begin genblk1[1] $end
$scope begin genblk2[1] $end
$scope module u_spsram $end
$var reg 32 3" \mem[15] [31:0] $end
$upscope $end
$upscope $end
$upscope $end
$upscope $end
$upscope $end
$enddefinitions $end
#0
$dumpvars
bx 3"
bx 2"
bx 1"
bx 0"
bx /"
bx ."
bx -"
bx ,"
bx +"
bx *"
bx )"
bx ("
bx '"
bx &"
bx %"
bx $"
bx #"
bx ""
bx !"
bx ~
bx }
bx |
bx {
bx z
bx y
bx x
bx w
bx v
bx u
bx t
bx s
bx r
bx q
bx p
bx o
bx n
bx m
bx l
bx k
bx j
bx i
bx h
bx g
bx f
bx e
bx d
bx c
bx b
bx a
bx `
bx _
bx ^
bx ]
bx \
bx [
bx Z
bx Y
bx X
bx W
bx V
bx U
bx T
bx S
bx R
bx Q
bx P
bx O
bx N
b0 M
0L
b0 K
bx J
b0 I
0H
b0 G
bx F
b0 E
0D
b0 C
bx B
b0 A
0@
b0 ?
bx >
b0 =
0<
b0 ;
bx :
b0 9
08
b0 7
bx 6
b0 5
14
b0 3
bx 2
b0 1
10
b0 /
b1 .
bx -
b0 ,
b0 +
b10000 *
bx )
b1011100010111101110110011000110110010000101111011100110111001001100001011011010101111101100101011110000111010001100101011011100111001101101001011011110110111000101110011101100110001101100100 (
b1010011010101000100000101001110010001000100001001011001 '
0&
0%
b0 $
0#
b0 "
bx !
$end
#5
bx R
bz 2
bx S
bz !
bz -
bz 6
bx T
bz :
bx U
bz >
bz B
bz F
bz J
bz N
1#
#10
b10101110101001001011111010000110011000001011000 '
1&
0#
b1 P
b1 Q
b1 )
#15
bx U
bx T
b0 S
b0 R
1#
#20
b1 /
b1 3
b1 7
b1 ;
b1 ?
b1 C
b1 G
b1 K
b1 1
b1 9
b1 A
b1 I
b10 P
b10 Q
b10 )
b1 "
b1 +
b1 $
b1 ,
0#
#25
b1 V
b0 W
bx X
bx Y
1#
#30
b10 /
b10 3
b10 7
b10 ;
b10 ?
b10 C
b10 G
b10 K
b10 1
b10 9
b10 A
b10 I
b11 P
b11 Q
b11 )
b10 "
b10 +
b10 $
b10 ,
0#
#35
bx ]
bx \
b0 [
b10 Z
1#
#40
b11 /
b11 3
b11 7
b11 ;
b11 ?
b11 C
b11 G
b11 K
b11 1
b11 9
b11 A
b11 I
b100 P
b100 Q
b100 )
b11 "
b11 +
b11 $
b11 ,
0#
#45
b11 ^
b0 _
bx `
bx a
1#
#50
b100 /
b100 3
b100 7
b100 ;
b100 ?
b100 C
b100 G
b100 K
b100 1
b100 9
b100 A
b100 I
b101 P
b101 Q
b101 )
b100 "
b100 +
b100 $
b100 ,
0#
#55
bx e
bx d
b0 c
b100 b
1#
#60
b101 /
b101 3
b101 7
b101 ;
b101 ?
b101 C
b101 G
b101 K
b101 1
b101 9
b101 A
b101 I
b110 P
b110 Q
b110 )
b101 "
b101 +
b101 $
b101 ,
0#
#65
b101 f
b0 g
bx h
bx i
1#
#70
b110 /
b110 3
b110 7
b110 ;
b110 ?
b110 C
b110 G
b110 K
b110 1
b110 9
b110 A
b110 I
b111 P
b111 Q
b111 )
b110 "
b110 +
b110 $
b110 ,
0#
#75
bx m
bx l
b0 k
b110 j
1#
#80
b111 /
b111 3
b111 7
b111 ;
b111 ?
b111 C
b111 G
b111 K
b111 1
b111 9
b111 A
b111 I
b1000 P
b1000 Q
b1000 )
b111 "
b111 +
b111 $
b111 ,
0#
#85
b111 n
b0 o
bx p
bx q
1#
#90
b1000 /
b1000 3
b1000 7
b1000 ;
b1000 ?
b1000 C
b1000 G
b1000 K
b1000 1
b1000 9
b1000 A
b1000 I
b1001 P
b1001 Q
b1001 )
b1000 "
b1000 +
b1000 $
b1000 ,
0#
#95
bx u
bx t
b0 s
b1000 r
1#
#100
b1001 /
b1001 3
b1001 7
b1001 ;
b1001 ?
b1001 C
b1001 G
b1001 K
b1001 1
b1001 9
b1001 A
b1001 I
b1010 P
b1010 Q
b1010 )
b1001 "
b1001 +
b1001 $
b1001 ,
0#
#105
b1001 v
b0 w
bx x
bx y
1#
