06_sram_extension/spsram.v
module spsram
#(
	parameter BW_DATA = 32,
	parameter BW_ADDR = 8
)(
	output		[BW_DATA-1:0]	o_data,
	input		[BW_DATA-1:0]	i_data,
	input		[BW_ADDR-1:0]	i_addr,
	input						i_wen,
	input						i_cen,
	input						i_oen,
	input						i_clk
);

	reg		[BW_DATA-1:0]	mem[0:2**BW_ADDR-1];
	always @(posedge i_clk) begin
		if (i_cen && i_wen) begin
			mem[i_addr]	<= i_data;
		end
		else begin
			mem[i_addr]	<= mem[i_addr];
		end
	end	

	`ifdef	SPSRAM_ASYNC
		assign o_data	=	!i_oen			 ? 'bz :
							i_cen &&  !i_wen ? mem[i_addr] : 'bz;
	`else
		reg		[BW_DATA-1:0] o_data;
		always @(posedge i_clk) begin
			if (i_oen) begin
				if (i_cen && !i_wen) begin
					o_data	<= mem[i_addr];
				end	
				else begin
					o_data <= 'bz;
				end	
			end 
			else begin
				o_data	<= 'bz;
			end	
		end	
	`endif
endmodule

06_sram_extension/sram_extension.v
`include "spsram.v"

module sram_extension
(
	output		[63:0]	o_data,
	input		[63:0]	i_data,
	input		[5:0]	i_addr,
	input				i_wen,
	input				i_oen,
	input				i_clk
);

	wire		[31:0]	w_o_data[1:0];
	wire		[31:0]	w_i_data[1:0];
	reg			[3:0]	cen;

	assign o_data 						= {w_o_data[1], w_o_data[0]};
	assign {w_i_data[1], w_i_data[0]}	= i_data;
	
	always @(*) begin
		case (i_addr[5:4])
			2'b00 : cen = 4'b0001;
			2'b01 : cen = 4'b0010;
			2'b10 : cen = 4'b0100;
			2'b11 : cen = 4'b1000;
		endcase
	end

	genvar i, j;
	generate 
		for (i=0; i<4; i=i+1) begin 	//  
			for (j=0; j<2; j=j+1) begin // j==0 : lower 32-bit, j==1 : upper 32-bit
				spsram
				#(
					.BW_DATA		(32           	),
					.BW_ADDR		(4            	)
				)
				u_spsram(
					.o_data			(w_o_data[j]	),
					.i_data			(w_i_data[j]	),
					.i_addr			(i_addr[3:0]  	),
					.i_wen			(i_wen			),
					.i_cen			(cen[i]       	),
					.i_oen			(i_oen			),
					.i_clk			(i_clk        	)
				);
			end
		end
	endgenerate

endmodule

06_sram_extension/sram_extension_tb.v
// --------------------------------------------------
//	Define Global Variables
// --------------------------------------------------
`define	CLKFREQ		100		// Clock Freq. (Unit: MHz)
`define	SIMCYCLE	64		// Sim. Cycles

// --------------------------------------------------
//	Includes
// --------------------------------------------------
`include	"sram_extension.v"

module sram_extension_tb;
// --------------------------------------------------
//	DUT Signals & Instantiate
// --------------------------------------------------

	wire	[63:0]	o_data;
	reg		[63:0]	i_data;
	reg		[5:0]	i_addr;
	reg				i_wen;
	reg				i_oen;
	reg				i_clk;

	sram_extension
	u_sram_extension(
		.o_data				(o_data				),
		.i_data				(i_data				),
		.i_addr				(i_addr				),
		.i_wen				(i_wen				),
		.i_oen				(i_oen				),
		.i_clk				(i_clk				)
	);
	
// --------------------------------------------------
//	Clock
// --------------------------------------------------
	always	#(500/`CLKFREQ)		i_clk = ~i_clk;

// --------------------------------------------------
//	Tasks
// --------------------------------------------------
	reg		[4*32-1:0]	taskState;

	task init;
		begin
			taskState		= "Init";
			i_data				= 0;
			i_addr				= 0;
			i_wen				= 0;
			i_oen				= 0;
			i_clk				= 0;
		end
	endtask

	task memWR;
		input [63:0]	ti_data;
		input [5:0]		ti_addr;
		begin
			@(negedge i_clk) begin
				i_data		= ti_data;
				i_addr		= ti_addr;
				i_wen		= 1;
				i_oen		= 0;
			end
		end
	endtask
	
	task memRD;
		input	[5:0]	ti_addr;
		begin
			@(negedge i_clk) begin
				i_addr		= ti_addr;
				i_wen		= 0;
				i_oen		= 1;
			end
		end
	endtask

// --------------------------------------------------
//	Test Stimulus
// --------------------------------------------------
	integer		i, j;
	initial begin
		init();
		#(1000/`CLKFREQ);
		for (i=0; i<`SIMCYCLE; i=i+1) begin
			memWR(i,i);
		end
		for (i=0; i<`SIMCYCLE; i=i+1) begin
			memRD(i);
		end
		#(1000/`CLKFREQ);
		i_oen = 0;
		for (i=0; i<20; i=i+1) begin
			#(1000/`CLKFREQ);
		end
		$finish;
	end
	
	always @(*) begin
		case ({i_wen, i_oen})
			2'b00 : taskState = "STANDBY";
			2'b01 : begin
				case (u_sram_extension.cen)
					4'b0001 : taskState = "RD_C0X";
					4'b0010 : taskState = "RD_C1X";
					4'b0100 : taskState = "RD_C2X";
					4'b1000 : taskState = "RD_C3X";
				endcase
			end
			2'b10 : begin
				case (u_sram_extension.cen)
					4'b0001 : taskState = "WR_C0X";
					4'b0010 : taskState = "WR_C1X";
					4'b0100 : taskState = "WR_C2X";
					4'b1000 : taskState = "WR_C3X";
				endcase
			end
			default : taskState = "NOT_ALLOWED";
		endcase
	end

// --------------------------------------------------
//	Dump VCD
// --------------------------------------------------
	reg	[8*32-1:0]	vcd_file;
	initial begin
		if ($value$plusargs("vcd_file=%s", vcd_file)) begin
			$dumpfile(vcd_file);
			$dumpvars;
		end else begin
			$dumpfile("sram_extension_tb.vcd");
			$dumpvars;
		end
	end

endmodule

06_sram_extension/vcd/sram_extension.vcd
$date
	Thu Jul  4 09:20:12 2024
$end
$version
	Icarus Verilog
$end
$timescale
	1s
$end
$scope module sram_extension_tb $end
$var wire 64 ! o_data [63:0] $end
$var reg 6 " i_addr [5:0] $end
$var reg 1 # i_clk $end
$var reg 64 $ i_data [63:0] $end
$var reg 1 % i_oen $end
$var reg 1 & i_wen $end
$var reg 128 ' taskState [127:0] $end
$var reg 256 ( vcd_file [255:0] $end
$var integer 32 ) i [31:0] $end
$scope module u_sram_extension $end
$var wire 6 * i_addr [5:0] $end
$var wire 1 # i_clk $end
$var wire 64 + i_data [63:0] $end
$var wire 1 % i_oen $end
$var wire 1 & i_wen $end
$var wire 64 , o_data [63:0] $end
$var reg 4 - cen [3:0] $end
$scope begin genblk1[0] $end
$scope begin genblk2[0] $end
$scope module u_spsram $end
$var wire 4 . i_addr [3:0] $end
$var wire 1 / i_cen $end
$var wire 1 # i_clk $end
$var wire 32 0 i_data [31:0] $end
$var wire 1 % i_oen $end
$var wire 1 & i_wen $end
$var reg 32 1 o_data [31:0] $end
$upscope $end
$upscope $end
$scope begin genblk2[1] $end
$scope module u_spsram $end
$var wire 4 2 i_addr [3:0] $end
$var wire 1 3 i_cen $end
$var wire 1 # i_clk $end
$var wire 32 4 i_data [31:0] $end
$var wire 1 % i_oen $end
$var wire 1 & i_wen $end
$var reg 32 5 o_data [31:0] $end
$upscope $end
$upscope $end
$upscope $end
$scope begin genblk1[1] $end
$scope begin genblk2[0] $end
$scope module u_spsram $end
$var wire 4 6 i_addr [3:0] $end
$var wire 1 7 i_cen $end
$var wire 1 # i_clk $end
$var wire 32 8 i_data [31:0] $end
$var wire 1 % i_oen $end
$var wire 1 & i_wen $end
$var reg 32 9 o_data [31:0] $end
$upscope $end
$upscope $end
$scope begin genblk2[1] $end
$scope module u_spsram $end
$var wire 4 : i_addr [3:0] $end
$var wire 1 ; i_cen $end
$var wire 1 # i_clk $end
$var wire 32 < i_data [31:0] $end
$var wire 1 % i_oen $end
$var wire 1 & i_wen $end
$var reg 32 = o_data [31:0] $end
$upscope $end
$upscope $end
$upscope $end
$scope begin genblk1[2] $end
$scope begin genblk2[0] $end
$scope module u_spsram $end
$var wire 4 > i_addr [3:0] $end
$var wire 1 ? i_cen $end
$var wire 1 # i_clk $end
$var wire 32 @ i_data [31:0] $end
$var wire 1 % i_oen $end
$var wire 1 & i_wen $end
$var reg 32 A o_data [31:0] $end
$upscope $end
$upscope $end
$scope begin genblk2[1] $end
$scope module u_spsram $end
$var wire 4 B i_addr [3:0] $end
$var wire 1 C i_cen $end
$var wire 1 # i_clk $end
$var wire 32 D i_data [31:0] $end
$var wire 1 % i_oen $end
$var wire 1 & i_wen $end
$var reg 32 E o_data [31:0] $end
$upscope $end
$upscope $end
$upscope $end
$scope begin genblk1[3] $end
$scope begin genblk2[0] $end
$scope module u_spsram $end
$var wire 4 F i_addr [3:0] $end
$var wire 1 G i_cen $end
$var wire 1 # i_clk $end
$var wire 32 H i_data [31:0] $end
$var wire 1 % i_oen $end
$var wire 1 & i_wen $end
$var reg 32 I o_data [31:0] $end
$upscope $end
$upscope $end
$scope begin genblk2[1] $end
$scope module u_spsram $end
$var wire 4 J i_addr [3:0] $end
$var wire 1 K i_cen $end
$var wire 1 # i_clk $end
$var wire 32 L i_data [31:0] $end
$var wire 1 % i_oen $end
$var wire 1 & i_wen $end
$var reg 32 M o_data [31:0] $end
$upscope $end
$upscope $end
$upscope $end
$upscope $end
$scope task init $end
$upscope $end
$scope task memRD $end
$var reg 6 N ti_addr [5:0] $end
$upscope $end
$scope task memWR $end
$var reg 6 O ti_addr [5:0] $end
$var reg 64 P ti_data [63:0] $end
$upscope $end
$upscope $end
$enddefinitions $end
#0
$dumpvars
bx P
bx O
bx N
bx M
b0 L
0K
b0 J
bx I
b0 H
0G
b0 F
bx E
b0 D
0C
b0 B
bx A
b0 @
0?
b0 >
bx =
b0 <
0;
b0 :
bx 9
b0 8
07
b0 6
bx 5
b0 4
13
b0 2
bx 1
b0 0
1/
b0 .
b1 -
bx ,
b0 +
b0 *
bx )
b1011100010111101110110011000110110010000101111011100110111001001100001011011010101111101100101011110000111010001100101011011100111001101101001011011110110111000101110011101100110001101100100 (
b1010011010101000100000101001110010001000100001001011001 '
0&
0%
b0 $
0#
b0 "
bx !
$end
#5
bz 1
bz !
bz ,
bz 5
bz 9
bz =
bz A
bz E
bz I
bz M
1#
#10
b10101110101001001011111010000110011000001011000 '
1&
0#
b1 O
b1 P
b1 )
#15
1#
#20
b1 .
b1 2
b1 6
b1 :
b1 >
b1 B
b1 F
b1 J
b1 0
b1 8
b1 @
b1 H
b10 O
b10 P
b10 )
b1 "
b1 *
b1 $
b1 +
0#
#25
1#
#30
b10 .
b10 2
b10 6
b10 :
b10 >
b10 B
b10 F
b10 J
b10 0
b10 8
b10 @
b10 H
b11 O
b11 P
b11 )
b10 "
b10 *
b10 $
b10 +
0#
#35
1#
#40
b11 .
b11 2
b11 6
b11 :
b11 >
b11 B
b11 F
b11 J
b11 0
b11 8
b11 @
b11 H
b100 O
b100 P
b100 )
b11 "
b11 *
b11 $
b11 +
0#
#45
1#
#50
b100 .
b100 2
b100 6
b100 :
b100 >
b100 B
b100 F
b100 J
b100 0
b100 8
b100 @
b100 H
b101 O
b101 P
b101 )
b100 "
b100 *
b100 $
b100 +
0#
#55
1#
#60
b101 .
b101 2
b101 6
b101 :
b101 >
b101 B
b101 F
b101 J
b101 0
b101 8
b101 @
b101 H
b110 O
b110 P
b110 )
b101 "
b101 *
b101 $
b101 +
0#
#65
1#
#70
b110 .
b110 2
b110 6
b110 :
b110 >
b110 B
b110 F
b110 J
b110 0
b110 8
b110 @
b110 H
b111 O
b111 P
b111 )
b110 "
b110 *
b110 $
b110 +
0#
#75
1#
#80
b111 .
b111 2
b111 6
b111 :
b111 >
b111 B
b111 F
b111 J
b111 0
b111 8
b111 @
b111 H
b1000 O
b1000 P
b1000 )
b111 "
b111 *
b111 $
b111 +
0#
#85
1#
#90
b1000 .
b1000 2
b1000 6
b1000 :
b1000 >
b1000 B
b1000 F
b1000 J
b1000 0
b1000 8
b1000 @
b1000 H
b1001 O
b1001 P
b1001 )
b1000 "
b1000 *
b1000 $
b1000 +
0#
#95
1#
#100
b1001 .
b1001 2
b1001 6
b1001 :
b1001 >
b1001 B
b1001 F
b1001 J
b1001 0
b1001 8
b1001 @
b1001 H
b1010 O
b1010 P
b1010 )
b1001 "
b1001 *
b1001 $
b1001 +
0#
#105
1#
#110
b1010 .
b1010 2
b1010 6
b1010 :
b1010 >
b1010 B
b1010 F
b1010 J
b1010 0
b1010 8
b1010 @
b1010 H
b1011 O
b1011 P
b1011 )
b1010 "
b1010 *
b1010 $
b1010 +
0#
#115
1#
#120
b1011 .
b1011 2
b1011 6
b1011 :
b1011 >
b1011 B
b1011 F
b1011 J
b1011 0
b1011 8
b1011 @
b1011 H
b1100 O
b1100 P
b1100 )
b1011 "
b1011 *
b1011 $
b1011 +
0#
#125
1#
#130
b1100 .
b1100 2
b1100 6
b1100 :
b1100 >
b1100 B
b1100 F
b1100 J
b1100 0
b1100 8
b1100 @
b1100 H
b1101 O
b1101 P
b1101 )
b1100 "
b1100 *
b1100 $
b1100 +
0#
#135
1#
#140
b1101 .
b1101 2
b1101 6
b1101 :
b1101 >
b1101 B
b1101 F
b1101 J
b1101 0
b1101 8
b1101 @
b1101 H
b1110 O
b1110 P
b1110 )
b1101 "
b1101 *
b1101 $
b1101 +
0#
#145
1#
#150
b1110 .
b1110 2
b1110 6
b1110 :
b1110 >
b1110 B
b1110 F
b1110 J
b1110 0
b1110 8
b1110 @
b1110 H
b1111 O
b1111 P
b1111 )
b1110 "
b1110 *
b1110 $
b1110 +
0#
#155
1#
#160
b1111 .
b1111 2
b1111 6
b1111 :
b1111 >
b1111 B
b1111 F
b1111 J
b1111 0
b1111 8
b1111 @
b1111 H
b10000 O
b10000 P
b10000 )
b1111 "
b1111 *
b1111 $
b1111 +
0#
#165
1#
#170
0/
03
17
1;
b10101110101001001011111010000110011000101011000 '
b10 -
b0 .
b0 2
b0 6
b0 :
b0 >
b0 B
b0 F
b0 J
b10000 0
b10000 8
b10000 @
b10000 H
b10001 O
b10001 P
b10001 )
b10000 "
b10000 *
b10000 $
b10000 +
0#
#175
1#
#180
b1 .
b1 2
b1 6
b1 :
b1 >
b1 B
b1 F
b1 J
b10001 0
b10001 8
b10001 @
b10001 H
b10010 O
b10010 P
b10010 )
b10001 "
b10001 *
b10001 $
b10001 +
0#
#185
1#
#190
b10 .
b10 2
b10 6
b10 :
b10 >
b10 B
b10 F
b10 J
b10010 0
b10010 8
b10010 @
b10010 H
b10011 O
b10011 P
b10011 )
b10010 "
b10010 *
b10010 $
b10010 +
0#
#195
1#
#200
b11 .
b11 2
b11 6
b11 :
b11 >
b11 B
b11 F
b11 J
b10011 0
b10011 8
b10011 @
b10011 H
b10100 O
b10100 P
b10100 )
b10011 "
b10011 *
b10011 $
b10011 +
0#
#205
1#
#210
b100 .
b100 2
b100 6
b100 :
b100 >
b100 B
b100 F
b100 J
b10100 0
b10100 8
b10100 @
b10100 H
b10101 O
b10101 P
b10101 )
b10100 "
b10100 *
b10100 $
b10100 +
0#
#215
1#
#220
b101 .
b101 2
b101 6
b101 :
b101 >
b101 B
b101 F
b101 J
b10101 0
b10101 8
b10101 @
b10101 H
b10110 O
b10110 P
b10110 )
b10101 "
b10101 *
b10101 $
b10101 +
0#
#225
1#
#230
b110 .
b110 2
b110 6
b110 :
b110 >
b110 B
b110 F
b110 J
b10110 0
b10110 8
b10110 @
b10110 H
b10111 O
b10111 P
b10111 )
b10110 "
b10110 *
b10110 $
b10110 +
0#
#235
1#
#240
b111 .
b111 2
b111 6
b111 :
b111 >
b111 B
b111 F
b111 J
b10111 0
b10111 8
b10111 @
b10111 H
b11000 O
b11000 P
b11000 )
b10111 "
b10111 *
b10111 $
b10111 +
0#
#245
1#
#250
b1000 .
b1000 2
b1000 6
b1000 :
b1000 >
b1000 B
b1000 F
b1000 J
b11000 0
b11000 8
b11000 @
b11000 H
b11001 O
b11001 P
b11001 )
b11000 "
b11000 *
b11000 $
b11000 +
0#
#255
1#
#260
b1001 .
b1001 2
b1001 6
b1001 :
b1001 >
b1001 B
b1001 F
b1001 J
b11001 0
b11001 8
b11001 @
b11001 H
b11010 O
b11010 P
b11010 )
b11001 "
b11001 *
b11001 $
b11001 +
0#
#265
1#
#270
b1010 .
b1010 2
b1010 6
b1010 :
b1010 >
b1010 B
b1010 F
b1010 J
b11010 0
b11010 8
b11010 @
b11010 H
b11011 O
b11011 P
b11011 )
b11010 "
b11010 *
b11010 $
b11010 +
0#
#275
1#
#280
b1011 .
b1011 2
b1011 6
b1011 :
b1011 >
b1011 B
b1011 F
b1011 J
b11011 0
b11011 8
b11011 @
b11011 H
b11100 O
b11100 P
b11100 )
b11011 "
b11011 *
b11011 $
b11011 +
0#
#285
1#
#290
b1100 .
b1100 2
b1100 6
b1100 :
b1100 >
b1100 B
b1100 F
b1100 J
b11100 0
b11100 8
b11100 @
b11100 H
b11101 O
b11101 P
b11101 )
b11100 "
b11100 *
b11100 $
b11100 +
0#
#295
1#
#300
b1101 .
b1101 2
b1101 6
b1101 :
b1101 >
b1101 B
b1101 F
b1101 J
b11101 0
b11101 8
b11101 @
b11101 H
b11110 O
b11110 P
b11110 )
b11101 "
b11101 *
b11101 $
b11101 +
0#
#305
1#
#310
b1110 .
b1110 2
b1110 6
b1110 :
b1110 >
b1110 B
b1110 F
b1110 J
b11110 0
b11110 8
b11110 @
b11110 H
b11111 O
b11111 P
b11111 )
b11110 "
b11110 *
b11110 $
b11110 +
0#
#315
1#
#320
b1111 .
b1111 2
b1111 6
b1111 :
b1111 >
b1111 B
b1111 F
b1111 J
b11111 0
b11111 8
b11111 @
b11111 H
b100000 O
b100000 P
b100000 )
b11111 "
b11111 *
b11111 $
b11111 +
0#
#325
1#
#330
07
0;
1?
1C
b10101110101001001011111010000110011001001011000 '
b100 -
b0 .
b0 2
b0 6
b0 :
b0 >
b0 B
b0 F
b0 J
b100000 0
b100000 8
b100000 @
b100000 H
b100001 O
b100001 P
b100001 )
b100000 "
b100000 *
b100000 $
b100000 +
0#
#335
1#
#340
b1 .
b1 2
b1 6
b1 :
b1 >
b1 B
b1 F
b1 J
b100001 0
b100001 8
b100001 @
b100001 H
b100010 O
b100010 P
b100010 )
b100001 "
b100001 *
b100001 $
b100001 +
0#
#345
1#
#350
b10 .
b10 2
b10 6
b10 :
b10 >
b10 B
b10 F
b10 J
b100010 0
b100010 8
b100010 @
b100010 H
b100011 O
b100011 P
b100011 )
b100010 "
b100010 *
b100010 $
b100010 +
0#
#355
1#
#360
b11 .
b11 2
b11 6
b11 :
b11 >
b11 B
b11 F
b11 J
b100011 0
b100011 8
b100011 @
b100011 H
b100100 O
b100100 P
b100100 )
b100011 "
b100011 *
b100011 $
b100011 +
0#
#365
1#
#370
b100 .
b100 2
b100 6
b100 :
b100 >
b100 B
b100 F
b100 J
b100100 0
b100100 8
b100100 @
b100100 H
b100101 O
b100101 P
b100101 )
b100100 "
b100100 *
b100100 $
b100100 +
0#
#375
1#
#380
b101 .
b101 2
b101 6
b101 :
b101 >
b101 B
b101 F
b101 J
b100101 0
b100101 8
b100101 @
b100101 H
b100110 O
b100110 P
b100110 )
b100101 "
b100101 *
b100101 $
b100101 +
0#
#385
1#
#390
b110 .
b110 2
b110 6
b110 :
b110 >
b110 B
b110 F
b110 J
b100110 0
b100110 8
b100110 @
b100110 H
b100111 O
b100111 P
b100111 )
b100110 "
b100110 *
b100110 $
b100110 +
0#
#395
1#
#400
b111 .
b111 2
b111 6
b111 :
b111 >
b111 B
b111 F
b111 J
b100111 0
b100111 8
b100111 @
b100111 H
b101000 O
b101000 P
b101000 )
b100111 "
b100111 *
b100111 $
b100111 +
0#
#405
1#
#410
b1000 .
b1000 2
b1000 6
b1000 :
b1000 >
b1000 B
b1000 F
b1000 J
b101000 0
b101000 8
b101000 @
b101000 H
b101001 O
b101001 P
b101001 )
b101000 "
b101000 *
b101000 $
b101000 +
0#
#415
1#
#420
b1001 .
b1001 2
b1001 6
b1001 :
b1001 >
b1001 B
b1001 F
b1001 J
b101001 0
b101001 8
b101001 @
b101001 H
b101010 O
b101010 P
b101010 )
b101001 "
b101001 *
b101001 $
b101001 +
0#
#425
1#
#430
b1010 .
b1010 2
b1010 6
b1010 :
b1010 >
b1010 B
b1010 F
b1010 J
b101010 0
b101010 8
b101010 @
b101010 H
b101011 O
b101011 P
b101011 )
b101010 "
b101010 *
b101010 $
b101010 +
0#
#435
1#
#440
b1011 .
b1011 2
b1011 6
b1011 :
b1011 >
b1011 B
b1011 F
b1011 J
b101011 0
b101011 8
b101011 @
b101011 H
b101100 O
b101100 P
b101100 )
b101011 "
b101011 *
b101011 $
b101011 +
0#
#445
1#
#450
b1100 .
b1100 2
b1100 6
b1100 :
b1100 >
b1100 B
b1100 F
b1100 J
b101100 0
b101100 8
b101100 @
b101100 H
b101101 O
b101101 P
b101101 )
b101100 "
b101100 *
b101100 $
b101100 +
0#
#455
1#
#460
b1101 .
b1101 2
b1101 6
b1101 :
b1101 >
b1101 B
b1101 F
b1101 J
b101101 0
b101101 8
b101101 @
b101101 H
b101110 O
b101110 P
b101110 )
b101101 "
b101101 *
b101101 $
b101101 +
0#
#465
1#
#470
b1110 .
b1110 2
b1110 6
b1110 :
b1110 >
b1110 B
b1110 F
b1110 J
b101110 0
b101110 8
b101110 @
b101110 H
b101111 O
b101111 P
b101111 )
b101110 "
b101110 *
b101110 $
b101110 +
0#
#475
1#
#480
b1111 .
b1111 2
b1111 6
b1111 :
b1111 >
b1111 B
b1111 F
b1111 J
b101111 0
b101111 8
b101111 @
b101111 H
b110000 O
b110000 P
b110000 )
b101111 "
b101111 *
b101111 $
b101111 +
0#
#485
1#
#490
0?
0C
1G
1K
b10101110101001001011111010000110011001101011000 '
b1000 -
b0 .
b0 2
b0 6
b0 :
b0 >
b0 B
b0 F
b0 J
b110000 0
b110000 8
b110000 @
b110000 H
b110001 O
b110001 P
b110001 )
b110000 "
b110000 *
b110000 $
b110000 +
0#
#495
1#
#500
b1 .
b1 2
b1 6
b1 :
b1 >
b1 B
b1 F
b1 J
b110001 0
b110001 8
b110001 @
b110001 H
b110010 O
b110010 P
b110010 )
b110001 "
b110001 *
b110001 $
b110001 +
0#
#505
1#
#510
b10 .
b10 2
b10 6
b10 :
b10 >
b10 B
b10 F
b10 J
b110010 0
b110010 8
b110010 @
b110010 H
b110011 O
b110011 P
b110011 )
b110010 "
b110010 *
b110010 $
b110010 +
0#
#515
1#
#520
b11 .
b11 2
b11 6
b11 :
b11 >
b11 B
b11 F
b11 J
b110011 0
b110011 8
b110011 @
b110011 H
b110100 O
b110100 P
b110100 )
b110011 "
b110011 *
b110011 $
b110011 +
0#
#525
1#
#530
b100 .
b100 2
b100 6
b100 :
b100 >
b100 B
b100 F
b100 J
b110100 0
b110100 8
b110100 @
b110100 H
b110101 O
b110101 P
b110101 )
b110100 "
b110100 *
b110100 $
b110100 +
0#
#535
1#
#540
b101 .
b101 2
b101 6
b101 :
b101 >
b101 B
b101 F
b101 J
b110101 0
b110101 8
b110101 @
b110101 H
b110110 O
b110110 P
b110110 )
b110101 "
b110101 *
b110101 $
b110101 +
0#
#545
1#
#550
b110 .
b110 2
b110 6
b110 :
b110 >
b110 B
b110 F
b110 J
b110110 0
b110110 8
b110110 @
b110110 H
b110111 O
b110111 P
b110111 )
b110110 "
b110110 *
b110110 $
b110110 +
0#
#555
1#
#560
b111 .
b111 2
b111 6
b111 :
b111 >
b111 B
b111 F
b111 J
b110111 0
b110111 8
b110111 @
b110111 H
b111000 O
b111000 P
b111000 )
b110111 "
b110111 *
b110111 $
b110111 +
0#
#565
1#
#570
b1000 .
b1000 2
b1000 6
b1000 :
b1000 >
b1000 B
b1000 F
b1000 J
b111000 0
b111000 8
b111000 @
b111000 H
b111001 O
b111001 P
b111001 )
b111000 "
b111000 *
b111000 $
b111000 +
0#
#575
1#
#580
b1001 .
b1001 2
b1001 6
b1001 :
b1001 >
b1001 B
b1001 F
b1001 J
b111001 0
b111001 8
b111001 @
b111001 H
b111010 O
b111010 P
b111010 )
b111001 "
b111001 *
b111001 $
b111001 +
0#
#585
1#
#590
b1010 .
b1010 2
b1010 6
b1010 :
b1010 >
b1010 B
b1010 F
b1010 J
b111010 0
b111010 8
b111010 @
b111010 H
b111011 O
b111011 P
b111011 )
b111010 "
b111010 *
b111010 $
b111010 +
0#
#595
1#
#600
b1011 .
b1011 2
b1011 6
b1011 :
b1011 >
b1011 B
b1011 F
b1011 J
b111011 0
b111011 8
b111011 @
b111011 H
b111100 O
b111100 P
b111100 )
b111011 "
b111011 *
b111011 $
b111011 +
0#
#605
1#
#610
b1100 .
b1100 2
b1100 6
b1100 :
b1100 >
b1100 B
b1100 F
b1100 J
b111100 0
b111100 8
b111100 @
b111100 H
b111101 O
b111101 P
b111101 )
b111100 "
b111100 *
b111100 $
b111100 +
0#
#615
1#
#620
b1101 .
b1101 2
b1101 6
b1101 :
b1101 >
b1101 B
b1101 F
b1101 J
b111101 0
b111101 8
b111101 @
b111101 H
b111110 O
b111110 P
b111110 )
b111101 "
b111101 *
b111101 $
b111101 +
0#
#625
1#
#630
b1110 .
b1110 2
b1110 6
b1110 :
b1110 >
b1110 B
b1110 F
b1110 J
b111110 0
b111110 8
b111110 @
b111110 H
b111111 O
b111111 P
b111111 )
b111110 "
b111110 *
b111110 $
b111110 +
0#
#635
1#
#640
b1111 .
b1111 2
b1111 6
b1111 :
b1111 >
b1111 B
b1111 F
b1111 J
b111111 0
b111111 8
b111111 @
b111111 H
b0 N
b0 )
b111111 "
b111111 *
b111111 $
b111111 +
0#
#645
1#
#650
1/
13
0G
0K
b10100100100010001011111010000110011000001011000 '
b1 -
b0 .
b0 2
b0 6
b0 :
b0 >
b0 B
b0 F
b0 J
b1 N
b1 )
1%
0&
b0 "
b0 *
0#
#655
b0 5
b0 !
b0 ,
b0 1
1#
#660
b1 .
b1 2
b1 6
b1 :
b1 >
b1 B
b1 F
b1 J
b10 N
b10 )
b1 "
b1 *
0#
#665
b1 !
b1 ,
b1 1
1#
#670
b10 .
b10 2
b10 6
b10 :
b10 >
b10 B
b10 F
b10 J
b11 N
b11 )
b10 "
b10 *
0#
#675
b10 !
b10 ,
b10 1
1#
#680
b11 .
b11 2
b11 6
b11 :
b11 >
b11 B
b11 F
b11 J
b100 N
b100 )
b11 "
b11 *
0#
#685
b11 !
b11 ,
b11 1
1#
#690
b100 .
b100 2
b100 6
b100 :
b100 >
b100 B
b100 F
b100 J
b101 N
b101 )
b100 "
b100 *
0#
#695
b100 !
b100 ,
b100 1
1#
#700
b101 .
b101 2
b101 6
b101 :
b101 >
b101 B
b101 F
b101 J
b110 N
b110 )
b101 "
b101 *
0#
#705
b101 !
b101 ,
b101 1
1#
#710
b110 .
b110 2
b110 6
b110 :
b110 >
b110 B
b110 F
b110 J
b111 N
b111 )
b110 "
b110 *
0#
#715
b110 !
b110 ,
b110 1
1#
#720
b111 .
b111 2
b111 6
b111 :
b111 >
b111 B
b111 F
b111 J
b1000 N
b1000 )
b111 "
b111 *
0#
#725
b111 !
b111 ,
b111 1
1#
#730
b1000 .
b1000 2
b1000 6
b1000 :
b1000 >
b1000 B
b1000 F
b1000 J
b1001 N
b1001 )
b1000 "
b1000 *
0#
#735
b1000 !
b1000 ,
b1000 1
1#
#740
b1001 .
b1001 2
b1001 6
b1001 :
b1001 >
b1001 B
b1001 F
b1001 J
b1010 N
b1010 )
b1001 "
b1001 *
0#
#745
b1001 !
b1001 ,
b1001 1
1#
#750
b1010 .
b1010 2
b1010 6
b1010 :
b1010 >
b1010 B
b1010 F
b1010 J
b1011 N
b1011 )
b1010 "
b1010 *
0#
#755
b1010 !
b1010 ,
b1010 1
1#
#760
b1011 .
b1011 2
b1011 6
b1011 :
b1011 >
b1011 B
b1011 F
b1011 J
b1100 N
b1100 )
b1011 "
b1011 *
0#
#765
b1011 !
b1011 ,
b1011 1
1#
#770
b1100 .
b1100 2
b1100 6
b1100 :
b1100 >
b1100 B
b1100 F
b1100 J
b1101 N
b1101 )
b1100 "
b1100 *
0#
#775
b1100 !
b1100 ,
b1100 1
1#
#780
b1101 .
b1101 2
b1101 6
b1101 :
b1101 >
b1101 B
b1101 F
b1101 J
b1110 N
b1110 )
b1101 "
b1101 *
0#
#785
b1101 !
b1101 ,
b1101 1
1#
#790
b1110 .
b1110 2
b1110 6
b1110 :
b1110 >
b1110 B
b1110 F
b1110 J
b1111 N
b1111 )
b1110 "
b1110 *
0#
#795
b1110 !
b1110 ,
b1110 1
1#
#800
b1111 .
b1111 2
b1111 6
b1111 :
b1111 >
b1111 B
b1111 F
b1111 J
b10000 N
b10000 )
b1111 "
b1111 *
0#
#805
b1111 !
b1111 ,
b1111 1
1#
#810
0/
03
17
1;
b10100100100010001011111010000110011000101011000 '
b10 -
b0 .
b0 2
b0 6
b0 :
b0 >
b0 B
b0 F
b0 J
b10001 N
b10001 )
b10000 "
b10000 *
0#
#815
b0 =
b10000 9
bz 5
b10000 !
b10000 ,
bz 1
1#
#820
b1 .
b1 2
b1 6
b1 :
b1 >
b1 B
b1 F
b1 J
b10010 N
b10010 )
b10001 "
b10001 *
0#
#825
b10001 !
b10001 ,
b10001 9
1#
#830
b10 .
b10 2
b10 6
b10 :
b10 >
b10 B
b10 F
b10 J
b10011 N
b10011 )
b10010 "
b10010 *
0#
#835
b10010 !
b10010 ,
b10010 9
1#
#840
b11 .
b11 2
b11 6
b11 :
b11 >
b11 B
b11 F
b11 J
b10100 N
b10100 )
b10011 "
b10011 *
0#
#845
b10011 !
b10011 ,
b10011 9
1#
#850
b100 .
b100 2
b100 6
b100 :
b100 >
b100 B
b100 F
b100 J
b10101 N
b10101 )
b10100 "
b10100 *
0#
#855
b10100 !
b10100 ,
b10100 9
1#
#860
b101 .
b101 2
b101 6
b101 :
b101 >
b101 B
b101 F
b101 J
b10110 N
b10110 )
b10101 "
b10101 *
0#
#865
b10101 !
b10101 ,
b10101 9
1#
#870
b110 .
b110 2
b110 6
b110 :
b110 >
b110 B
b110 F
b110 J
b10111 N
b10111 )
b10110 "
b10110 *
0#
#875
b10110 !
b10110 ,
b10110 9
1#
#880
b111 .
b111 2
b111 6
b111 :
b111 >
b111 B
b111 F
b111 J
b11000 N
b11000 )
b10111 "
b10111 *
0#
#885
b10111 !
b10111 ,
b10111 9
1#
