06_sram_extension/spsram.v
module spsram
#(
	parameter BW_DATA = 32,
	parameter BW_ADDR = 8
)(
	output		[BW_DATA-1:0]	o_data,
	input		[BW_DATA-1:0]	i_data,
	input		[BW_ADDR-1:0]	i_addr,
	input						i_wen,
	input						i_cen,
	input						i_oen,
	input						i_clk
);

	reg		[BW_DATA-1:0]	mem[0:2**BW_ADDR-1];
	always @(posedge i_clk) begin
		if (i_cen && i_wen) begin
			mem[i_addr]	<= i_data;
		end
		else begin
			mem[i_addr]	<= mem[i_addr];
		end
	end	

	`ifdef	SPSRAM_ASYNC
		assign o_data	=	!i_oen			 ? 'bz :
							i_cen &&  !i_wen ? mem[i_addr] : 'bz;
	`else
		reg		[BW_DATA-1:0] o_data;
		always @(posedge i_clk) begin
			if (i_oen) begin
				if (i_cen && !i_wen) begin
					o_data	<= mem[i_addr];
				end	
				else begin
					o_data <= 'bz;
				end	
			end 
			else begin
				o_data	<= 'bz;
			end	
		end	
	`endif
endmodule

06_sram_extension/sram_extension.v
`include "spsram.v"

module sram_extension
(
	output		[63:0]	o_data,
	input		[63:0]	i_data,
	input		[5:0]	i_addr,
	input				i_wen,
	input				i_oen,
	input				i_clk
);

	wire		[31:0]	w_o_data[1:0];
	wire		[31:0]	w_i_data[1:0];
	reg			[3:0]	cen;

	assign o_data 						= {w_o_data[1], w_o_data[0]};
	assign {w_i_data[1], w_i_data[0]}	= i_data;
	
	always @(*) begin
		case (i_addr[5:4])
			2'b00 : cen = 4'b0001;
			2'b01 : cen = 4'b0010;
			2'b10 : cen = 4'b0100;
			2'b11 : cen = 4'b1000;
		endcase
	end

	genvar i, j;
	generate 
		for (i=0; i<4; i=i+1) begin 	//  
			for (j=0; j<2; j=j+1) begin // j==0 : lower 32-bit, j==1 : upper 32-bit
				spsram
				#(
					.BW_DATA		(32           	),
					.BW_ADDR		(4            	)
				)
				u_spsram(
					.o_data			(w_o_data[j]	),
					.i_data			(w_i_data[j]	),
					.i_addr			(i_addr[3:0]  	),
					.i_wen			(i_wen&&cen[i]	),
					.i_cen			(cen[i]       	),
					.i_oen			(i_oen&&cen[i]	),
					.i_clk			(i_clk        	)
				);
			end
		end
	endgenerate

endmodule

06_sram_extension/sram_extension_tb.v
// --------------------------------------------------
//	Define Global Variables
// --------------------------------------------------
`define	CLKFREQ		100		// Clock Freq. (Unit: MHz)
`define	SIMCYCLE	64		// Sim. Cycles

// --------------------------------------------------
//	Includes
// --------------------------------------------------
`include	"sram_extension.v"

module sram_extension_tb;
// --------------------------------------------------
//	DUT Signals & Instantiate
// --------------------------------------------------

	wire	[63:0]	o_data;
	reg		[63:0]	i_data;
	reg		[5:0]	i_addr;
	reg				i_wen;
	reg				i_oen;
	reg				i_clk;

	sram_extension
	u_sram_extension(
		.o_data				(o_data				),
		.i_data				(i_data				),
		.i_addr				(i_addr				),
		.i_wen				(i_wen				),
		.i_oen				(i_oen				),
		.i_clk				(i_clk				)
	);

// --------------------------------------------------
//	Clock
// --------------------------------------------------
	always	#(500/`CLKFREQ)		i_clk = ~i_clk;

// --------------------------------------------------
//	Tasks
// --------------------------------------------------
	reg		[4*32-1:0]	taskState;

	task init;
		begin
			taskState		= "Init";
			i_data				= 0;
			i_addr				= 0;
			i_wen				= 0;
			i_oen				= 0;
			i_clk				= 0;
		end
	endtask

	task memWR;
		input [63:0]	ti_data;
		input [5:0]		ti_addr;
		begin
			@(negedge i_clk) begin
				i_data		= ti_data;
				i_addr		= ti_addr;
				i_wen		= 1;
				i_oen		= 0;
			end
		end
	endtask
	
	task memRD;
		input	[5:0]	ti_addr;
		begin
			@(negedge i_clk) begin
				i_addr		= ti_addr;
				i_wen		= 0;
				i_oen		= 1;
			end
		end
	endtask

// --------------------------------------------------
//	Test Stimulus
// --------------------------------------------------
	integer		i, j;
	initial begin
		init();
		#(1000/`CLKFREQ);
		for (i=0; i<`SIMCYCLE; i=i+1) begin
			memWR(i,i);
		end
		for (i=0; i<`SIMCYCLE; i=i+1) begin
			memRD(i);
		end
		#(1000/`CLKFREQ);
		i_oen = 0;
		for (i=0; i<20; i=i+1) begin
			#(1000/`CLKFREQ);
		end
		$finish;
	end
	
	always @(*) begin
		case ({i_wen, i_oen})
			2'b00 : taskState = "STANDBY";
			2'b01 : begin
				case (u_sram_extension.cen)
					4'b0001 : taskState = "RD_C0X";
					4'b0010 : taskState = "RD_C1X";
					4'b0100 : taskState = "RD_C2X";
					4'b1000 : taskState = "RD_C3X";
				endcase
			end
			2'b10 : begin
				case (u_sram_extension.cen)
					4'b0001 : taskState = "WR_C0X";
					4'b0010 : taskState = "WR_C1X";
					4'b0100 : taskState = "WR_C2X";
					4'b1000 : taskState = "WR_C3X";
				endcase
			end
			default : taskState = "NOT_ALLOWED";
		endcase
	end

// --------------------------------------------------
//	Dump VCD
// --------------------------------------------------
	reg	[8*32-1:0]	vcd_file;
	initial begin
		if ($value$plusargs("vcd_file=%s", vcd_file)) begin
			$dumpfile(vcd_file);
			$dumpvars;
		end else begin
			$dumpfile("sram_extension_tb.vcd");
			$dumpvars;
		end
	end

endmodule

06_sram_extension/vcd/sram_extension.vcd
$date
	Mon Jul  1 18:02:47 2024
$end
$version
	Icarus Verilog
$end
$timescale
	1s
$end
$scope module sram_extension_tb $end
$var wire 64 ! o_data [63:0] $end
$var reg 6 " i_addr [5:0] $end
$var reg 1 # i_clk $end
$var reg 64 $ i_data [63:0] $end
$var reg 1 % i_oen $end
$var reg 1 & i_wen $end
$var reg 128 ' taskState [127:0] $end
$var reg 256 ( vcd_file [255:0] $end
$var integer 32 ) i [31:0] $end
$scope module u_sram_extension $end
$var wire 6 * i_addr [5:0] $end
$var wire 1 # i_clk $end
$var wire 64 + i_data [63:0] $end
$var wire 1 % i_oen $end
$var wire 1 & i_wen $end
$var wire 64 , o_data [63:0] $end
$var reg 4 - cen [3:0] $end
$scope begin genblk1[0] $end
$scope begin genblk2[0] $end
$scope module u_spsram $end
$var wire 4 . i_addr [3:0] $end
$var wire 1 / i_cen $end
$var wire 1 # i_clk $end
$var wire 32 0 i_data [31:0] $end
$var wire 1 1 i_oen $end
$var wire 1 2 i_wen $end
$var reg 32 3 o_data [31:0] $end
$upscope $end
$upscope $end
$scope begin genblk2[1] $end
$scope module u_spsram $end
$var wire 4 4 i_addr [3:0] $end
$var wire 1 5 i_cen $end
$var wire 1 # i_clk $end
$var wire 32 6 i_data [31:0] $end
$var wire 1 7 i_oen $end
$var wire 1 8 i_wen $end
$var reg 32 9 o_data [31:0] $end
$upscope $end
$upscope $end
$upscope $end
$scope begin genblk1[1] $end
$scope begin genblk2[0] $end
$scope module u_spsram $end
$var wire 4 : i_addr [3:0] $end
$var wire 1 ; i_cen $end
$var wire 1 # i_clk $end
$var wire 32 < i_data [31:0] $end
$var wire 1 = i_oen $end
$var wire 1 > i_wen $end
$var reg 32 ? o_data [31:0] $end
$upscope $end
$upscope $end
$scope begin genblk2[1] $end
$scope module u_spsram $end
$var wire 4 @ i_addr [3:0] $end
$var wire 1 A i_cen $end
$var wire 1 # i_clk $end
$var wire 32 B i_data [31:0] $end
$var wire 1 C i_oen $end
$var wire 1 D i_wen $end
$var reg 32 E o_data [31:0] $end
$upscope $end
$upscope $end
$upscope $end
$scope begin genblk1[2] $end
$scope begin genblk2[0] $end
$scope module u_spsram $end
$var wire 4 F i_addr [3:0] $end
$var wire 1 G i_cen $end
$var wire 1 # i_clk $end
$var wire 32 H i_data [31:0] $end
$var wire 1 I i_oen $end
$var wire 1 J i_wen $end
$var reg 32 K o_data [31:0] $end
$upscope $end
$upscope $end
$scope begin genblk2[1] $end
$scope module u_spsram $end
$var wire 4 L i_addr [3:0] $end
$var wire 1 M i_cen $end
$var wire 1 # i_clk $end
$var wire 32 N i_data [31:0] $end
$var wire 1 O i_oen $end
$var wire 1 P i_wen $end
$var reg 32 Q o_data [31:0] $end
$upscope $end
$upscope $end
$upscope $end
$scope begin genblk1[3] $end
$scope begin genblk2[0] $end
$scope module u_spsram $end
$var wire 4 R i_addr [3:0] $end
$var wire 1 S i_cen $end
$var wire 1 # i_clk $end
$var wire 32 T i_data [31:0] $end
$var wire 1 U i_oen $end
$var wire 1 V i_wen $end
$var reg 32 W o_data [31:0] $end
$upscope $end
$upscope $end
$scope begin genblk2[1] $end
$scope module u_spsram $end
$var wire 4 X i_addr [3:0] $end
$var wire 1 Y i_cen $end
$var wire 1 # i_clk $end
$var wire 32 Z i_data [31:0] $end
$var wire 1 [ i_oen $end
$var wire 1 \ i_wen $end
$var reg 32 ] o_data [31:0] $end
$upscope $end
$upscope $end
$upscope $end
$upscope $end
$scope task init $end
$upscope $end
$scope task memRD $end
$var reg 6 ^ ti_addr [5:0] $end
$upscope $end
$scope task memWR $end
$var reg 6 _ ti_addr [5:0] $end
$var reg 64 ` ti_data [63:0] $end
$upscope $end
$upscope $end
$enddefinitions $end
#0
$dumpvars
bx `
bx _
bx ^
bx ]
0\
0[
b0 Z
0Y
b0 X
bx W
0V
0U
b0 T
0S
b0 R
bx Q
0P
0O
b0 N
0M
b0 L
bx K
0J
0I
b0 H
0G
b0 F
bx E
0D
0C
b0 B
0A
b0 @
bx ?
0>
0=
b0 <
0;
b0 :
bx 9
08
07
b0 6
15
b0 4
bx 3
02
01
b0 0
1/
b0 .
b1 -
bx ,
b0 +
b0 *
bx )
b1011100010111101110110011000110110010000101111011100110111001001100001011011010101111101100101011110000111010001100101011011100111001101101001011011110110111000101110011101100110001101100100 (
b1010011010101000100000101001110010001000100001001011001 '
0&
0%
b0 $
0#
b0 "
bx !
$end
#5
bz 3
bz !
bz ,
bz 9
bz ?
bz E
bz K
bz Q
bz W
bz ]
1#
#10
12
18
b10101110101001001011111010000110011000001011000 '
1&
0#
b1 _
b1 `
b1 )
#15
1#
#20
b1 .
b1 4
b1 :
b1 @
b1 F
b1 L
b1 R
b1 X
b1 0
b1 <
b1 H
b1 T
b10 _
b10 `
b10 )
b1 "
b1 *
b1 $
b1 +
0#
#25
1#
#30
b10 .
b10 4
b10 :
b10 @
b10 F
b10 L
b10 R
b10 X
b10 0
b10 <
b10 H
b10 T
b11 _
b11 `
b11 )
b10 "
b10 *
b10 $
b10 +
0#
#35
1#
#40
b11 .
b11 4
b11 :
b11 @
b11 F
b11 L
b11 R
b11 X
b11 0
b11 <
b11 H
b11 T
b100 _
b100 `
b100 )
b11 "
b11 *
b11 $
b11 +
0#
#45
1#
#50
b100 .
b100 4
b100 :
b100 @
b100 F
b100 L
b100 R
b100 X
b100 0
b100 <
b100 H
b100 T
b101 _
b101 `
b101 )
b100 "
b100 *
b100 $
b100 +
0#
#55
1#
#60
b101 .
b101 4
b101 :
b101 @
b101 F
b101 L
b101 R
b101 X
b101 0
b101 <
b101 H
b101 T
b110 _
b110 `
b110 )
b101 "
b101 *
b101 $
b101 +
0#
#65
1#
#70
b110 .
b110 4
b110 :
b110 @
b110 F
b110 L
b110 R
b110 X
b110 0
b110 <
b110 H
b110 T
b111 _
b111 `
b111 )
b110 "
b110 *
b110 $
b110 +
0#
#75
1#
#80
b111 .
b111 4
b111 :
b111 @
b111 F
b111 L
b111 R
b111 X
b111 0
b111 <
b111 H
b111 T
b1000 _
b1000 `
b1000 )
b111 "
b111 *
b111 $
b111 +
0#
#85
1#
#90
b1000 .
b1000 4
b1000 :
b1000 @
b1000 F
b1000 L
b1000 R
b1000 X
b1000 0
b1000 <
b1000 H
b1000 T
b1001 _
b1001 `
b1001 )
b1000 "
b1000 *
b1000 $
b1000 +
0#
#95
1#
#100
b1001 .
b1001 4
b1001 :
b1001 @
b1001 F
b1001 L
b1001 R
b1001 X
b1001 0
b1001 <
b1001 H
b1001 T
b1010 _
b1010 `
b1010 )
b1001 "
b1001 *
b1001 $
b1001 +
0#
#105
1#
#110
b1010 .
b1010 4
b1010 :
b1010 @
b1010 F
b1010 L
b1010 R
b1010 X
b1010 0
b1010 <
b1010 H
b1010 T
b1011 _
b1011 `
b1011 )
b1010 "
b1010 *
b1010 $
b1010 +
0#
#115
1#
#120
b1011 .
b1011 4
b1011 :
b1011 @
b1011 F
b1011 L
b1011 R
b1011 X
b1011 0
b1011 <
b1011 H
b1011 T
b1100 _
b1100 `
b1100 )
b1011 "
b1011 *
b1011 $
b1011 +
0#
#125
1#
#130
b1100 .
b1100 4
b1100 :
b1100 @
b1100 F
b1100 L
b1100 R
b1100 X
b1100 0
b1100 <
b1100 H
b1100 T
b1101 _
b1101 `
b1101 )
b1100 "
b1100 *
b1100 $
b1100 +
0#
#135
1#
#140
b1101 .
b1101 4
b1101 :
b1101 @
b1101 F
b1101 L
b1101 R
b1101 X
b1101 0
b1101 <
b1101 H
b1101 T
b1110 _
b1110 `
b1110 )
b1101 "
b1101 *
b1101 $
b1101 +
0#
#145
1#
#150
b1110 .
b1110 4
b1110 :
b1110 @
b1110 F
b1110 L
b1110 R
b1110 X
b1110 0
b1110 <
b1110 H
b1110 T
b1111 _
b1111 `
b1111 )
b1110 "
b1110 *
b1110 $
b1110 +
0#
#155
1#
#160
b1111 .
b1111 4
b1111 :
b1111 @
b1111 F
b1111 L
b1111 R
b1111 X
b1111 0
b1111 <
b1111 H
b1111 T
b10000 _
b10000 `
b10000 )
b1111 "
b1111 *
b1111 $
b1111 +
0#
#165
1#
#170
02
08
1>
1D
0/
05
1;
1A
b10101110101001001011111010000110011000101011000 '
b10 -
b0 .
b0 4
b0 :
b0 @
b0 F
b0 L
b0 R
b0 X
b10000 0
b10000 <
b10000 H
b10000 T
b10001 _
b10001 `
b10001 )
b10000 "
b10000 *
b10000 $
b10000 +
0#
#175
1#
#180
b1 .
b1 4
b1 :
b1 @
b1 F
b1 L
b1 R
b1 X
b10001 0
b10001 <
b10001 H
b10001 T
b10010 _
b10010 `
b10010 )
b10001 "
b10001 *
b10001 $
b10001 +
0#
#185
1#
#190
b10 .
b10 4
b10 :
b10 @
b10 F
b10 L
b10 R
b10 X
b10010 0
b10010 <
b10010 H
b10010 T
b10011 _
b10011 `
b10011 )
b10010 "
b10010 *
b10010 $
b10010 +
0#
#195
1#
#200
b11 .
b11 4
b11 :
b11 @
b11 F
b11 L
b11 R
b11 X
b10011 0
b10011 <
b10011 H
b10011 T
b10100 _
b10100 `
b10100 )
b10011 "
b10011 *
b10011 $
b10011 +
0#
#205
1#
#210
b100 .
b100 4
b100 :
b100 @
b100 F
b100 L
b100 R
b100 X
b10100 0
b10100 <
b10100 H
b10100 T
b10101 _
b10101 `
b10101 )
b10100 "
b10100 *
b10100 $
b10100 +
0#
#215
1#
#220
b101 .
b101 4
b101 :
b101 @
b101 F
b101 L
b101 R
b101 X
b10101 0
b10101 <
b10101 H
b10101 T
b10110 _
b10110 `
b10110 )
b10101 "
b10101 *
b10101 $
b10101 +
0#
#225
1#
#230
b110 .
b110 4
b110 :
b110 @
b110 F
b110 L
b110 R
b110 X
b10110 0
b10110 <
b10110 H
b10110 T
b10111 _
b10111 `
b10111 )
b10110 "
b10110 *
b10110 $
b10110 +
0#
#235
1#
#240
b111 .
b111 4
b111 :
b111 @
b111 F
b111 L
b111 R
b111 X
b10111 0
b10111 <
b10111 H
b10111 T
b11000 _
b11000 `
b11000 )
b10111 "
b10111 *
b10111 $
b10111 +
0#
#245
1#
#250
b1000 .
b1000 4
b1000 :
b1000 @
b1000 F
b1000 L
b1000 R
b1000 X
b11000 0
b11000 <
b11000 H
b11000 T
b11001 _
b11001 `
b11001 )
b11000 "
b11000 *
b11000 $
b11000 +
0#
#255
1#
#260
b1001 .
b1001 4
b1001 :
b1001 @
b1001 F
b1001 L
b1001 R
b1001 X
b11001 0
b11001 <
b11001 H
b11001 T
b11010 _
b11010 `
b11010 )
b11001 "
b11001 *
b11001 $
b11001 +
0#
#265
1#
#270
b1010 .
b1010 4
b1010 :
b1010 @
b1010 F
b1010 L
b1010 R
b1010 X
b11010 0
b11010 <
b11010 H
b11010 T
b11011 _
b11011 `
b11011 )
b11010 "
b11010 *
b11010 $
b11010 +
0#
#275
1#
#280
b1011 .
b1011 4
b1011 :
b1011 @
b1011 F
b1011 L
b1011 R
b1011 X
b11011 0
b11011 <
b11011 H
b11011 T
b11100 _
b11100 `
b11100 )
b11011 "
b11011 *
b11011 $
b11011 +
0#
#285
1#
#290
b1100 .
b1100 4
b1100 :
b1100 @
b1100 F
b1100 L
b1100 R
b1100 X
b11100 0
b11100 <
b11100 H
b11100 T
b11101 _
b11101 `
b11101 )
b11100 "
b11100 *
b11100 $
b11100 +
0#
#295
1#
#300
b1101 .
b1101 4
b1101 :
b1101 @
b1101 F
b1101 L
b1101 R
b1101 X
b11101 0
b11101 <
b11101 H
b11101 T
b11110 _
b11110 `
b11110 )
b11101 "
b11101 *
b11101 $
b11101 +
0#
#305
1#
#310
b1110 .
b1110 4
b1110 :
b1110 @
b1110 F
b1110 L
b1110 R
b1110 X
b11110 0
b11110 <
b11110 H
b11110 T
b11111 _
b11111 `
b11111 )
b11110 "
b11110 *
b11110 $
b11110 +
0#
#315
1#
#320
b1111 .
b1111 4
b1111 :
b1111 @
b1111 F
b1111 L
b1111 R
b1111 X
b11111 0
b11111 <
b11111 H
b11111 T
b100000 _
b100000 `
b100000 )
b11111 "
b11111 *
b11111 $
b11111 +
0#
#325
1#
#330
0>
0D
1J
1P
0;
0A
1G
1M
b10101110101001001011111010000110011001001011000 '
b100 -
b0 .
b0 4
b0 :
b0 @
b0 F
b0 L
b0 R
b0 X
b100000 0
b100000 <
b100000 H
b100000 T
b100001 _
b100001 `
b100001 )
b100000 "
b100000 *
b100000 $
b100000 +
0#
#335
1#
#340
b1 .
b1 4
b1 :
b1 @
b1 F
b1 L
b1 R
b1 X
b100001 0
b100001 <
b100001 H
b100001 T
b100010 _
b100010 `
b100010 )
b100001 "
b100001 *
b100001 $
b100001 +
0#
#345
1#
#350
b10 .
b10 4
b10 :
b10 @
b10 F
b10 L
b10 R
b10 X
b100010 0
b100010 <
b100010 H
b100010 T
b100011 _
b100011 `
b100011 )
b100010 "
b100010 *
b100010 $
b100010 +
0#
#355
1#
#360
b11 .
b11 4
b11 :
b11 @
b11 F
b11 L
b11 R
b11 X
b100011 0
b100011 <
b100011 H
b100011 T
b100100 _
b100100 `
b100100 )
b100011 "
b100011 *
b100011 $
b100011 +
0#
#365
1#
#370
b100 .
b100 4
b100 :
b100 @
b100 F
b100 L
b100 R
b100 X
b100100 0
b100100 <
b100100 H
b100100 T
b100101 _
b100101 `
b100101 )
b100100 "
b100100 *
b100100 $
b100100 +
0#
#375
1#
#380
b101 .
b101 4
b101 :
b101 @
b101 F
b101 L
b101 R
b101 X
b100101 0
b100101 <
b100101 H
b100101 T
b100110 _
b100110 `
b100110 )
b100101 "
b100101 *
b100101 $
b100101 +
0#
#385
1#
#390
b110 .
b110 4
b110 :
b110 @
b110 F
b110 L
b110 R
b110 X
b100110 0
b100110 <
b100110 H
b100110 T
b100111 _
b100111 `
b100111 )
b100110 "
b100110 *
b100110 $
b100110 +
0#
#395
1#
#400
b111 .
b111 4
b111 :
b111 @
b111 F
b111 L
b111 R
b111 X
b100111 0
b100111 <
b100111 H
b100111 T
b101000 _
b101000 `
b101000 )
b100111 "
b100111 *
b100111 $
b100111 +
0#
#405
1#
#410
b1000 .
b1000 4
b1000 :
b1000 @
b1000 F
b1000 L
b1000 R
b1000 X
b101000 0
b101000 <
b101000 H
b101000 T
b101001 _
b101001 `
b101001 )
b101000 "
b101000 *
b101000 $
b101000 +
0#
#415
1#
#420
b1001 .
b1001 4
b1001 :
b1001 @
b1001 F
b1001 L
b1001 R
b1001 X
b101001 0
b101001 <
b101001 H
b101001 T
b101010 _
b101010 `
b101010 )
b101001 "
b101001 *
b101001 $
b101001 +
0#
#425
1#
#430
b1010 .
b1010 4
b1010 :
b1010 @
b1010 F
b1010 L
b1010 R
b1010 X
b101010 0
b101010 <
b101010 H
b101010 T
b101011 _
b101011 `
b101011 )
b101010 "
b101010 *
b101010 $
b101010 +
0#
#435
1#
#440
b1011 .
b1011 4
b1011 :
b1011 @
b1011 F
b1011 L
b1011 R
b1011 X
b101011 0
b101011 <
b101011 H
b101011 T
b101100 _
b101100 `
b101100 )
b101011 "
b101011 *
b101011 $
b101011 +
0#
#445
1#
#450
b1100 .
b1100 4
b1100 :
b1100 @
b1100 F
b1100 L
b1100 R
b1100 X
b101100 0
b101100 <
b101100 H
b101100 T
b101101 _
b101101 `
b101101 )
b101100 "
b101100 *
b101100 $
b101100 +
0#
#455
1#
#460
b1101 .
b1101 4
b1101 :
b1101 @
b1101 F
b1101 L
b1101 R
b1101 X
b101101 0
b101101 <
b101101 H
b101101 T
b101110 _
b101110 `
b101110 )
b101101 "
b101101 *
b101101 $
b101101 +
0#
#465
1#
#470
b1110 .
b1110 4
b1110 :
b1110 @
b1110 F
b1110 L
b1110 R
b1110 X
b101110 0
b101110 <
b101110 H
b101110 T
b101111 _
b101111 `
b101111 )
b101110 "
b101110 *
b101110 $
b101110 +
0#
#475
1#
#480
b1111 .
b1111 4
b1111 :
b1111 @
b1111 F
b1111 L
b1111 R
b1111 X
b101111 0
b101111 <
b101111 H
b101111 T
b110000 _
b110000 `
b110000 )
b101111 "
b101111 *
b101111 $
b101111 +
0#
#485
1#
#490
0J
0P
1V
1\
0G
0M
1S
1Y
b10101110101001001011111010000110011001101011000 '
b1000 -
b0 .
b0 4
b0 :
b0 @
b0 F
b0 L
b0 R
b0 X
b110000 0
b110000 <
b110000 H
b110000 T
b110001 _
b110001 `
b110001 )
b110000 "
b110000 *
b110000 $
b110000 +
0#
#495
1#
#500
b1 .
b1 4
b1 :
b1 @
b1 F
b1 L
b1 R
b1 X
b110001 0
b110001 <
b110001 H
b110001 T
b110010 _
b110010 `
b110010 )
b110001 "
b110001 *
b110001 $
b110001 +
0#
#505
1#
#510
b10 .
b10 4
b10 :
b10 @
b10 F
b10 L
b10 R
b10 X
b110010 0
b110010 <
b110010 H
b110010 T
b110011 _
b110011 `
b110011 )
b110010 "
b110010 *
b110010 $
b110010 +
0#
#515
1#
#520
b11 .
b11 4
b11 :
b11 @
b11 F
b11 L
b11 R
b11 X
b110011 0
b110011 <
b110011 H
b110011 T
b110100 _
b110100 `
b110100 )
b110011 "
b110011 *
b110011 $
b110011 +
0#
#525
1#
#530
b100 .
b100 4
b100 :
b100 @
b100 F
b100 L
b100 R
b100 X
b110100 0
b110100 <
b110100 H
b110100 T
b110101 _
b110101 `
b110101 )
b110100 "
b110100 *
b110100 $
b110100 +
0#
#535
1#
#540
b101 .
b101 4
b101 :
b101 @
b101 F
b101 L
b101 R
b101 X
b110101 0
b110101 <
b110101 H
b110101 T
b110110 _
b110110 `
b110110 )
b110101 "
b110101 *
b110101 $
b110101 +
0#
#545
1#
#550
b110 .
b110 4
b110 :
b110 @
b110 F
b110 L
b110 R
b110 X
b110110 0
b110110 <
b110110 H
b110110 T
b110111 _
b110111 `
b110111 )
b110110 "
b110110 *
b110110 $
b110110 +
0#
#555
1#
#560
b111 .
b111 4
b111 :
b111 @
b111 F
b111 L
b111 R
b111 X
b110111 0
b110111 <
b110111 H
b110111 T
b111000 _
b111000 `
b111000 )
b110111 "
b110111 *
b110111 $
b110111 +
0#
#565
1#
#570
b1000 .
b1000 4
b1000 :
b1000 @
b1000 F
b1000 L
b1000 R
b1000 X
b111000 0
b111000 <
b111000 H
b111000 T
b111001 _
b111001 `
b111001 )
b111000 "
b111000 *
b111000 $
b111000 +
0#
#575
1#
#580
b1001 .
b1001 4
b1001 :
b1001 @
b1001 F
b1001 L
b1001 R
b1001 X
b111001 0
b111001 <
b111001 H
b111001 T
b111010 _
b111010 `
b111010 )
b111001 "
b111001 *
b111001 $
b111001 +
0#
#585
1#
#590
b1010 .
b1010 4
b1010 :
b1010 @
b1010 F
b1010 L
b1010 R
b1010 X
b111010 0
b111010 <
b111010 H
b111010 T
b111011 _
b111011 `
b111011 )
b111010 "
b111010 *
b111010 $
b111010 +
0#
#595
1#
#600
b1011 .
b1011 4
b1011 :
b1011 @
b1011 F
b1011 L
b1011 R
b1011 X
b111011 0
b111011 <
b111011 H
b111011 T
b111100 _
b111100 `
b111100 )
b111011 "
b111011 *
b111011 $
b111011 +
0#
#605
1#
#610
b1100 .
b1100 4
b1100 :
b1100 @
b1100 F
b1100 L
b1100 R
b1100 X
b111100 0
b111100 <
b111100 H
b111100 T
b111101 _
b111101 `
b111101 )
b111100 "
b111100 *
b111100 $
b111100 +
0#
#615
1#
#620
b1101 .
b1101 4
b1101 :
b1101 @
b1101 F
b1101 L
b1101 R
b1101 X
b111101 0
b111101 <
b111101 H
b111101 T
b111110 _
b111110 `
b111110 )
b111101 "
b111101 *
b111101 $
b111101 +
0#
#625
1#
#630
b1110 .
b1110 4
b1110 :
b1110 @
b1110 F
b1110 L
b1110 R
b1110 X
b111110 0
b111110 <
b111110 H
b111110 T
b111111 _
b111111 `
b111111 )
b111110 "
b111110 *
b111110 $
b111110 +
0#
#635
1#
#640
b1111 .
b1111 4
b1111 :
b1111 @
b1111 F
b1111 L
b1111 R
b1111 X
b111111 0
b111111 <
b111111 H
b111111 T
b0 ^
b0 )
b111111 "
b111111 *
b111111 $
b111111 +
0#
#645
1#
#650
11
17
1/
15
0S
0Y
0U
0[
0V
0\
b10100100100010001011111010000110011000001011000 '
b1 -
b0 .
b0 4
b0 :
b0 @
b0 F
b0 L
b0 R
b0 X
b1 ^
b1 )
1%
0&
b0 "
b0 *
0#
#655
b0 9
b0 !
b0 ,
b0 3
1#
#660
b1 .
b1 4
b1 :
b1 @
b1 F
b1 L
b1 R
b1 X
b10 ^
b10 )
b1 "
b1 *
0#
#665
b1 !
b1 ,
b1 3
1#
#670
b10 .
b10 4
b10 :
b10 @
b10 F
b10 L
b10 R
b10 X
b11 ^
b11 )
b10 "
b10 *
0#
#675
b10 !
b10 ,
b10 3
1#
#680
b11 .
b11 4
b11 :
b11 @
b11 F
b11 L
b11 R
b11 X
b100 ^
b100 )
b11 "
b11 *
0#
#685
b11 !
b11 ,
b11 3
1#
#690
b100 .
b100 4
b100 :
b100 @
b100 F
b100 L
b100 R
b100 X
b101 ^
b101 )
b100 "
b100 *
0#
#695
b100 !
b100 ,
b100 3
1#
#700
b101 .
b101 4
b101 :
b101 @
b101 F
b101 L
b101 R
b101 X
b110 ^
b110 )
b101 "
b101 *
0#
#705
b101 !
b101 ,
b101 3
1#
#710
b110 .
b110 4
b110 :
b110 @
b110 F
b110 L
b110 R
b110 X
b111 ^
b111 )
b110 "
b110 *
0#
#715
b110 !
b110 ,
b110 3
1#
#720
b111 .
b111 4
b111 :
b111 @
b111 F
b111 L
b111 R
b111 X
b1000 ^
b1000 )
b111 "
b111 *
0#
#725
b111 !
b111 ,
b111 3
1#
#730
b1000 .
b1000 4
b1000 :
b1000 @
b1000 F
b1000 L
b1000 R
b1000 X
b1001 ^
b1001 )
b1000 "
b1000 *
0#
#735
b1000 !
b1000 ,
b1000 3
1#
#740
b1001 .
b1001 4
b1001 :
b1001 @
b1001 F
b1001 L
b1001 R
b1001 X
b1010 ^
b1010 )
b1001 "
b1001 *
0#
#745
b1001 !
b1001 ,
b1001 3
1#
#750
b1010 .
b1010 4
b1010 :
b1010 @
b1010 F
b1010 L
b1010 R
b1010 X
b1011 ^
b1011 )
b1010 "
b1010 *
0#
#755
b1010 !
b1010 ,
b1010 3
1#
#760
b1011 .
b1011 4
b1011 :
b1011 @
b1011 F
b1011 L
b1011 R
b1011 X
b1100 ^
b1100 )
b1011 "
b1011 *
0#
#765
b1011 !
b1011 ,
b1011 3
1#
#770
b1100 .
b1100 4
b1100 :
b1100 @
b1100 F
b1100 L
b1100 R
b1100 X
b1101 ^
b1101 )
b1100 "
b1100 *
0#
#775
b1100 !
b1100 ,
b1100 3
1#
#780
b1101 .
b1101 4
b1101 :
b1101 @
b1101 F
b1101 L
b1101 R
b1101 X
b1110 ^
b1110 )
b1101 "
b1101 *
0#
#785
b1101 !
b1101 ,
b1101 3
1#
#790
b1110 .
b1110 4
b1110 :
b1110 @
b1110 F
b1110 L
b1110 R
b1110 X
b1111 ^
b1111 )
b1110 "
b1110 *
0#
#795
b1110 !
b1110 ,
b1110 3
1#
#800
b1111 .
b1111 4
b1111 :
b1111 @
b1111 F
b1111 L
b1111 R
b1111 X
b10000 ^
b10000 )
b1111 "
b1111 *
0#
#805
b1111 !
b1111 ,
b1111 3
1#
#810
01
07
1=
1C
0/
05
1;
1A
b10100100100010001011111010000110011000101011000 '
b10 -
b0 .
b0 4
b0 :
b0 @
b0 F
b0 L
b0 R
b0 X
b10001 ^
b10001 )
b10000 "
b10000 *
0#
#815
b0 E
b10000 ?
bz 9
b10000 !
b10000 ,
bz 3
1#
#820
b1 .
b1 4
b1 :
b1 @
b1 F
b1 L
b1 R
b1 X
b10010 ^
b10010 )
b10001 "
b10001 *
0#
#825
b10001 !
b10001 ,
b10001 ?
1#
#830
b10 .
b10 4
b10 :
b10 @
b10 F
b10 L
b10 R
b10 X
b10011 ^
b10011 )
b10010 "
b10010 *
0#
#835
b10010 !
b10010 ,
b10010 ?
1#
#840
b11 .
b11 4
b11 :
b11 @
b11 F
b11 L
b11 R
b11 X
b10100 ^
b10100 )
b10011 "
b10011 *
0#
#845
b10011 !
b10011 ,
b10011 ?
1#
#850
b100 .
b100 4
b100 :
b100 @
b100 F
b100 L
b100 R
b100 X
b10101 ^
b10101 )
b10100 "
b10100 *
0#
#855
b10100 !
b10100 ,
b10100 ?
1#
#860
b101 .
b101 4
b101 :
b101 @
b101 F
b101 L
b101 R
b101 X
b10110 ^
b10110 )
b10101 "
b10101 *
0#
#865
b10101 !
b10101 ,
b10101 ?
1#
